Workbook
Name \0: #REF!
Name \1: #REF!
Name \a: #REF!
Name \m: #REF!
Name ___sm2: #REF!
Name __SM1: #REF!
Name __SM10: #REF!
Name __SM11: #REF!
Name __SM12: #REF!
Name __sm13: #REF!
Name __SM2: #REF!
Name __SM3: #REF!
Name __SM4: #REF!
Name __SM5: #REF!
Name __SM6: #REF!
Name __SM7: #REF!
Name __SM8: #REF!
Name __SM9: #REF!
Name _l: #REF!
Name _SM1: #REF!
Name _SM10: #REF!
Name _SM11: #REF!
Name _SM12: #REF!
Name _sm13: #REF!
Name _SM2: #REF!
Name _SM3: #REF!
Name _SM4: #REF!
Name _SM5: #REF!
Name _SM6: #REF!
Name _SM7: #REF!
Name _SM8: #REF!
Name _SM9: #REF!
Name _sss: #REF!
Name a: #REF!
Name aaaa: #REF!
Name aaaaaaaaaaa: #REF!
Name AB: #REF!
Name ABREV_E: #REF!
Name Administração: #REF!
Name ALUMÍNIO_2: #REF!
Name ASASASAS: #REF!
Name b: #REF!
Name BDI: 1.43344312465585
Name Betune: #REF!
Name BOLETIM174: #REF!
Name COD_ELE: #REF!
Name comp2: #REF!
Name compinst.: #REF!
Name CRITÉRIOS_IM: #REF!
Name crogr: #REF!
Name d: #REF!
Name dasdfhik: #REF!
Name ddddddd: #REF!
Name DESTINO: #REF!
Name Excel_BuiltIn_Database: #REF!
Name Excel_BuiltIn_Print_Area_1: #REF!
Name f: #REF!
Name fl: #REF!
Name FL_1: #REF!
Name FL_2: #REF!

Sheet Detalhamento - G200
I1: ACOMPANHAMENTO FINANCEIRO
K2: Data de Emissão: 12/05/26
K3: Versão: 00
A4: DETALHAMENTO
A5: CÓDIGO | B5: DESCRIÇÃO | C5: VALOR ORÇADO | D5: ABR | F5: VALOR COMPROMETIDO | G5: SALDO DO COMPROMETIDO | H5: VALOR REALIZADO | I5: PROJEÇÕES | J5: TENDÊNCIA | K5: VARIAÇÃO
A6: 0 | B6: TOTAL OBRA | C6: =SUBTOTAL(9,C7:C253) -> 4.532026e+08 | F6: =SUBTOTAL(9,F7:F253) -> 3.3465024e+08 | G6: =SUBTOTAL(9,G7:G253) -> 1.1855237e+08 | H6: =SUBTOTAL(9,H7:H253) -> 1.0674933e+08 | I6: =SUBTOTAL(9,I7:I253) -> -267155.08 | J6: =SUBTOTAL(9,J7:J253) -> 3.3438308e+08 | K6: =SUBTOTAL(9,K7:K253) -> 1.1881952e+08
A7: 1 | B7: DESPESAS DIRETAS | C7: =SUBTOTAL(9,C8:C109) -> 3.8640159e+08 | D7: =_xlfn.XLOOKUP(A7,'[1]CADASTRO CENTRO DE CUSTO-ALOCAÇ'!$A:$A,'[1]CADASTRO CENTRO DE CUSTO-ALOCAÇ'!$C:$C) -> #N/A | E7: =C7-D7 -> #N/A | F7: =SUBTOTAL(9,F8:F109) -> 2.7037121e+08 | G7: =SUBTOTAL(9,G8:G109) -> 1.1603038e+08 | H7: =SUBTOTAL(9,H8:H109) -> 86608972 | I7: =SUBTOTAL(9,I8:I109) -> -427518.59 | J7: =SUBTOTAL(9,J8:J109) -> 2.6994369e+08 | K7: =SUBTOTAL(9,K8:K109) -> 1.164579e+08
A8: 1001 | B8: GALPÃO G200 | C8: =SUBTOTAL(9,C9:C56) -> 2.0206133e+08 | D8: =_xlfn.XLOOKUP(A8,'[1]CADASTRO CENTRO DE CUSTO-ALOCAÇ'!$A:$A,'[1]CADASTRO CENTRO DE CUSTO-ALOCAÇ'!$C:$C) -> #N/A | E8: =C8-D8 -> #N/A | F8: =SUBTOTAL(9,F9:F56) -> 1.400033e+08 | G8: =SUBTOTAL(9,G9:G56) -> 62058025 | H8: =SUBTOTAL(9,H9:H56) -> 71147139 | I8: =SUBTOTAL(9,I9:I56) -> -1750968.1 | J8: =SUBTOTAL(9,J9:J56) -> 1.3825234e+08 | K8: =SUBTOTAL(9,K9:K56) -> 63808993
A9: 1001001 | B9: PROJETOS E CONSULTORIAS | C9: =SUBTOTAL(9,C10:C11) -> 4318265.1 | D9: =_xlfn.XLOOKUP(A9,'[1]CADASTRO CENTRO DE CUSTO-ALOCAÇ'!$A:$A,'[1]CADASTRO CENTRO DE CUSTO-ALOCAÇ'!$C:$C) -> 4318265.1 | E9: =C9-D9 -> 0 | F9: =SUBTOTAL(9,F10:F11) -> 4160984.3 | G9: =SUBTOTAL(9,G10:G11) -> 157280.79 | H9: =SUBTOTAL(9,H10:H11) -> 826261.2 | I9: =SUBTOTAL(9,I10:I11) -> 0 | J9: =SUBTOTAL(9,J10:J11) -> 4160984.3 | K9: =SUBTOTAL(9,K10:K11) -> 157280.79
A10: 1001001001 | B10: PROJETOS | C10: 2017612.7 | D10: =_xlfn.XLOOKUP(A10,'[1]CADASTRO CENTRO DE CUSTO-ALOCAÇ'!$A:$A,'[1]CADASTRO CENTRO DE CUSTO-ALOCAÇ'!$C:$C) -> 2017612.7 | E10: =C10-D10 -> 0 | F10: =SUMIF('Contratos - G200'!E:E,'Detalhamento - G200'!A10,'Contratos - G200'!J:J)+SUMIF('Pedidos - G200'!D:D,'Detalhamento - G200'!A10,'Pedidos - G200'!H:H) -> 2005691.7 | G10: =C10-F10 -> 11921 | H10: =SUMIF('Notas fiscais - G200'!D:D,'Detalhamento - G200'!A10,'Notas fiscais - G200'!T:T) -> 654946.18 | I10: =VLOOKUP(A10,'Projeções - G200'!B:F,5,FALSE) -> 0 | J10: =F10+I10 -> 2005691.7 | K10: =C10-J10 -> 11921
A11: 1001001002 | B11: ENSAIOS E CONSULTORIAS | C11: 2300652.4 | D11: =_xlfn.XLOOKUP(A11,'[1]CADASTRO CENTRO DE CUSTO-ALOCAÇ'!$A:$A,'[1]CADASTRO CENTRO DE CUSTO-ALOCAÇ'!$C:$C) -> 2300652.4 | E11: =C11-D11 -> 0 | F11: =SUMIF('Contratos - G200'!E:E,'Detalhamento - G200'!A11,'Contratos - G200'!J:J)+SUMIF('Pedidos - G200'!D:D,'Detalhamento - G200'!A11,'Pedidos - G200'!H:H) -> 2155292.6 | G11: =C11-F11 -> 145359.79 | H11: =SUMIF('Notas fiscais - G200'!D:D,'Detalhamento - G200'!A11,'Notas fiscais - G200'!T:T) -> 171315.02 | I11: =VLOOKUP(A11,'Projeções - G200'!B:F,5,FALSE) -> 0 | J11: =F11+I11 -> 2155292.6 | K11: =C11-J11 -> 145359.79
A12: 1001002 | B12: TERRAPLENAGEM, CONTENÇÃO E DRENAGEM | C12: =SUBTOTAL(9,C13:C19) -> 39946136 | D12: =_xlfn.XLOOKUP(A12,'[1]CADASTRO CENTRO DE CUSTO-ALOCAÇ'!$A:$A,'[1]CADASTRO CENTRO DE CUSTO-ALOCAÇ'!$C:$C) -> #N/A | E12: =C12-D12 -> #N/A | F12: =SUBTOTAL(9,F13:F19) -> 34428613 | G12: =SUBTOTAL(9,G13:G19) -> 5517522.9 | H12: =SUBTOTAL(9,H13:H19) -> 13951581 | I12: =SUBTOTAL(9,I13:I19) -> 0 | J12: =SUBTOTAL(9,J13:J19) -> 34428613 | K12: =SUBTOTAL(9,K13:K19) -> 5517522.9
A13: 1001002002 | B13: MOVIMENTO DE TERRA - ESCOPO MÍNIMO | C13: 4636906.6 | D13: =_xlfn.XLOOKUP(A13,'[1]CADASTRO CENTRO DE CUSTO-ALOCAÇ'!$A:$A,'[1]CADASTRO CENTRO DE CUSTO-ALOCAÇ'!$C:$C) -> 4636906.6 | E13: =C13-D13 -> 0 | F13: =SUMIF('Contratos - G200'!E:E,'Detalhamento - G200'!A13,'Contratos - G200'!J:J)+SUMIF('Pedidos - G200'!D:D,'Detalhamento - G200'!A13,'Pedidos - G200'!H:H) -> 4636906.6 | G13: =C13-F13 -> 0 | H13: =SUMIF('Notas fiscais - G200'!D:D,'Detalhamento - G200'!A13,'Notas fiscais - G200'!T:T) -> 4434001.7 | I13: =VLOOKUP(A13,'Projeções - G200'!B:F,5,FALSE) -> 0 | J13: =F13+I13 -> 4636906.6 | K13: =C13-J13 -> 0
A14: 1001002003 | B14: MOVIMENTAÇÃO DE TERRA | C14: 22691172 | D14: =_xlfn.XLOOKUP(A14,'[1]CADASTRO CENTRO DE CUSTO-ALOCAÇ'!$A:$A,'[1]CADASTRO CENTRO DE CUSTO-ALOCAÇ'!$C:$C) -> 22691172 | E14: =C14-D14 -> 0 | F14: =SUMIF('Contratos - G200'!E:E,'Detalhamento - G200'!A14,'Contratos - G200'!J:J)+SUMIF('Pedidos - G200'!D:D,'Detalhamento - G200'!A14,'Pedidos - G200'!H:H) -> 22341905 | G14: =C14-F14 -> 349267 | H14: =SUMIF('Notas fiscais - G200'!D:D,'Detalhamento - G200'!A14,'Notas fiscais - G200'!T:T) -> 7771538.4 | I14: =VLOOKUP(A14,'Projeções - G200'!B:F,5,FALSE) -> 0 | J14: =F14+I14 -> 22341905 | K14: =C14-J14 -> 349267
A15: 1001002004 | B15: LINHA DE VIDA MOVEL PARA TALUDES | C15: 80552.54 | D15: =_xlfn.XLOOKUP(A15,'[1]CADASTRO CENTRO DE CUSTO-ALOCAÇ'!$A:$A,'[1]CADASTRO CENTRO DE CUSTO-ALOCAÇ'!$C:$C) -> 80552.54 | E15: =C15-D15 -> 0 | F15: =SUMIF('Contratos - G200'!E:E,'Detalhamento - G200'!A15,'Contratos - G200'!J:J)+SUMIF('Pedidos - G200'!D:D,'Detalhamento - G200'!A15,'Pedidos - G200'!H:H) -> 0 | G15: =C15-F15 -> 80552.54 | H15: =SUMIF('Notas fiscais - G200'!D:D,'Detalhamento - G200'!A15,'Notas fiscais - G200'!T:T) -> 0 | I15: =VLOOKUP(A15,'Projeções - G200'!B:F,5,FALSE) -> 0 | J15: =F15+I15 -> 0 | K15: =C15-J15 -> 80552.54
A16: 1001002005 | B16: HIDROSSEMEADURA | C16: 712470 | D16: =_xlfn.XLOOKUP(A16,'[1]CADASTRO CENTRO DE CUSTO-ALOCAÇ'!$A:$A,'[1]CADASTRO CENTRO DE CUSTO-ALOCAÇ'!$C:$C) -> 712470 | E16: =C16-D16 -> 0 | F16: =SUMIF('Contratos - G200'!E:E,'Detalhamento - G200'!A16,'Contratos - G200'!J:J)+SUMIF('Pedidos - G200'!D:D,'Detalhamento - G200'!A16,'Pedidos - G200'!H:H) -> 575368.71 | G16: =C16-F16 -> 137101.29 | H16: =SUMIF('Notas fiscais - G200'!D:D,'Detalhamento - G200'!A16,'Notas fiscais - G200'!T:T) -> 0 | I16: =VLOOKUP(A16,'Projeções - G200'!B:F,5,FALSE) -> 0 | J16: =F16+I16 -> 575368.71 | K16: =C16-J16 -> 137101.29
A17: 1001002006 | B17: CONTENÇÕES | C17: 6392000 | D17: =_xlfn.XLOOKUP(A17,'[1]CADASTRO CENTRO DE CUSTO-ALOCAÇ'!$A:$A,'[1]CADASTRO CENTRO DE CUSTO-ALOCAÇ'!$C:$C) -> 6392000 | E17: =C17-D17 -> 0 | F17: =SUMIF('Contratos - G200'!E:E,'Detalhamento - G200'!A17,'Contratos - G200'!J:J)+SUMIF('Pedidos - G200'!D:D,'Detalhamento - G200'!A17,'Pedidos - G200'!H:H) -> 5727065.1 | G17: =C17-F17 -> 664934.9 | H17: =SUMIF('Notas fiscais - G200'!D:D,'Detalhamento - G200'!A17,'Notas fiscais - G200'!T:T) -> 1598299.8 | I17: =VLOOKUP(A17,'Projeções - G200'!B:F,5,FALSE) -> 0 | J17: =F17+I17 -> 5727065.1 | K17: =C17-J17 -> 664934.9
A18: 1001002007 | B18: ESCAVAÇÃO NO TARDOZ | C18: 800400 | D18: =_xlfn.XLOOKUP(A18,'[1]CADASTRO CENTRO DE CUSTO-ALOCAÇ'!$A:$A,'[1]CADASTRO CENTRO DE CUSTO-ALOCAÇ'!$C:$C) -> 800400 | E18: =C18-D18 -> 0 | F18: =SUMIF('Contratos - G200'!E:E,'Detalhamento - G200'!A18,'Contratos - G200'!J:J)+SUMIF('Pedidos - G200'!D:D,'Detalhamento - G200'!A18,'Pedidos - G200'!H:H) -> 800400.01 | G18: =C18-F18 -> -0.01 | H18: =SUMIF('Notas fiscais - G200'!D:D,'Detalhamento - G200'!A18,'Notas fiscais - G200'!T:T) -> 136068.71 | I18: =VLOOKUP(A18,'Projeções - G200'!B:F,5,FALSE) -> 0 | J18: =F18+I18 -> 800400.01 | K18: =C18-J18 -> -0.01
A19: 1001002008 | B19: DRENAGEM | C19: 4632635.2 | D19: =_xlfn.XLOOKUP(A19,'[1]CADASTRO CENTRO DE CUSTO-ALOCAÇ'!$A:$A,'[1]CADASTRO CENTRO DE CUSTO-ALOCAÇ'!$C:$C) -> 4632635.2 | E19: =C19-D19 -> 0 | F19: =SUMIF('Contratos - G200'!E:E,'Detalhamento - G200'!A19,'Contratos - G200'!J:J)+SUMIF('Pedidos - G200'!D:D,'Detalhamento - G200'!A19,'Pedidos - G200'!H:H) -> 346968.04 | G19: =C19-F19 -> 4285667.1 | H19: =SUMIF('Notas fiscais - G200'!D:D,'Detalhamento - G200'!A19,'Notas fiscais - G200'!T:T) -> 11672.07 | I19: =VLOOKUP(A19,'Projeções - G200'!B:F,5,FALSE) -> 0 | J19: =F19+I19 -> 346968.04 | K19: =C19-J19 -> 4285667.1
A20: 1001003 | B20: GALPÃO PRINCIPAL | C20: =SUBTOTAL(9,C21:C34) -> 86690399 | D20: =_xlfn.XLOOKUP(A20,'[1]CADASTRO CENTRO DE CUSTO-ALOCAÇ'!$A:$A,'[1]CADASTRO CENTRO DE CUSTO-ALOCAÇ'!$C:$C) -> #N/A | E20: =C20-D20 -> #N/A | F20: =SUBTOTAL(9,F21:F34) -> 65637369 | G20: =SUBTOTAL(9,G21:G34) -> 21053030 | H20: =SUBTOTAL(9,H21:H34) -> 42534556 | I20: =SUBTOTAL(9,I21:I34) -> -646893.62 | J20: =SUBTOTAL(9,J21:J34) -> 64990475 | K20: =SUBTOTAL(9,K21:K34) -> 21699924
A21: 1001003001 | B21: FUNDAÇÃO GALPÃO | C21: 9773681.3 | D21: =_xlfn.XLOOKUP(A21,'[1]CADASTRO CENTRO DE CUSTO-ALOCAÇ'!$A:$A,'[1]CADASTRO CENTRO DE CUSTO-ALOCAÇ'!$C:$C) -> 9773681.3 | E21: =C21-D21 -> 0 | F21: =SUMIF('Contratos - G200'!E:E,'Detalhamento - G200'!A21,'Contratos - G200'!J:J)+SUMIF('Pedidos - G200'!D:D,'Detalhamento - G200'!A21,'Pedidos - G200'!H:H) -> 7710689.8 | G21: =C21-F21 -> 2062991.5 | H21: =SUMIF('Notas fiscais - G200'!D:D,'Detalhamento - G200'!A21,'Notas fiscais - G200'!T:T) -> 893277.54 | I21: =VLOOKUP(A21,'Projeções - G200'!B:F,5,FALSE) -> 0 | J21: =F21+I21 -> 7710689.8 | K21: =C21-J21 -> 2062991.5
A22: 1001003002 | B22: SUPERESTRUTURA GALPÃO | C22: 12610439 | D22: =_xlfn.XLOOKUP(A22,'[1]CADASTRO CENTRO DE CUSTO-ALOCAÇ'!$A:$A,'[1]CADASTRO CENTRO DE CUSTO-ALOCAÇ'!$C:$C) -> 12610439 | E22: =C22-D22 -> 0 | F22: =SUMIF('Contratos - G200'!E:E,'Detalhamento - G200'!A22,'Contratos - G200'!J:J)+SUMIF('Pedidos - G200'!D:D,'Detalhamento - G200'!A22,'Pedidos - G200'!H:H) -> 14432797 | G22: =C22-F22 -> -1822357.6 | H22: =SUMIF('Notas fiscais - G200'!D:D,'Detalhamento - G200'!A22,'Notas fiscais - G200'!T:T) -> 38764242 | I22: =VLOOKUP(A22,'Projeções - G200'!B:F,5,FALSE) -> 0 | J22: =F22+I22 -> 14432797 | K22: =C22-J22 -> -1822357.6
A23: 1001003003 | B23: COBERTURA E FECHAMENTO METALICO | C23: 39714155 | D23: =_xlfn.XLOOKUP(A23,'[1]CADASTRO CENTRO DE CUSTO-ALOCAÇ'!$A:$A,'[1]CADASTRO CENTRO DE CUSTO-ALOCAÇ'!$C:$C) -> 39714155 | E23: =C23-D23 -> 0 | F23: =SUMIF('Contratos - G200'!E:E,'Detalhamento - G200'!A23,'Contratos - G200'!J:J)+SUMIF('Pedidos - G200'!D:D,'Detalhamento - G200'!A23,'Pedidos - G200'!H:H) -> 39251594 | G23: =C23-F23 -> 462561 | H23: =SUMIF('Notas fiscais - G200'!D:D,'Detalhamento - G200'!A23,'Notas fiscais - G200'!T:T) -> 0 | I23: =VLOOKUP(A23,'Projeções - G200'!B:F,5,FALSE) -> 0 | J23: =F23+I23 -> 39251594 | K23: =C23-J23 -> 462561
A24: 1001003004 | B24: PISO DE CONCRETO | C24: 16686202 | D24: =_xlfn.XLOOKUP(A24,'[1]CADASTRO CENTRO DE CUSTO-ALOCAÇ'!$A:$A,'[1]CADASTRO CENTRO DE CUSTO-ALOCAÇ'!$C:$C) -> 16686202 | E24: =C24-D24 -> 0 | F24: =SUMIF('Contratos - G200'!E:E,'Detalhamento - G200'!A24,'Contratos - G200'!J:J)+SUMIF('Pedidos - G200'!D:D,'Detalhamento - G200'!A24,'Pedidos - G200'!H:H) -> 0 | G24: =C24-F24 -> 16686202 | H24: =SUMIF('Notas fiscais - G200'!D:D,'Detalhamento - G200'!A24,'Notas fiscais - G200'!T:T) -> 0 | I24: =VLOOKUP(A24,'Projeções - G200'!B:F,5,FALSE) -> 0 | J24: =F24+I24 -> 0 | K24: =C24-J24 -> 16686202
A25: 1001003005 | B25: ESQUADRIAS E CAIXILHOS | C25: 2316824.1 | D25: =_xlfn.XLOOKUP(A25,'[1]CADASTRO CENTRO DE CUSTO-ALOCAÇ'!$A:$A,'[1]CADASTRO CENTRO DE CUSTO-ALOCAÇ'!$C:$C) -> 2316824.1 | E25: =C25-D25 -> 0 | F25: =SUMIF('Contratos - G200'!E:E,'Detalhamento - G200'!A25,'Contratos - G200'!J:J)+SUMIF('Pedidos - G200'!D:D,'Detalhamento - G200'!A25,'Pedidos - G200'!H:H) -> 1450590 | G25: =C25-F25 -> 866234.14 | H25: =SUMIF('Notas fiscais - G200'!D:D,'Detalhamento - G200'!A25,'Notas fiscais - G200'!T:T) -> 1112193 | I25: =VLOOKUP(A25,'Projeções - G200'!B:F,5,FALSE) -> 0 | J25: =F25+I25 -> 1450590 | K25: =C25-J25 -> 866234.14
A26: 1001003006 | B26: IMPERMEABILIZAÇÃO | C26: 750757.69 | D26: =_xlfn.XLOOKUP(A26,'[1]CADASTRO CENTRO DE CUSTO-ALOCAÇ'!$A:$A,'[1]CADASTRO CENTRO DE CUSTO-ALOCAÇ'!$C:$C) -> 750757.69 | E26: =C26-D26 -> 0 | F26: =SUMIF('Contratos - G200'!E:E,'Detalhamento - G200'!A26,'Contratos - G200'!J:J)+SUMIF('Pedidos - G200'!D:D,'Detalhamento - G200'!A26,'Pedidos - G200'!H:H) -> 30241.363 | G26: =C26-F26 -> 720516.33 | H26: =SUMIF('Notas fiscais - G200'!D:D,'Detalhamento - G200'!A26,'Notas fiscais - G200'!T:T) -> 1017.32 | I26: =VLOOKUP(A26,'Projeções - G200'!B:F,5,FALSE) -> 0 | J26: =F26+I26 -> 30241.363 | K26: =C26-J26 -> 720516.33
A27: 1001003007 | B27: REVESTIMENTOS | C27: 0 | D27: =_xlfn.XLOOKUP(A27,'[1]CADASTRO CENTRO DE CUSTO-ALOCAÇ'!$A:$A,'[1]CADASTRO CENTRO DE CUSTO-ALOCAÇ'!$C:$C) -> 0 | E27: =C27-D27 -> 0 | F27: =SUMIF('Contratos - G200'!E:E,'Detalhamento - G200'!A27,'Contratos - G200'!J:J)+SUMIF('Pedidos - G200'!D:D,'Detalhamento - G200'!A27,'Pedidos - G200'!H:H) -> 0 | G27: =C27-F27 -> 0 | H27: =SUMIF('Notas fiscais - G200'!D:D,'Detalhamento - G200'!A27,'Notas fiscais - G200'!T:T) -> 0 | I27: =VLOOKUP(A27,'Projeções - G200'!B:F,5,FALSE) -> 0 | J27: =F27+I27 -> 0 | K27: =C27-J27 -> 0
A28: 1001003008 | B28: FORRO | C28: 0 | D28: =_xlfn.XLOOKUP(A28,'[1]CADASTRO CENTRO DE CUSTO-ALOCAÇ'!$A:$A,'[1]CADASTRO CENTRO DE CUSTO-ALOCAÇ'!$C:$C) -> 0 | E28: =C28-D28 -> 0 | F28: =SUMIF('Contratos - G200'!E:E,'Detalhamento - G200'!A28,'Contratos - G200'!J:J)+SUMIF('Pedidos - G200'!D:D,'Detalhamento - G200'!A28,'Pedidos - G200'!H:H) -> 0 | G28: =C28-F28 -> 0 | H28: =SUMIF('Notas fiscais - G200'!D:D,'Detalhamento - G200'!A28,'Notas fiscais - G200'!T:T) -> 0 | I28: =VLOOKUP(A28,'Projeções - G200'!B:F,5,FALSE) -> 0 | J28: =F28+I28 -> 0 | K28: =C28-J28 -> 0
A29: 1001003009 | B29: LOUÇAS, METAIS E INSTALAÇÕES DE BANHEIRO | C29: 0 | D29: =_xlfn.XLOOKUP(A29,'[1]CADASTRO CENTRO DE CUSTO-ALOCAÇ'!$A:$A,'[1]CADASTRO CENTRO DE CUSTO-ALOCAÇ'!$C:$C) -> 0 | E29: =C29-D29 -> 0 | F29: =SUMIF('Contratos - G200'!E:E,'Detalhamento - G200'!A29,'Contratos - G200'!J:J)+SUMIF('Pedidos - G200'!D:D,'Detalhamento - G200'!A29,'Pedidos - G200'!H:H) -> 0 | G29: =C29-F29 -> 0 | H29: =SUMIF('Notas fiscais - G200'!D:D,'Detalhamento - G200'!A29,'Notas fiscais - G200'!T:T) -> 0 | I29: =VLOOKUP(A29,'Projeções - G200'!B:F,5,FALSE) -> 0 | J29: =F29+I29 -> 0 | K29: =C29-J29 -> 0
A30: 1001003010 | B30: SERRALHERIA GALPÃO | C30: 779756.42 | D30: =_xlfn.XLOOKUP(A30,'[1]CADASTRO CENTRO DE CUSTO-ALOCAÇ'!$A:$A,'[1]CADASTRO CENTRO DE CUSTO-ALOCAÇ'!$C:$C) -> 779756.42 | E30: =C30-D30 -> 0 | F30: =SUMIF('Contratos - G200'!E:E,'Detalhamento - G200'!A30,'Contratos - G200'!J:J)+SUMIF('Pedidos - G200'!D:D,'Detalhamento - G200'!A30,'Pedidos - G200'!H:H) -> 611161.88 | G30: =C30-F30 -> 168594.54 | H30: =SUMIF('Notas fiscais - G200'!D:D,'Detalhamento - G200'!A30,'Notas fiscais - G200'!T:T) -> 115550.02 | I30: =VLOOKUP(A30,'Projeções - G200'!B:F,5,FALSE) -> 0 | J30: =F30+I30 -> 611161.88 | K30: =C30-J30 -> 168594.54
A31: 1001003011 | B31: EQUIPAMENTOS GALPÃO | C31: 2965707.5 | D31: =_xlfn.XLOOKUP(A31,'[1]CADASTRO CENTRO DE CUSTO-ALOCAÇ'!$A:$A,'[1]CADASTRO CENTRO DE CUSTO-ALOCAÇ'!$C:$C) -> 2965707.5 | E31: =C31-D31 -> 0 | F31: =SUMIF('Contratos - G200'!E:E,'Detalhamento - G200'!A31,'Contratos - G200'!J:J)+SUMIF('Pedidos - G200'!D:D,'Detalhamento - G200'!A31,'Pedidos - G200'!H:H) -> 2149410 | G31: =C31-F31 -> 816297.48 | H31: =SUMIF('Notas fiscais - G200'!D:D,'Detalhamento - G200'!A31,'Notas fiscais - G200'!T:T) -> 1648276.1 | I31: =VLOOKUP(A31,'Projeções - G200'!B:F,5,FALSE) -> -646893.62 | J31: =F31+I31 -> 1502516.4 | K31: =C31-J31 -> 1463191.1
A32: 1001003012 | B32: PINTURA GALPÃO | C32: 311057.28 | D32: =_xlfn.XLOOKUP(A32,'[1]CADASTRO CENTRO DE CUSTO-ALOCAÇ'!$A:$A,'[1]CADASTRO CENTRO DE CUSTO-ALOCAÇ'!$C:$C) -> 311057.28 | E32: =C32-D32 -> 0 | F32: =SUMIF('Contratos - G200'!E:E,'Detalhamento - G200'!A32,'Contratos - G200'!J:J)+SUMIF('Pedidos - G200'!D:D,'Detalhamento - G200'!A32,'Pedidos - G200'!H:H) -> 0 | G32: =C32-F32 -> 311057.28 | H32: =SUMIF('Notas fiscais - G200'!D:D,'Detalhamento - G200'!A32,'Notas fiscais - G200'!T:T) -> 0 | I32: =VLOOKUP(A32,'Projeções - G200'!B:F,5,FALSE) -> 0 | J32: =F32+I32 -> 0 | K32: =C32-J32 -> 311057.28
... A34: 1001003014 | B34: COMUNICAÇÃO VISUAL GALPÃO | C34: 0 | D34: =_xlfn.XLOOKUP(A34,'[1]CADASTRO CENTRO DE CUSTO-ALOCAÇ'!$A:$A,'[1]CADASTRO CENTRO DE CUSTO-ALOCAÇ'!$C:$C) -> 0 | E34: =C34-D34 -> 0 | F34: =SUMIF('Contratos - G200'!E:E,'Detalhamento - G200'!A34,'Contratos - G200'!J:J)+SUMIF('Pedidos - G200'!D:D,'Detalhamento - G200'!A34,'Pedidos - G200'!H:H) -> 885 | G34: =C34-F34 -> -885 | H34: =SUMIF('Notas fiscais - G200'!D:D,'Detalhamento - G200'!A34,'Notas fiscais - G200'!T:T) -> 0 | I34: =VLOOKUP(A34,'Projeções - G200'!B:F,5,FALSE) -> 0 | J34: =F34+I34 -> 885 | K34: =C34-J34 -> -885
A35: 1001004 | B35: OUTRAS EDIFICAÇÕES | C35: =SUBTOTAL(9,C36:C45) -> 23248542 | D35: =_xlfn.XLOOKUP(A35,'[1]CADASTRO CENTRO DE CUSTO-ALOCAÇ'!$A:$A,'[1]CADASTRO CENTRO DE CUSTO-ALOCAÇ'!$C:$C) -> 23248542 | E35: =C35-D35 -> 0 | F35: =SUBTOTAL(9,F36:F45) -> 9355187.5 | G35: =SUBTOTAL(9,G36:G45) -> 13893355 | H35: =SUBTOTAL(9,H36:H45) -> 29165.31 | I35: =SUBTOTAL(9,I36:I45) -> 0 | J35: =SUBTOTAL(9,J36:J45) -> 9355187.5 | K35: =SUBTOTAL(9,K36:K45) -> 13893355
A36: 1001004001 | B36: PORTARIA / COBERTURA DA ECLUSA | C36: 4576075.6 | D36: =_xlfn.XLOOKUP(A36,'[1]CADASTRO CENTRO DE CUSTO-ALOCAÇ'!$A:$A,'[1]CADASTRO CENTRO DE CUSTO-ALOCAÇ'!$C:$C) -> 4576075.6 | E36: =C36-D36 -> 0 | F36: =SUMIF('Contratos - G200'!E:E,'Detalhamento - G200'!A36,'Contratos - G200'!J:J)+SUMIF('Pedidos - G200'!D:D,'Detalhamento - G200'!A36,'Pedidos - G200'!H:H) -> 2882643.7 | G36: =C36-F36 -> 1693431.9 | H36: =SUMIF('Notas fiscais - G200'!D:D,'Detalhamento - G200'!A36,'Notas fiscais - G200'!T:T) -> 0 | I36: =VLOOKUP(A36,'Projeções - G200'!B:F,5,FALSE) -> 0 | J36: =F36+I36 -> 2882643.7 | K36: =C36-J36 -> 1693431.9
A37: 1001004002 | B37: APOIO (VESTIÁRIO + REFEITÓRIO) | C37: 9253125 | D37: =_xlfn.XLOOKUP(A37,'[1]CADASTRO CENTRO DE CUSTO-ALOCAÇ'!$A:$A,'[1]CADASTRO CENTRO DE CUSTO-ALOCAÇ'!$C:$C) -> 9253125 | E37: =C37-D37 -> 0 | F37: =SUMIF('Contratos - G200'!E:E,'Detalhamento - G200'!A37,'Contratos - G200'!J:J)+SUMIF('Pedidos - G200'!D:D,'Detalhamento - G200'!A37,'Pedidos - G200'!H:H) -> 2739057.3 | G37: =C37-F37 -> 6514067.7 | H37: =SUMIF('Notas fiscais - G200'!D:D,'Detalhamento - G200'!A37,'Notas fiscais - G200'!T:T) -> 15983.14 | I37: =VLOOKUP(A37,'Projeções - G200'!B:F,5,FALSE) -> 0 | J37: =F37+I37 -> 2739057.3 | K37: =C37-J37 -> 6514067.7
A38: 1001004003 | B38: COBERTURA PEDESTRES | C38: 0 | D38: =_xlfn.XLOOKUP(A38,'[1]CADASTRO CENTRO DE CUSTO-ALOCAÇ'!$A:$A,'[1]CADASTRO CENTRO DE CUSTO-ALOCAÇ'!$C:$C) -> 0 | E38: =C38-D38 -> 0 | F38: =SUMIF('Contratos - G200'!E:E,'Detalhamento - G200'!A38,'Contratos - G200'!J:J)+SUMIF('Pedidos - G200'!D:D,'Detalhamento - G200'!A38,'Pedidos - G200'!H:H) -> 0 | G38: =C38-F38 -> 0 | H38: =SUMIF('Notas fiscais - G200'!D:D,'Detalhamento - G200'!A38,'Notas fiscais - G200'!T:T) -> 0 | I38: =VLOOKUP(A38,'Projeções - G200'!B:F,5,FALSE) -> 0 | J38: =F38+I38 -> 0 | K38: =C38-J38 -> 0
A39: 1001004004 | B39: APOIO MOTORISTA | C39: 0 | D39: =_xlfn.XLOOKUP(A39,'[1]CADASTRO CENTRO DE CUSTO-ALOCAÇ'!$A:$A,'[1]CADASTRO CENTRO DE CUSTO-ALOCAÇ'!$C:$C) -> 0 | E39: =C39-D39 -> 0 | F39: =SUMIF('Contratos - G200'!E:E,'Detalhamento - G200'!A39,'Contratos - G200'!J:J)+SUMIF('Pedidos - G200'!D:D,'Detalhamento - G200'!A39,'Pedidos - G200'!H:H) -> 0 | G39: =C39-F39 -> 0 | H39: =SUMIF('Notas fiscais - G200'!D:D,'Detalhamento - G200'!A39,'Notas fiscais - G200'!T:T) -> 0 | I39: =VLOOKUP(A39,'Projeções - G200'!B:F,5,FALSE) -> 0 | J39: =F39+I39 -> 0 | K39: =C39-J39 -> 0
A40: 1001004005 | B40: UTILIDADES | C40: 1094800 | D40: =_xlfn.XLOOKUP(A40,'[1]CADASTRO CENTRO DE CUSTO-ALOCAÇ'!$A:$A,'[1]CADASTRO CENTRO DE CUSTO-ALOCAÇ'!$C:$C) -> 1094800 | E40: =C40-D40 -> 0 | F40: =SUMIF('Contratos - G200'!E:E,'Detalhamento - G200'!A40,'Contratos - G200'!J:J)+SUMIF('Pedidos - G200'!D:D,'Detalhamento - G200'!A40,'Pedidos - G200'!H:H) -> 192891.6 | G40: =C40-F40 -> 901908.4 | H40: =SUMIF('Notas fiscais - G200'!D:D,'Detalhamento - G200'!A40,'Notas fiscais - G200'!T:T) -> 1634.24 | I40: =VLOOKUP(A40,'Projeções - G200'!B:F,5,FALSE) -> 0 | J40: =F40+I40 -> 192891.6 | K40: =C40-J40 -> 901908.4
A41: 1001004006 | B41: SANITÁRIOS EXTERNOS AO GALPÃO | C41: 4091136.1 | D41: =_xlfn.XLOOKUP(A41,'[1]CADASTRO CENTRO DE CUSTO-ALOCAÇ'!$A:$A,'[1]CADASTRO CENTRO DE CUSTO-ALOCAÇ'!$C:$C) -> 4091136.1 | E41: =C41-D41 -> 0 | F41: =SUMIF('Contratos - G200'!E:E,'Detalhamento - G200'!A41,'Contratos - G200'!J:J)+SUMIF('Pedidos - G200'!D:D,'Detalhamento - G200'!A41,'Pedidos - G200'!H:H) -> 740085.44 | G41: =C41-F41 -> 3351050.7 | H41: =SUMIF('Notas fiscais - G200'!D:D,'Detalhamento - G200'!A41,'Notas fiscais - G200'!T:T) -> 11547.93 | I41: =VLOOKUP(A41,'Projeções - G200'!B:F,5,FALSE) -> 0 | J41: =F41+I41 -> 740085.44 | K41: =C41-J41 -> 3351050.7
A42: 1001004007 | B42: PASSARELA DE PEDESTRES / COBERTURA DE ESTACIONAMENTO | C42: 2078605.4 | D42: =_xlfn.XLOOKUP(A42,'[1]CADASTRO CENTRO DE CUSTO-ALOCAÇ'!$A:$A,'[1]CADASTRO CENTRO DE CUSTO-ALOCAÇ'!$C:$C) -> 2078605.4 | E42: =C42-D42 -> 0 | F42: =SUMIF('Contratos - G200'!E:E,'Detalhamento - G200'!A42,'Contratos - G200'!J:J)+SUMIF('Pedidos - G200'!D:D,'Detalhamento - G200'!A42,'Pedidos - G200'!H:H) -> 1924371.3 | G42: =C42-F42 -> 154234.14 | H42: =SUMIF('Notas fiscais - G200'!D:D,'Detalhamento - G200'!A42,'Notas fiscais - G200'!T:T) -> 0 | I42: =VLOOKUP(A42,'Projeções - G200'!B:F,5,FALSE) -> 0 | J42: =F42+I42 -> 1924371.3 | K42: =C42-J42 -> 154234.14
A43: 1001004008 | B43: BICICLETÁRIO | C43: 40000 | D43: =_xlfn.XLOOKUP(A43,'[1]CADASTRO CENTRO DE CUSTO-ALOCAÇ'!$A:$A,'[1]CADASTRO CENTRO DE CUSTO-ALOCAÇ'!$C:$C) -> 40000 | E43: =C43-D43 -> 0 | F43: =SUMIF('Contratos - G200'!E:E,'Detalhamento - G200'!A43,'Contratos - G200'!J:J)+SUMIF('Pedidos - G200'!D:D,'Detalhamento - G200'!A43,'Pedidos - G200'!H:H) -> 0 | G43: =C43-F43 -> 40000 | H43: =SUMIF('Notas fiscais - G200'!D:D,'Detalhamento - G200'!A43,'Notas fiscais - G200'!T:T) -> 0 | I43: =VLOOKUP(A43,'Projeções - G200'!B:F,5,FALSE) -> 0 | J43: =F43+I43 -> 0 | K43: =C43-J43 -> 40000
A44: 1001004009 | B44: LIXO | C44: 0 | D44: =_xlfn.XLOOKUP(A44,'[1]CADASTRO CENTRO DE CUSTO-ALOCAÇ'!$A:$A,'[1]CADASTRO CENTRO DE CUSTO-ALOCAÇ'!$C:$C) -> 0 | E44: =C44-D44 -> 0 | F44: =SUMIF('Contratos - G200'!E:E,'Detalhamento - G200'!A44,'Contratos - G200'!J:J)+SUMIF('Pedidos - G200'!D:D,'Detalhamento - G200'!A44,'Pedidos - G200'!H:H) -> 0 | G44: =C44-F44 -> 0 | H44: =SUMIF('Notas fiscais - G200'!D:D,'Detalhamento - G200'!A44,'Notas fiscais - G200'!T:T) -> 0 | I44: =VLOOKUP(A44,'Projeções - G200'!B:F,5,FALSE) -> 0 | J44: =F44+I44 -> 0 | K44: =C44-J44 -> 0
A45: 1001004010 | B45: ÁREA DE LAZER | C45: 2114800 | D45: =_xlfn.XLOOKUP(A45,'[1]CADASTRO CENTRO DE CUSTO-ALOCAÇ'!$A:$A,'[1]CADASTRO CENTRO DE CUSTO-ALOCAÇ'!$C:$C) -> 2114800 | E45: =C45-D45 -> 0 | F45: =SUMIF('Contratos - G200'!E:E,'Detalhamento - G200'!A45,'Contratos - G200'!J:J)+SUMIF('Pedidos - G200'!D:D,'Detalhamento - G200'!A45,'Pedidos - G200'!H:H) -> 876138.3 | G45: =C45-F45 -> 1238661.7 | H45: =SUMIF('Notas fiscais - G200'!D:D,'Detalhamento - G200'!A45,'Notas fiscais - G200'!T:T) -> 0 | I45: =VLOOKUP(A45,'Projeções - G200'!B:F,5,FALSE) -> 0 | J45: =F45+I45 -> 876138.3 | K45: =C45-J45 -> 1238661.7
A46: 1001005 | B46: INSTALAÇÕES GERAIS - GALPÃO | C46: =SUBTOTAL(9,C47:C48) -> 27926047 | D46: =_xlfn.XLOOKUP(A46,'[1]CADASTRO CENTRO DE CUSTO-ALOCAÇ'!$A:$A,'[1]CADASTRO CENTRO DE CUSTO-ALOCAÇ'!$C:$C) -> 27926047 | E46: =C46-D46 -> 0 | F46: =SUBTOTAL(9,F47:F48) -> 23761031 | G46: =SUBTOTAL(9,G47:G48) -> 4165015.9 | H46: =SUBTOTAL(9,H47:H48) -> 12677419 | I46: =SUBTOTAL(9,I47:I48) -> -1067074.5 | J46: =SUBTOTAL(9,J47:J48) -> 22693957 | K46: =SUBTOTAL(9,K47:K48) -> 5232090.4
A47: 1001005001 | B47: ELETRICA, HIDRÁULICA E COMBATE A INCÊNDIO - MEP | C47: 27273270 | D47: =_xlfn.XLOOKUP(A47,'[1]CADASTRO CENTRO DE CUSTO-ALOCAÇ'!$A:$A,'[1]CADASTRO CENTRO DE CUSTO-ALOCAÇ'!$C:$C) -> 27273270 | E47: =C47-D47 -> 0 | F47: =SUMIF('Contratos - G200'!E:E,'Detalhamento - G200'!A47,'Contratos - G200'!J:J)+SUMIF('Pedidos - G200'!D:D,'Detalhamento - G200'!A47,'Pedidos - G200'!H:H) -> 23131833 | G47: =C47-F47 -> 4141436.8 | H47: =SUMIF('Notas fiscais - G200'!D:D,'Detalhamento - G200'!A47,'Notas fiscais - G200'!T:T) -> 12601759 | I47: =VLOOKUP(A47,'Projeções - G200'!B:F,5,FALSE) -> -1067074.5 | J47: =F47+I47 -> 22064758 | K47: =C47-J47 -> 5208511.3
A48: 1001005002 | B48: SISTEMA DE AR CONDICIONADO E EXAUSTÃO | C48: 652777.67 | D48: =_xlfn.XLOOKUP(A48,'[1]CADASTRO CENTRO DE CUSTO-ALOCAÇ'!$A:$A,'[1]CADASTRO CENTRO DE CUSTO-ALOCAÇ'!$C:$C) -> 652777.67 | E48: =C48-D48 -> 0 | F48: =SUMIF('Contratos - G200'!E:E,'Detalhamento - G200'!A48,'Contratos - G200'!J:J)+SUMIF('Pedidos - G200'!D:D,'Detalhamento - G200'!A48,'Pedidos - G200'!H:H) -> 629198.54 | G48: =C48-F48 -> 23579.13 | H48: =SUMIF('Notas fiscais - G200'!D:D,'Detalhamento - G200'!A48,'Notas fiscais - G200'!T:T) -> 75659.74 | I48: =VLOOKUP(A48,'Projeções - G200'!B:F,5,FALSE) -> 0 | J48: =F48+I48 -> 629198.54 | K48: =C48-J48 -> 23579.13
A49: 1001006 | B49: SERVIÇOS EXTERNOS | C49: =SUBTOTAL(9,C50:C56) -> 19931939 | D49: =_xlfn.XLOOKUP(A49,'[1]CADASTRO CENTRO DE CUSTO-ALOCAÇ'!$A:$A,'[1]CADASTRO CENTRO DE CUSTO-ALOCAÇ'!$C:$C) -> 19931939 | E49: =C49-D49 -> 0 | F49: =SUBTOTAL(9,F50:F56) -> 2660118 | G49: =SUBTOTAL(9,G50:G56) -> 17271821 | H49: =SUBTOTAL(9,H50:H56) -> 1128156.5 | I49: =SUBTOTAL(9,I50:I56) -> -37000 | J49: =SUBTOTAL(9,J50:J56) -> 2623118 | K49: =SUBTOTAL(9,K50:K56) -> 17308821
A50: 1001006001 | B50: PAVIMENTAÇÃO EXTERNA | C50: 13356940 | D50: =_xlfn.XLOOKUP(A50,'[1]CADASTRO CENTRO DE CUSTO-ALOCAÇ'!$A:$A,'[1]CADASTRO CENTRO DE CUSTO-ALOCAÇ'!$C:$C) -> 13356940 | E50: =C50-D50 -> 0 | F50: =SUMIF('Contratos - G200'!E:E,'Detalhamento - G200'!A50,'Contratos - G200'!J:J)+SUMIF('Pedidos - G200'!D:D,'Detalhamento - G200'!A50,'Pedidos - G200'!H:H) -> 23.88 | G50: =C50-F50 -> 13356916 | H50: =SUMIF('Notas fiscais - G200'!D:D,'Detalhamento - G200'!A50,'Notas fiscais - G200'!T:T) -> 0 | I50: =VLOOKUP(A50,'Projeções - G200'!B:F,5,FALSE) -> 0 | J50: =F50+I50 -> 23.88 | K50: =C50-J50 -> 13356916
A51: 1001006002 | B51: FECHAMENTO PERIMETRAL E PAISAGISMO | C51: 3354411.1 | D51: =_xlfn.XLOOKUP(A51,'[1]CADASTRO CENTRO DE CUSTO-ALOCAÇ'!$A:$A,'[1]CADASTRO CENTRO DE CUSTO-ALOCAÇ'!$C:$C) -> 3354411.1 | E51: =C51-D51 -> 0 | F51: =SUMIF('Contratos - G200'!E:E,'Detalhamento - G200'!A51,'Contratos - G200'!J:J)+SUMIF('Pedidos - G200'!D:D,'Detalhamento - G200'!A51,'Pedidos - G200'!H:H) -> 23.88 | G51: =C51-F51 -> 3354387.2 | H51: =SUMIF('Notas fiscais - G200'!D:D,'Detalhamento - G200'!A51,'Notas fiscais - G200'!T:T) -> 0 | I51: =VLOOKUP(A51,'Projeções - G200'!B:F,5,FALSE) -> 0 | J51: =F51+I51 -> 23.88 | K51: =C51-J51 -> 3354387.2
A52: 1001006003 | B52: POÇO ARTESIANO | C52: 221200 | D52: =_xlfn.XLOOKUP(A52,'[1]CADASTRO CENTRO DE CUSTO-ALOCAÇ'!$A:$A,'[1]CADASTRO CENTRO DE CUSTO-ALOCAÇ'!$C:$C) -> 221200 | E52: =C52-D52 -> 0 | F52: =SUMIF('Contratos - G200'!E:E,'Detalhamento - G200'!A52,'Contratos - G200'!J:J)+SUMIF('Pedidos - G200'!D:D,'Detalhamento - G200'!A52,'Pedidos - G200'!H:H) -> 288238.27 | G52: =C52-F52 -> -67038.27 | H52: =SUMIF('Notas fiscais - G200'!D:D,'Detalhamento - G200'!A52,'Notas fiscais - G200'!T:T) -> 137101.73 | I52: =VLOOKUP(A52,'Projeções - G200'!B:F,5,FALSE) -> 0 | J52: =F52+I52 -> 288238.27 | K52: =C52-J52 -> -67038.27
A53: 1001006004 | B53: RESERVATÓRIO METÁLICO | C53: 836000 | D53: =_xlfn.XLOOKUP(A53,'[1]CADASTRO CENTRO DE CUSTO-ALOCAÇ'!$A:$A,'[1]CADASTRO CENTRO DE CUSTO-ALOCAÇ'!$C:$C) -> 836000 | E53: =C53-D53 -> 0 | F53: =SUMIF('Contratos - G200'!E:E,'Detalhamento - G200'!A53,'Contratos - G200'!J:J)+SUMIF('Pedidos - G200'!D:D,'Detalhamento - G200'!A53,'Pedidos - G200'!H:H) -> 799000 | G53: =C53-F53 -> 37000 | H53: =SUMIF('Notas fiscais - G200'!D:D,'Detalhamento - G200'!A53,'Notas fiscais - G200'!T:T) -> 639200 | I53: =VLOOKUP(A53,'Projeções - G200'!B:F,5,FALSE) -> -37000 | J53: =F53+I53 -> 762000 | K53: =C53-J53 -> 74000
A54: 1001006005 | B54: FUNDAÇÃO PARA RESERVATÓRIO METÁLICO | C54: 250000 | D54: =_xlfn.XLOOKUP(A54,'[1]CADASTRO CENTRO DE CUSTO-ALOCAÇ'!$A:$A,'[1]CADASTRO CENTRO DE CUSTO-ALOCAÇ'!$C:$C) -> 250000 | E54: =C54-D54 -> 0 | F54: =SUMIF('Contratos - G200'!E:E,'Detalhamento - G200'!A54,'Contratos - G200'!J:J)+SUMIF('Pedidos - G200'!D:D,'Detalhamento - G200'!A54,'Pedidos - G200'!H:H) -> 0 | G54: =C54-F54 -> 250000 | H54: =SUMIF('Notas fiscais - G200'!D:D,'Detalhamento - G200'!A54,'Notas fiscais - G200'!T:T) -> 0 | I54: =VLOOKUP(A54,'Projeções - G200'!B:F,5,FALSE) -> 0 | J54: =F54+I54 -> 0 | K54: =C54-J54 -> 250000
A55: 1001006006 | B55: ETE | C55: 1913388 | D55: =_xlfn.XLOOKUP(A55,'[1]CADASTRO CENTRO DE CUSTO-ALOCAÇ'!$A:$A,'[1]CADASTRO CENTRO DE CUSTO-ALOCAÇ'!$C:$C) -> 1913388 | E55: =C55-D55 -> 0 | F55: =SUMIF('Contratos - G200'!E:E,'Detalhamento - G200'!A55,'Contratos - G200'!J:J)+SUMIF('Pedidos - G200'!D:D,'Detalhamento - G200'!A55,'Pedidos - G200'!H:H) -> 1572832 | G55: =C55-F55 -> 340556.06 | H55: =SUMIF('Notas fiscais - G200'!D:D,'Detalhamento - G200'!A55,'Notas fiscais - G200'!T:T) -> 351854.76 | I55: =VLOOKUP(A55,'Projeções - G200'!B:F,5,FALSE) -> 0 | J55: =F55+I55 -> 1572832 | K55: =C55-J55 -> 340556.06
A56: 1001006007 | B56: DIVERSOS | C56: 0 | D56: =_xlfn.XLOOKUP(A56,'[1]CADASTRO CENTRO DE CUSTO-ALOCAÇ'!$A:$A,'[1]CADASTRO CENTRO DE CUSTO-ALOCAÇ'!$C:$C) -> 0 | E56: =C56-D56 -> 0 | F56: =SUMIF('Contratos - G200'!E:E,'Detalhamento - G200'!A56,'Contratos - G200'!J:J)+SUMIF('Pedidos - G200'!D:D,'Detalhamento - G200'!A56,'Pedidos - G200'!H:H) -> 0 | G56: =C56-F56 -> 0 | H56: =SUMIF('Notas fiscais - G200'!D:D,'Detalhamento - G200'!A56,'Notas fiscais - G200'!T:T) -> 0 | I56: =VLOOKUP(A56,'Projeções - G200'!B:F,5,FALSE) -> 0 | J56: =F56+I56 -> 0 | K56: =C56-J56 -> 0
A57: 1002 | B57: MEZANINO GERAL | C57: =SUBTOTAL(9,C58:C69) -> 1.3440429e+08 | D57: =_xlfn.XLOOKUP(A57,'[1]CADASTRO CENTRO DE CUSTO-ALOCAÇ'!$A:$A,'[1]CADASTRO CENTRO DE CUSTO-ALOCAÇ'!$C:$C) -> 1.3440429e+08 | E57: =C57-D57 -> 0 | F57: =SUBTOTAL(9,F58:F69) -> 85475779 | G57: =SUBTOTAL(9,G58:G69) -> 48928515 | H57: =SUBTOTAL(9,H58:H69) -> 5047777.7 | I57: =SUBTOTAL(9,I58:I69) -> 2224759.7 | J57: =SUBTOTAL(9,J58:J69) -> 87700539 | K57: =SUBTOTAL(9,K58:K69) -> 46703755
A58: 1002001 | B58: PROJETO E CONSULTORIA | C58: =SUBTOTAL(9,C59:C60) -> 1402140.9 | D58: =_xlfn.XLOOKUP(A58,'[1]CADASTRO CENTRO DE CUSTO-ALOCAÇ'!$A:$A,'[1]CADASTRO CENTRO DE CUSTO-ALOCAÇ'!$C:$C) -> 1402140.9 | E58: =C58-D58 -> 0 | F58: =SUBTOTAL(9,F59:F60) -> 100000 | G58: =SUBTOTAL(9,G59:G60) -> 1302140.9 | H58: =SUBTOTAL(9,H59:H60) -> 0 | I58: =SUBTOTAL(9,I59:I60) -> 0 | J58: =SUBTOTAL(9,J59:J60) -> 100000 | K58: =SUBTOTAL(9,K59:K60) -> 1302140.9
A59: 1002001001 | B59: PROJETO | C59: 652140.9 | D59: =_xlfn.XLOOKUP(A59,'[1]CADASTRO CENTRO DE CUSTO-ALOCAÇ'!$A:$A,'[1]CADASTRO CENTRO DE CUSTO-ALOCAÇ'!$C:$C) -> 652140.9 | E59: =C59-D59 -> 0 | F59: =SUMIF('Contratos - G200'!E:E,'Detalhamento - G200'!A59,'Contratos - G200'!J:J)+SUMIF('Pedidos - G200'!D:D,'Detalhamento - G200'!A59,'Pedidos - G200'!H:H) -> 0 | G59: =C59-F59 -> 652140.9 | H59: =SUMIF('Notas fiscais - G200'!D:D,'Detalhamento - G200'!A59,'Notas fiscais - G200'!T:T) -> 0 | I59: =VLOOKUP(A59,'Projeções - G200'!B:F,5,FALSE) -> 0 | J59: =F59+I59 -> 0 | K59: =C59-J59 -> 652140.9
A60: 1002001002 | B60: ENSAIO E CONSULTORIA | C60: 750000 | D60: =_xlfn.XLOOKUP(A60,'[1]CADASTRO CENTRO DE CUSTO-ALOCAÇ'!$A:$A,'[1]CADASTRO CENTRO DE CUSTO-ALOCAÇ'!$C:$C) -> 750000 | E60: =C60-D60 -> 0 | F60: =SUMIF('Contratos - G200'!E:E,'Detalhamento - G200'!A60,'Contratos - G200'!J:J)+SUMIF('Pedidos - G200'!D:D,'Detalhamento - G200'!A60,'Pedidos - G200'!H:H) -> 100000 | G60: =C60-F60 -> 650000 | H60: =SUMIF('Notas fiscais - G200'!D:D,'Detalhamento - G200'!A60,'Notas fiscais - G200'!T:T) -> 0 | I60: =VLOOKUP(A60,'Projeções - G200'!B:F,5,FALSE) -> 0 | J60: =F60+I60 -> 100000 | K60: =C60-J60 -> 650000
A61: 1002002 | B61: MEZANINO | C61: =SUBTOTAL(9,C62:C67) -> 1.078271e+08 | D61: =_xlfn.XLOOKUP(A61,'[1]CADASTRO CENTRO DE CUSTO-ALOCAÇ'!$A:$A,'[1]CADASTRO CENTRO DE CUSTO-ALOCAÇ'!$C:$C) -> 1.078271e+08 | E61: =C61-D61 -> 0 | F61: =SUBTOTAL(9,F62:F67) -> 61765254 | G61: =SUBTOTAL(9,G62:G67) -> 46061849 | H61: =SUBTOTAL(9,H62:H67) -> 2555449 | I61: =SUBTOTAL(9,I62:I67) -> 2224759.7 | J61: =SUBTOTAL(9,J62:J67) -> 63990014 | K61: =SUBTOTAL(9,K62:K67) -> 43837089
A62: 1002002001 | B62: FUNDAÇÃO | C62: 23488209 | D62: =_xlfn.XLOOKUP(A62,'[1]CADASTRO CENTRO DE CUSTO-ALOCAÇ'!$A:$A,'[1]CADASTRO CENTRO DE CUSTO-ALOCAÇ'!$C:$C) -> 23488209 | E62: =C62-D62 -> 0 | F62: =SUMIF('Contratos - G200'!E:E,'Detalhamento - G200'!A62,'Contratos - G200'!J:J)+SUMIF('Pedidos - G200'!D:D,'Detalhamento - G200'!A62,'Pedidos - G200'!H:H) -> 1428595.8 | G62: =C62-F62 -> 22059613 | H62: =SUMIF('Notas fiscais - G200'!D:D,'Detalhamento - G200'!A62,'Notas fiscais - G200'!T:T) -> 1220174.8 | I62: =VLOOKUP(A62,'Projeções - G200'!B:F,5,FALSE) -> 0 | J62: =F62+I62 -> 1428595.8 | K62: =C62-J62 -> 22059613
A63: 1002002002 | B63: SUPERESTRUTURA | C63: 63105862 | D63: =_xlfn.XLOOKUP(A63,'[1]CADASTRO CENTRO DE CUSTO-ALOCAÇ'!$A:$A,'[1]CADASTRO CENTRO DE CUSTO-ALOCAÇ'!$C:$C) -> 63105862 | E63: =C63-D63 -> 0 | F63: =SUMIF('Contratos - G200'!E:E,'Detalhamento - G200'!A63,'Contratos - G200'!J:J)+SUMIF('Pedidos - G200'!D:D,'Detalhamento - G200'!A63,'Pedidos - G200'!H:H) -> 58737885 | G63: =C63-F63 -> 4367977.8 | H63: =SUMIF('Notas fiscais - G200'!D:D,'Detalhamento - G200'!A63,'Notas fiscais - G200'!T:T) -> 1015524.2 | I63: =VLOOKUP(A63,'Projeções - G200'!B:F,5,FALSE) -> 2472610.9 | J63: =F63+I63 -> 61210496 | K63: =C63-J63 -> 1895366.9
A64: 1002002003 | B64: CAPEAMENTO | C64: 16862598 | D64: =_xlfn.XLOOKUP(A64,'[1]CADASTRO CENTRO DE CUSTO-ALOCAÇ'!$A:$A,'[1]CADASTRO CENTRO DE CUSTO-ALOCAÇ'!$C:$C) -> 16862598 | E64: =C64-D64 -> 0 | F64: =SUMIF('Contratos - G200'!E:E,'Detalhamento - G200'!A64,'Contratos - G200'!J:J)+SUMIF('Pedidos - G200'!D:D,'Detalhamento - G200'!A64,'Pedidos - G200'!H:H) -> 0 | G64: =C64-F64 -> 16862598 | H64: =SUMIF('Notas fiscais - G200'!D:D,'Detalhamento - G200'!A64,'Notas fiscais - G200'!T:T) -> 0 | I64: =VLOOKUP(A64,'Projeções - G200'!B:F,5,FALSE) -> 0 | J64: =F64+I64 -> 0 | K64: =C64-J64 -> 16862598
A65: 1002002004 | B65: SERRALHERIA | C65: 3620433.7 | D65: =_xlfn.XLOOKUP(A65,'[1]CADASTRO CENTRO DE CUSTO-ALOCAÇ'!$A:$A,'[1]CADASTRO CENTRO DE CUSTO-ALOCAÇ'!$C:$C) -> 3620433.7 | E65: =C65-D65 -> 0 | F65: =SUMIF('Contratos - G200'!E:E,'Detalhamento - G200'!A65,'Contratos - G200'!J:J)+SUMIF('Pedidos - G200'!D:D,'Detalhamento - G200'!A65,'Pedidos - G200'!H:H) -> 1598773.8 | G65: =C65-F65 -> 2021659.9 | H65: =SUMIF('Notas fiscais - G200'!D:D,'Detalhamento - G200'!A65,'Notas fiscais - G200'!T:T) -> 319750.06 | I65: =VLOOKUP(A65,'Projeções - G200'!B:F,5,FALSE) -> -247851.13 | J65: =F65+I65 -> 1350922.6 | K65: =C65-J65 -> 2269511
A66: 1002002005 | B66: PINTURA | C66: 250000 | D66: =_xlfn.XLOOKUP(A66,'[1]CADASTRO CENTRO DE CUSTO-ALOCAÇ'!$A:$A,'[1]CADASTRO CENTRO DE CUSTO-ALOCAÇ'!$C:$C) -> 250000 | E66: =C66-D66 -> 0 | F66: =SUMIF('Contratos - G200'!E:E,'Detalhamento - G200'!A66,'Contratos - G200'!J:J)+SUMIF('Pedidos - G200'!D:D,'Detalhamento - G200'!A66,'Pedidos - G200'!H:H) -> 0 | G66: =C66-F66 -> 250000 | H66: =SUMIF('Notas fiscais - G200'!D:D,'Detalhamento - G200'!A66,'Notas fiscais - G200'!T:T) -> 0 | I66: =VLOOKUP(A66,'Projeções - G200'!B:F,5,FALSE) -> 0 | J66: =F66+I66 -> 0 | K66: =C66-J66 -> 250000
A67: 1002002006 | B67: LIMPEZA | C67: 500000 | D67: =_xlfn.XLOOKUP(A67,'[1]CADASTRO CENTRO DE CUSTO-ALOCAÇ'!$A:$A,'[1]CADASTRO CENTRO DE CUSTO-ALOCAÇ'!$C:$C) -> 500000 | E67: =C67-D67 -> 0 | F67: =SUMIF('Contratos - G200'!E:E,'Detalhamento - G200'!A67,'Contratos - G200'!J:J)+SUMIF('Pedidos - G200'!D:D,'Detalhamento - G200'!A67,'Pedidos - G200'!H:H) -> 0 | G67: =C67-F67 -> 500000 | H67: =SUMIF('Notas fiscais - G200'!D:D,'Detalhamento - G200'!A67,'Notas fiscais - G200'!T:T) -> 0 | I67: =VLOOKUP(A67,'Projeções - G200'!B:F,5,FALSE) -> 0 | J67: =F67+I67 -> 0 | K67: =C67-J67 -> 500000
A68: 1002003 | B68: INSTALAÇÕES GERAIS | C68: =SUBTOTAL(9,C69) -> 25175050 | D68: =_xlfn.XLOOKUP(A68,'[1]CADASTRO CENTRO DE CUSTO-ALOCAÇ'!$A:$A,'[1]CADASTRO CENTRO DE CUSTO-ALOCAÇ'!$C:$C) -> 25175050 | E68: =C68-D68 -> 0 | F68: =SUBTOTAL(9,F69) -> 23610525 | G68: =SUBTOTAL(9,G69) -> 1564524.8 | H68: =SUBTOTAL(9,H69) -> 2492328.6 | I68: =SUBTOTAL(9,I69) -> 0 | J68: =SUBTOTAL(9,J69) -> 23610525 | K68: =SUBTOTAL(9,K69) -> 1564524.8
A69: 1002003001 | B69: ELETRICA, HIDRÁULICA E COMBATE A INCÊNDIO | C69: 25175050 | D69: =_xlfn.XLOOKUP(A69,'[1]CADASTRO CENTRO DE CUSTO-ALOCAÇ'!$A:$A,'[1]CADASTRO CENTRO DE CUSTO-ALOCAÇ'!$C:$C) -> 25175050 | E69: =C69-D69 -> 0 | F69: =SUMIF('Contratos - G200'!E:E,'Detalhamento - G200'!A69,'Contratos - G200'!J:J)+SUMIF('Pedidos - G200'!D:D,'Detalhamento - G200'!A69,'Pedidos - G200'!H:H) -> 23610525 | G69: =C69-F69 -> 1564524.8 | H69: =SUMIF('Notas fiscais - G200'!D:D,'Detalhamento - G200'!A69,'Notas fiscais - G200'!T:T) -> 2492328.6 | I69: =VLOOKUP(A69,'Projeções - G200'!B:F,5,FALSE) -> 0 | J69: =F69+I69 -> 23610525 | K69: =C69-J69 -> 1564524.8
A70: 1003 | B70: HVAC - GALPÃO E MEZANINO | C70: =SUBTOTAL(9,C71:C85) -> 44294933 | D70: =_xlfn.XLOOKUP(A70,'[1]CADASTRO CENTRO DE CUSTO-ALOCAÇ'!$A:$A,'[1]CADASTRO CENTRO DE CUSTO-ALOCAÇ'!$C:$C) -> 44294933 | E70: =C70-D70 -> 0 | F70: =SUBTOTAL(9,F71:F85) -> 42726115 | G70: =SUBTOTAL(9,G71:G85) -> 1568818.5 | H70: =SUBTOTAL(9,H71:H85) -> 8967779.6 | I70: =SUBTOTAL(9,I71:I85) -> -892310.26 | J70: =SUBTOTAL(9,J71:J85) -> 41833805 | K70: =SUBTOTAL(9,K71:K85) -> 2461128.7
A71: 1003001 | B71: EQUIPAMENTOS | C71: =SUBTOTAL(9,C72) -> 12807447 | D71: =_xlfn.XLOOKUP(A71,'[1]CADASTRO CENTRO DE CUSTO-ALOCAÇ'!$A:$A,'[1]CADASTRO CENTRO DE CUSTO-ALOCAÇ'!$C:$C) -> 12807447 | E71: =C71-D71 -> 0 | F71: =SUBTOTAL(9,F72) -> 11915137 | G71: =SUBTOTAL(9,G72) -> 892310.27 | H71: =SUBTOTAL(9,H72) -> 3575077.7 | I71: =SUBTOTAL(9,I72) -> -892310.27 | J71: =SUBTOTAL(9,J72) -> 11022827 | K71: =SUBTOTAL(9,K72) -> 1784620.5
A72: 1003001001 | B72: EQUIPAMENTO | C72: 12807447 | D72: =_xlfn.XLOOKUP(A72,'[1]CADASTRO CENTRO DE CUSTO-ALOCAÇ'!$A:$A,'[1]CADASTRO CENTRO DE CUSTO-ALOCAÇ'!$C:$C) -> 12807447 | E72: =C72-D72 -> 0 | F72: =SUMIF('Contratos - G200'!E:E,'Detalhamento - G200'!A72,'Contratos - G200'!J:J)+SUMIF('Pedidos - G200'!D:D,'Detalhamento - G200'!A72,'Pedidos - G200'!H:H) -> 11915137 | G72: =C72-F72 -> 892310.27 | H72: =SUMIF('Notas fiscais - G200'!D:D,'Detalhamento - G200'!A72,'Notas fiscais - G200'!T:T) -> 3575077.7 | I72: =VLOOKUP(A72,'Projeções - G200'!B:F,5,FALSE) -> -892310.27 | J72: =F72+I72 -> 11022827 | K72: =C72-J72 -> 1784620.5
A73: 1003002 | B73: REDES HIDRÁULICAS | C73: =SUBTOTAL(9,C74:C75) -> 8740881.3 | D73: =_xlfn.XLOOKUP(A73,'[1]CADASTRO CENTRO DE CUSTO-ALOCAÇ'!$A:$A,'[1]CADASTRO CENTRO DE CUSTO-ALOCAÇ'!$C:$C) -> 8740881.3 | E73: =C73-D73 -> 0 | F73: =SUBTOTAL(9,F74:F75) -> 8740881.3 | G73: =SUBTOTAL(9,G74:G75) -> -0.0099999998 | H73: =SUBTOTAL(9,H74:H75) -> 1127043.9 | I73: =SUBTOTAL(9,I74:I75) -> 0.0099999998 | J73: =SUBTOTAL(9,J74:J75) -> 8740881.3 | K73: =SUBTOTAL(9,K74:K75) -> -0.02
A74: 1003002001 | B74: CAVALETES HIDRÁULICOS E VÁLVULAS | C74: 1824735.1 | D74: =_xlfn.XLOOKUP(A74,'[1]CADASTRO CENTRO DE CUSTO-ALOCAÇ'!$A:$A,'[1]CADASTRO CENTRO DE CUSTO-ALOCAÇ'!$C:$C) -> 1824735.1 | E74: =C74-D74 -> 0 | F74: =SUMIF('Contratos - G200'!E:E,'Detalhamento - G200'!A74,'Contratos - G200'!J:J)+SUMIF('Pedidos - G200'!D:D,'Detalhamento - G200'!A74,'Pedidos - G200'!H:H) -> 1824735.1 | G74: =C74-F74 -> 0 | H74: =SUMIF('Notas fiscais - G200'!D:D,'Detalhamento - G200'!A74,'Notas fiscais - G200'!T:T) -> 235202.92 | I74: =VLOOKUP(A74,'Projeções - G200'!B:F,5,FALSE) -> 0 | J74: =F74+I74 -> 1824735.1 | K74: =C74-J74 -> 0
A75: 1003002002 | B75: REDE HIDRÁULICA | C75: 6916146.2 | D75: =_xlfn.XLOOKUP(A75,'[1]CADASTRO CENTRO DE CUSTO-ALOCAÇ'!$A:$A,'[1]CADASTRO CENTRO DE CUSTO-ALOCAÇ'!$C:$C) -> 6916146.2 | E75: =C75-D75 -> 0 | F75: =SUMIF('Contratos - G200'!E:E,'Detalhamento - G200'!A75,'Contratos - G200'!J:J)+SUMIF('Pedidos - G200'!D:D,'Detalhamento - G200'!A75,'Pedidos - G200'!H:H) -> 6916146.3 | G75: =C75-F75 -> -0.0099999998 | H75: =SUMIF('Notas fiscais - G200'!D:D,'Detalhamento - G200'!A75,'Notas fiscais - G200'!T:T) -> 891841.03 | I75: =VLOOKUP(A75,'Projeções - G200'!B:F,5,FALSE) -> 0.0099999998 | J75: =F75+I75 -> 6916146.3 | K75: =C75-J75 -> -0.02
A76: 1003003 | B76: REDES ELÉTRICAS | C76: =SUBTOTAL(9,C77:C78) -> 8331760.8 | D76: =_xlfn.XLOOKUP(A76,'[1]CADASTRO CENTRO DE CUSTO-ALOCAÇ'!$A:$A,'[1]CADASTRO CENTRO DE CUSTO-ALOCAÇ'!$C:$C) -> 8331760.8 | E76: =C76-D76 -> 0 | F76: =SUBTOTAL(9,F77:F78) -> 8331760.8 | G76: =SUBTOTAL(9,G77:G78) -> 0 | H76: =SUBTOTAL(9,H77:H78) -> 2206471.5 | I76: =SUBTOTAL(9,I77:I78) -> 0 | J76: =SUBTOTAL(9,J77:J78) -> 8331760.8 | K76: =SUBTOTAL(9,K77:K78) -> 0
A77: 1003003001 | B77: QUADROS ELÉTRICOS E AUTOMAÇÃO | C77: 3616579.1 | D77: =_xlfn.XLOOKUP(A77,'[1]CADASTRO CENTRO DE CUSTO-ALOCAÇ'!$A:$A,'[1]CADASTRO CENTRO DE CUSTO-ALOCAÇ'!$C:$C) -> 3616579.1 | E77: =C77-D77 -> 0 | F77: =SUMIF('Contratos - G200'!E:E,'Detalhamento - G200'!A77,'Contratos - G200'!J:J)+SUMIF('Pedidos - G200'!D:D,'Detalhamento - G200'!A77,'Pedidos - G200'!H:H) -> 3616579.1 | G77: =C77-F77 -> 0 | H77: =SUMIF('Notas fiscais - G200'!D:D,'Detalhamento - G200'!A77,'Notas fiscais - G200'!T:T) -> 971381.53 | I77: =VLOOKUP(A77,'Projeções - G200'!B:F,5,FALSE) -> 0 | J77: =F77+I77 -> 3616579.1 | K77: =C77-J77 -> 0
A78: 1003003002 | B78: INTERLIGAÇÕES ELÉTRICAS | C78: 4715181.7 | D78: =_xlfn.XLOOKUP(A78,'[1]CADASTRO CENTRO DE CUSTO-ALOCAÇ'!$A:$A,'[1]CADASTRO CENTRO DE CUSTO-ALOCAÇ'!$C:$C) -> 4715181.7 | E78: =C78-D78 -> 0 | F78: =SUMIF('Contratos - G200'!E:E,'Detalhamento - G200'!A78,'Contratos - G200'!J:J)+SUMIF('Pedidos - G200'!D:D,'Detalhamento - G200'!A78,'Pedidos - G200'!H:H) -> 4715181.7 | G78: =C78-F78 -> 0 | H78: =SUMIF('Notas fiscais - G200'!D:D,'Detalhamento - G200'!A78,'Notas fiscais - G200'!T:T) -> 1235090 | I78: =VLOOKUP(A78,'Projeções - G200'!B:F,5,FALSE) -> 0 | J78: =F78+I78 -> 4715181.7 | K78: =C78-J78 -> 0
A79: 1003004 | B79: REDES DE DUTOS E DIFUSÃO | C79: =SUBTOTAL(9,C80:C81) -> 10910524 | D79: =_xlfn.XLOOKUP(A79,'[1]CADASTRO CENTRO DE CUSTO-ALOCAÇ'!$A:$A,'[1]CADASTRO CENTRO DE CUSTO-ALOCAÇ'!$C:$C) -> 10910524 | E79: =C79-D79 -> 0 | F79: =SUBTOTAL(9,F80:F81) -> 10910524 | G79: =SUBTOTAL(9,G80:G81) -> -6.9849193e-10 | H79: =SUBTOTAL(9,H80:H81) -> 1127289.7 | I79: =SUBTOTAL(9,I80:I81) -> 6.9900352e-10 | J79: =SUBTOTAL(9,J80:J81) -> 10910524 | K79: =SUBTOTAL(9,K80:K81) -> -1.3969839e-09
A80: 1003004001 | B80: REDES DE DUTOS | C80: 9431584.8 | D80: =_xlfn.XLOOKUP(A80,'[1]CADASTRO CENTRO DE CUSTO-ALOCAÇ'!$A:$A,'[1]CADASTRO CENTRO DE CUSTO-ALOCAÇ'!$C:$C) -> 9431584.8 | E80: =C80-D80 -> 0 | F80: =SUMIF('Contratos - G200'!E:E,'Detalhamento - G200'!A80,'Contratos - G200'!J:J)+SUMIF('Pedidos - G200'!D:D,'Detalhamento - G200'!A80,'Pedidos - G200'!H:H) -> 9431821.2 | G80: =C80-F80 -> -236.38 | H80: =SUMIF('Notas fiscais - G200'!D:D,'Detalhamento - G200'!A80,'Notas fiscais - G200'!T:T) -> 916244.93 | I80: =VLOOKUP(A80,'Projeções - G200'!B:F,5,FALSE) -> 236.38 | J80: =F80+I80 -> 9432057.6 | K80: =C80-J80 -> -472.76
A81: 1003004002 | B81: DIFUSÃO | C81: 1478939.4 | D81: =_xlfn.XLOOKUP(A81,'[1]CADASTRO CENTRO DE CUSTO-ALOCAÇ'!$A:$A,'[1]CADASTRO CENTRO DE CUSTO-ALOCAÇ'!$C:$C) -> 1478939.4 | E81: =C81-D81 -> 0 | F81: =SUMIF('Contratos - G200'!E:E,'Detalhamento - G200'!A81,'Contratos - G200'!J:J)+SUMIF('Pedidos - G200'!D:D,'Detalhamento - G200'!A81,'Pedidos - G200'!H:H) -> 1478703 | G81: =C81-F81 -> 236.38 | H81: =SUMIF('Notas fiscais - G200'!D:D,'Detalhamento - G200'!A81,'Notas fiscais - G200'!T:T) -> 211044.78 | I81: =VLOOKUP(A81,'Projeções - G200'!B:F,5,FALSE) -> -236.38 | J81: =F81+I81 -> 1478466.6 | K81: =C81-J81 -> 472.76
A82: 1003005 | B82: SERVIÇOS CIVIS | C82: =SUBTOTAL(9,C83) -> 2566738.3 | D82: =_xlfn.XLOOKUP(A82,'[1]CADASTRO CENTRO DE CUSTO-ALOCAÇ'!$A:$A,'[1]CADASTRO CENTRO DE CUSTO-ALOCAÇ'!$C:$C) -> 2566738.3 | E82: =C82-D82 -> 0 | F82: =SUBTOTAL(9,F83) -> 1890230.1 | G82: =SUBTOTAL(9,G83) -> 676508.21 | H82: =SUBTOTAL(9,H83) -> 64700.01 | I82: =SUBTOTAL(9,I83) -> 0 | J82: =SUBTOTAL(9,J83) -> 1890230.1 | K82: =SUBTOTAL(9,K83) -> 676508.21
A83: 1003005001 | B83: SERVIÇO CIVIL | C83: 2566738.3 | D83: =_xlfn.XLOOKUP(A83,'[1]CADASTRO CENTRO DE CUSTO-ALOCAÇ'!$A:$A,'[1]CADASTRO CENTRO DE CUSTO-ALOCAÇ'!$C:$C) -> 2566738.3 | E83: =C83-D83 -> 0 | F83: =SUMIF('Contratos - G200'!E:E,'Detalhamento - G200'!A83,'Contratos - G200'!J:J)+SUMIF('Pedidos - G200'!D:D,'Detalhamento - G200'!A83,'Pedidos - G200'!H:H) -> 1890230.1 | G83: =C83-F83 -> 676508.21 | H83: =SUMIF('Notas fiscais - G200'!D:D,'Detalhamento - G200'!A83,'Notas fiscais - G200'!T:T) -> 64700.01 | I83: =VLOOKUP(A83,'Projeções - G200'!B:F,5,FALSE) -> 0 | J83: =F83+I83 -> 1890230.1 | K83: =C83-J83 -> 676508.21
A84: 1003006 | B84: PROJETOS, CQPS E ASBUILT | C84: =SUBTOTAL(9,C85) -> 937581.62 | D84: =_xlfn.XLOOKUP(A84,'[1]CADASTRO CENTRO DE CUSTO-ALOCAÇ'!$A:$A,'[1]CADASTRO CENTRO DE CUSTO-ALOCAÇ'!$C:$C) -> 937581.62 | E84: =C84-D84 -> 0 | F84: =SUBTOTAL(9,F85) -> 937581.62 | G84: =SUBTOTAL(9,G85) -> 0 | H84: =SUBTOTAL(9,H85) -> 867196.79 | I84: =SUBTOTAL(9,I85) -> 0 | J84: =SUBTOTAL(9,J85) -> 937581.62 | K84: =SUBTOTAL(9,K85) -> 0
A85: 1003006001 | B85: PROJETOS, CQPS E AS BUILT | C85: 937581.62 | D85: =_xlfn.XLOOKUP(A85,'[1]CADASTRO CENTRO DE CUSTO-ALOCAÇ'!$A:$A,'[1]CADASTRO CENTRO DE CUSTO-ALOCAÇ'!$C:$C) -> 937581.62 | E85: =C85-D85 -> 0 | F85: =SUMIF('Contratos - G200'!E:E,'Detalhamento - G200'!A85,'Contratos - G200'!J:J)+SUMIF('Pedidos - G200'!D:D,'Detalhamento - G200'!A85,'Pedidos - G200'!H:H) -> 937581.62 | G85: =C85-F85 -> 0 | H85: =SUMIF('Notas fiscais - G200'!D:D,'Detalhamento - G200'!A85,'Notas fiscais - G200'!T:T) -> 867196.79 | I85: =VLOOKUP(A85,'Projeções - G200'!B:F,5,FALSE) -> 0 | J85: =F85+I85 -> 937581.62 | K85: =C85-J85 -> 0
A86: 1004 | B86: CAPEX | C86: =SUBTOTAL(9,C87:C104) -> 4448328.9 | D86: =_xlfn.XLOOKUP(A86,'[1]CADASTRO CENTRO DE CUSTO-ALOCAÇ'!$A:$A,'[1]CADASTRO CENTRO DE CUSTO-ALOCAÇ'!$C:$C) -> 4448328.9 | E86: =C86-D86 -> 0 | F86: =SUBTOTAL(9,F87:F104) -> 2166011.7 | G86: =SUBTOTAL(9,G87:G104) -> 2282317.2 | H86: =SUBTOTAL(9,H87:H104) -> 253572.99 | I86: =SUBTOTAL(9,I87:I104) -> -9000 | J86: =SUBTOTAL(9,J87:J104) -> 2157011.7 | K86: =SUBTOTAL(9,K87:K104) -> 2291317.2
A87: 1004001 | B87: CAPEX MELI | C87: =SUBTOTAL(9,C88:C92) -> 2203988.7 | D87: =_xlfn.XLOOKUP(A87,'[1]CADASTRO CENTRO DE CUSTO-ALOCAÇ'!$A:$A,'[1]CADASTRO CENTRO DE CUSTO-ALOCAÇ'!$C:$C) -> 2203988.7 | E87: =C87-D87 -> 0 | F87: =SUBTOTAL(9,F88:F92) -> 1849458.2 | G87: =SUBTOTAL(9,G88:G92) -> 354530.48 | H87: =SUBTOTAL(9,H88:H92) -> 127000.44 | I87: =SUBTOTAL(9,I88:I92) -> -9000 | J87: =SUBTOTAL(9,J88:J92) -> 1840458.2 | K87: =SUBTOTAL(9,K88:K92) -> 363530.48
A88: 1004001001 | B88: POÇO E ALVENARIAS PERIFÉRICAS - ELEVADOR | C88: 40000 | D88: =_xlfn.XLOOKUP(A88,'[1]CADASTRO CENTRO DE CUSTO-ALOCAÇ'!$A:$A,'[1]CADASTRO CENTRO DE CUSTO-ALOCAÇ'!$C:$C) -> 40000 | E88: =C88-D88 -> 0 | F88: =SUMIF('Contratos - G200'!E:E,'Detalhamento - G200'!A88,'Contratos - G200'!J:J)+SUMIF('Pedidos - G200'!D:D,'Detalhamento - G200'!A88,'Pedidos - G200'!H:H) -> 0 | G88: =C88-F88 -> 40000 | H88: =SUMIF('Notas fiscais - G200'!D:D,'Detalhamento - G200'!A88,'Notas fiscais - G200'!T:T) -> 0 | I88: =VLOOKUP(A88,'Projeções - G200'!B:F,5,FALSE) -> 0 | J88: =F88+I88 -> 0 | K88: =C88-J88 -> 40000
A89: 1004001002 | B89: ELEVADOR MEZANINO | C89: 180000 | D89: =_xlfn.XLOOKUP(A89,'[1]CADASTRO CENTRO DE CUSTO-ALOCAÇ'!$A:$A,'[1]CADASTRO CENTRO DE CUSTO-ALOCAÇ'!$C:$C) -> 180000 | E89: =C89-D89 -> 0 | F89: =SUMIF('Contratos - G200'!E:E,'Detalhamento - G200'!A89,'Contratos - G200'!J:J)+SUMIF('Pedidos - G200'!D:D,'Detalhamento - G200'!A89,'Pedidos - G200'!H:H) -> 171000 | G89: =C89-F89 -> 9000 | H89: =SUMIF('Notas fiscais - G200'!D:D,'Detalhamento - G200'!A89,'Notas fiscais - G200'!T:T) -> 101745 | I89: =VLOOKUP(A89,'Projeções - G200'!B:F,5,FALSE) -> -9000 | J89: =F89+I89 -> 162000 | K89: =C89-J89 -> 18000
A90: 1004001003 | B90: AUMENTO DO LUX DA ÁREA EXTERNA | C90: 178456.92 | D90: =_xlfn.XLOOKUP(A90,'[1]CADASTRO CENTRO DE CUSTO-ALOCAÇ'!$A:$A,'[1]CADASTRO CENTRO DE CUSTO-ALOCAÇ'!$C:$C) -> 178456.92 | E90: =C90-D90 -> 0 | F90: =SUMIF('Contratos - G200'!E:E,'Detalhamento - G200'!A90,'Contratos - G200'!J:J)+SUMIF('Pedidos - G200'!D:D,'Detalhamento - G200'!A90,'Pedidos - G200'!H:H) -> 174426.45 | G90: =C90-F90 -> 4030.4664 | H90: =SUMIF('Notas fiscais - G200'!D:D,'Detalhamento - G200'!A90,'Notas fiscais - G200'!T:T) -> 0 | I90: =VLOOKUP(A90,'Projeções - G200'!B:F,5,FALSE) -> 0 | J90: =F90+I90 -> 174426.45 | K90: =C90-J90 -> 4030.4664
A91: 1004001004 | B91: HVAC - COZINHA E REFEITÓRIO | C91: 1504031.8 | D91: =_xlfn.XLOOKUP(A91,'[1]CADASTRO CENTRO DE CUSTO-ALOCAÇ'!$A:$A,'[1]CADASTRO CENTRO DE CUSTO-ALOCAÇ'!$C:$C) -> 1504031.8 | E91: =C91-D91 -> 0 | F91: =SUMIF('Contratos - G200'!E:E,'Detalhamento - G200'!A91,'Contratos - G200'!J:J)+SUMIF('Pedidos - G200'!D:D,'Detalhamento - G200'!A91,'Pedidos - G200'!H:H) -> 1504031.7 | G91: =C91-F91 -> 0.01 | H91: =SUMIF('Notas fiscais - G200'!D:D,'Detalhamento - G200'!A91,'Notas fiscais - G200'!T:T) -> 25255.44 | I91: =VLOOKUP(A91,'Projeções - G200'!B:F,5,FALSE) -> 0 | J91: =F91+I91 -> 1504031.7 | K91: =C91-J91 -> 0.01
A92: 1004001005 | B92: CÂMARA FRIA - COZINHA INDUSTRIAL | C92: 301500 | D92: =_xlfn.XLOOKUP(A92,'[1]CADASTRO CENTRO DE CUSTO-ALOCAÇ'!$A:$A,'[1]CADASTRO CENTRO DE CUSTO-ALOCAÇ'!$C:$C) -> 301500 | E92: =C92-D92 -> 0 | F92: =SUMIF('Contratos - G200'!E:E,'Detalhamento - G200'!A92,'Contratos - G200'!J:J)+SUMIF('Pedidos - G200'!D:D,'Detalhamento - G200'!A92,'Pedidos - G200'!H:H) -> 0 | G92: =C92-F92 -> 301500 | H92: =SUMIF('Notas fiscais - G200'!D:D,'Detalhamento - G200'!A92,'Notas fiscais - G200'!T:T) -> 0 | I92: =VLOOKUP(A92,'Projeções - G200'!B:F,5,FALSE) -> 0 | J92: =F92+I92 -> 0 | K92: =C92-J92 -> 301500
A93: 1004002 | B93: ESPECIFIDADES LYON | C93: =SUBTOTAL(9,C94:C104) -> 2244340.2 | D93: =_xlfn.XLOOKUP(A93,'[1]CADASTRO CENTRO DE CUSTO-ALOCAÇ'!$A:$A,'[1]CADASTRO CENTRO DE CUSTO-ALOCAÇ'!$C:$C) -> 2244340.2 | E93: =C93-D93 -> 0 | F93: =SUBTOTAL(9,F94:F104) -> 316553.54 | G93: =SUBTOTAL(9,G94:G104) -> 1927786.7 | H93: =SUBTOTAL(9,H94:H104) -> 126572.55 | I93: =SUBTOTAL(9,I94:I104) -> 0 | J93: =SUBTOTAL(9,J94:J104) -> 316553.54 | K93: =SUBTOTAL(9,K94:K104) -> 1927786.7
A94: 1004002001 | B94: INCLUSÃO DE JUNTAS EPÓXIS SEMIRRÍGIDAS EM 100% DAS JUNTAS SERRADAS | C94: 552250 | D94: =_xlfn.XLOOKUP(A94,'[1]CADASTRO CENTRO DE CUSTO-ALOCAÇ'!$A:$A,'[1]CADASTRO CENTRO DE CUSTO-ALOCAÇ'!$C:$C) -> 552250 | E94: =C94-D94 -> 0 | F94: =SUMIF('Contratos - G200'!E:E,'Detalhamento - G200'!A94,'Contratos - G200'!J:J)+SUMIF('Pedidos - G200'!D:D,'Detalhamento - G200'!A94,'Pedidos - G200'!H:H) -> 0 | G94: =C94-F94 -> 552250 | H94: =SUMIF('Notas fiscais - G200'!D:D,'Detalhamento - G200'!A94,'Notas fiscais - G200'!T:T) -> 0 | I94: =VLOOKUP(A94,'Projeções - G200'!B:F,5,FALSE) -> 0 | J94: =F94+I94 -> 0 | K94: =C94-J94 -> 552250
A95: 1004002002 | B95: AUMENTO DA LARGURA DA RAMPA DE ACESSO DE EMPILHADEIRA DE 4,00 PARA 5,00 M | C95: 41260 | D95: =_xlfn.XLOOKUP(A95,'[1]CADASTRO CENTRO DE CUSTO-ALOCAÇ'!$A:$A,'[1]CADASTRO CENTRO DE CUSTO-ALOCAÇ'!$C:$C) -> 41260 | E95: =C95-D95 -> 0 | F95: =SUMIF('Contratos - G200'!E:E,'Detalhamento - G200'!A95,'Contratos - G200'!J:J)+SUMIF('Pedidos - G200'!D:D,'Detalhamento - G200'!A95,'Pedidos - G200'!H:H) -> 0 | G95: =C95-F95 -> 41260 | H95: =SUMIF('Notas fiscais - G200'!D:D,'Detalhamento - G200'!A95,'Notas fiscais - G200'!T:T) -> 0 | I95: =VLOOKUP(A95,'Projeções - G200'!B:F,5,FALSE) -> 0 | J95: =F95+I95 -> 0 | K95: =C95-J95 -> 41260
A96: 1004002003 | B96: BOLLARDS DE PROTEÇÃO PARA QUADROS (2 POR QUADRO) | C96: 63606.44 | D96: =_xlfn.XLOOKUP(A96,'[1]CADASTRO CENTRO DE CUSTO-ALOCAÇ'!$A:$A,'[1]CADASTRO CENTRO DE CUSTO-ALOCAÇ'!$C:$C) -> 63606.44 | E96: =C96-D96 -> 0 | F96: =SUMIF('Contratos - G200'!E:E,'Detalhamento - G200'!A96,'Contratos - G200'!J:J)+SUMIF('Pedidos - G200'!D:D,'Detalhamento - G200'!A96,'Pedidos - G200'!H:H) -> 0 | G96: =C96-F96 -> 63606.44 | H96: =SUMIF('Notas fiscais - G200'!D:D,'Detalhamento - G200'!A96,'Notas fiscais - G200'!T:T) -> 0 | I96: =VLOOKUP(A96,'Projeções - G200'!B:F,5,FALSE) -> 0 | J96: =F96+I96 -> 0 | K96: =C96-J96 -> 63606.44
A97: 1004002004 | B97: MARQUISE DE ENTRADA MELI - TESTEIRA ACM | C97: 90000 | D97: =_xlfn.XLOOKUP(A97,'[1]CADASTRO CENTRO DE CUSTO-ALOCAÇ'!$A:$A,'[1]CADASTRO CENTRO DE CUSTO-ALOCAÇ'!$C:$C) -> 90000 | E97: =C97-D97 -> 0 | F97: =SUMIF('Contratos - G200'!E:E,'Detalhamento - G200'!A97,'Contratos - G200'!J:J)+SUMIF('Pedidos - G200'!D:D,'Detalhamento - G200'!A97,'Pedidos - G200'!H:H) -> 0 | G97: =C97-F97 -> 90000 | H97: =SUMIF('Notas fiscais - G200'!D:D,'Detalhamento - G200'!A97,'Notas fiscais - G200'!T:T) -> 0 | I97: =VLOOKUP(A97,'Projeções - G200'!B:F,5,FALSE) -> 0 | J97: =F97+I97 -> 0 | K97: =C97-J97 -> 90000
A98: 1004002005 | B98: MARQUISE DE ENTRADA MELI - FORRO ACM | C98: 75000 | D98: =_xlfn.XLOOKUP(A98,'[1]CADASTRO CENTRO DE CUSTO-ALOCAÇ'!$A:$A,'[1]CADASTRO CENTRO DE CUSTO-ALOCAÇ'!$C:$C) -> 75000 | E98: =C98-D98 -> 0 | F98: =SUMIF('Contratos - G200'!E:E,'Detalhamento - G200'!A98,'Contratos - G200'!J:J)+SUMIF('Pedidos - G200'!D:D,'Detalhamento - G200'!A98,'Pedidos - G200'!H:H) -> 0 | G98: =C98-F98 -> 75000 | H98: =SUMIF('Notas fiscais - G200'!D:D,'Detalhamento - G200'!A98,'Notas fiscais - G200'!T:T) -> 0 | I98: =VLOOKUP(A98,'Projeções - G200'!B:F,5,FALSE) -> 0 | J98: =F98+I98 -> 0 | K98: =C98-J98 -> 75000
A99: 1004002006 | B99: PASSARELAS DE PEDESTRE/ÔNIBUS - TESTEIRA RAL 5022 | C99: 75000 | D99: =_xlfn.XLOOKUP(A99,'[1]CADASTRO CENTRO DE CUSTO-ALOCAÇ'!$A:$A,'[1]CADASTRO CENTRO DE CUSTO-ALOCAÇ'!$C:$C) -> 75000 | E99: =C99-D99 -> 0 | F99: =SUMIF('Contratos - G200'!E:E,'Detalhamento - G200'!A99,'Contratos - G200'!J:J)+SUMIF('Pedidos - G200'!D:D,'Detalhamento - G200'!A99,'Pedidos - G200'!H:H) -> 74630.86 | G99: =C99-F99 -> 369.14 | H99: =SUMIF('Notas fiscais - G200'!D:D,'Detalhamento - G200'!A99,'Notas fiscais - G200'!T:T) -> 0 | I99: =VLOOKUP(A99,'Projeções - G200'!B:F,5,FALSE) -> 0 | J99: =F99+I99 -> 74630.86 | K99: =C99-J99 -> 369.14
A100: 1004002007 | B100: PASSARELAS DE PEDESTRE/ÔNIBUS - CALHA | C100: 75000 | D100: =_xlfn.XLOOKUP(A100,'[1]CADASTRO CENTRO DE CUSTO-ALOCAÇ'!$A:$A,'[1]CADASTRO CENTRO DE CUSTO-ALOCAÇ'!$C:$C) -> 75000 | E100: =C100-D100 -> 0 | F100: =SUMIF('Contratos - G200'!E:E,'Detalhamento - G200'!A100,'Contratos - G200'!J:J)+SUMIF('Pedidos - G200'!D:D,'Detalhamento - G200'!A100,'Pedidos - G200'!H:H) -> 74630.86 | G100: =C100-F100 -> 369.14 | H100: =SUMIF('Notas fiscais - G200'!D:D,'Detalhamento - G200'!A100,'Notas fiscais - G200'!T:T) -> 0 | I100: =VLOOKUP(A100,'Projeções - G200'!B:F,5,FALSE) -> 0 | J100: =F100+I100 -> 74630.86 | K100: =C100-J100 -> 369.14
A101: 1004002008 | B101: PASSARELAS DE PEDESTRE/ÔNIBUS - SISTEMA DE DRENAGEM | C101: 90000 | D101: =_xlfn.XLOOKUP(A101,'[1]CADASTRO CENTRO DE CUSTO-ALOCAÇ'!$A:$A,'[1]CADASTRO CENTRO DE CUSTO-ALOCAÇ'!$C:$C) -> 90000 | E101: =C101-D101 -> 0 | F101: =SUMIF('Contratos - G200'!E:E,'Detalhamento - G200'!A101,'Contratos - G200'!J:J)+SUMIF('Pedidos - G200'!D:D,'Detalhamento - G200'!A101,'Pedidos - G200'!H:H) -> 0 | G101: =C101-F101 -> 90000 | H101: =SUMIF('Notas fiscais - G200'!D:D,'Detalhamento - G200'!A101,'Notas fiscais - G200'!T:T) -> 0 | I101: =VLOOKUP(A101,'Projeções - G200'!B:F,5,FALSE) -> 0 | J101: =F101+I101 -> 0 | K101: =C101-J101 -> 90000
...

Sheet Pedidos - G200
I1: BASE SIENGE | J1: MÊS
B2: Instruções: | C2: No Sienge (Suprimentos / Contratos e Medições / Relatórios / Contratos / Faturamentos diretos);
C3: Obras 152/ Consultar / Gerar relatório excel;
B4: Observação: | C4: Esta planilha serva para a aba "analítico" não duplicar os custos, ou seja, para não associar as notas como uma nova contratação e estourar um saldo já contratado. Não preencher a coluna "F" com absolutamente nenhum caracter se não for vinculado a um contrato
I5: 32280 | J5: Fev
I6: 5422769.2 | J6: março
I7: 14890073 | J7: abril
J8: maio
D11: TOTAL | F11: =SUBTOTAL(9,F14:F1048576) -> 26099070 | G11: =F11-H11 -> 15635731 | H11: =SUBTOTAL(9,H14:H1048576) -> 10463339
A13: MÊS | B13: PEDIDO | C13: CREDOR | D13: APROPRIAÇÃO | E13: DESCRIÇÃO DA EAP | F13: VALOR | G13: VÍNCULO DE FATURAMENTO DIRETO | H13: VALOR À CONSIDERAR
A14: Fev | B14: PPC/25660 | C14: SOLUCAO TOLDOS EIRELI | D14: 2001001007 | E14: =_xlfn.XLOOKUP(D14,'Detalhamento - G200'!A:A,'Detalhamento - G200'!B:B,0) -> LOCAÇÃO DE TOLDO | F14: =32280 -> 32280 | H14: =IF(G14<>"",0,F14) -> 32280
A15: Mar | B15: PPC/26418 | C15: HIDRO LOGICA CONSULTORIA E TREINAMENTO LTDA | D15: 1001001001 | E15: =_xlfn.XLOOKUP(D15,'Detalhamento - G200'!A:A,'Detalhamento - G200'!B:B,0) -> PROJETOS | F15: 7000 | H15: =IF(G15<>"",0,F15) -> 7000
A16: Mar | B16: PPC/26511 | C16: A J S SOUZA SERVICOS GRAFICOS | D16: 2001001006 | E16: =_xlfn.XLOOKUP(D16,'Detalhamento - G200'!A:A,'Detalhamento - G200'!B:B,0) -> IMPLANTAÇÃO DE CANTEIRO - CIVIL | F16: 11921 | H16: =IF(G16<>"",0,F16) -> 11921
A17: Mar | B17: PPC/26526 | C17: HD MORENO - COMÉRCIO E SERVIÇOS METALURGICOS EIRELI | D17: 1001003002 | E17: =_xlfn.XLOOKUP(D17,'Detalhamento - G200'!A:A,'Detalhamento - G200'!B:B,0) -> SUPERESTRUTURA GALPÃO | F17: 3350 | H17: =IF(G17<>"",0,F17) -> 3350
A18: Mar | B18: PPC/26527 | C18: PARATEC - PARA RAIOS E ACESSORIOS LTDA | D18: 1001003002 | E18: =_xlfn.XLOOKUP(D18,'Detalhamento - G200'!A:A,'Detalhamento - G200'!B:B,0) -> SUPERESTRUTURA GALPÃO | F18: 23458 | H18: =IF(G18<>"",0,F18) -> 23458
A19: Mar | B19: PPC/26557 | C19: GENERAL WIRING DO BRASIL INDUSTRIA E COMERCIO EIRELI | D19: 1001002006 | E19: =_xlfn.XLOOKUP(D19,'Detalhamento - G200'!A:A,'Detalhamento - G200'!B:B,0) -> CONTENÇÕES | F19: 3111.6 | G19: CLSF/200-3-039 | H19: =IF(G19<>"",0,F19) -> 0
A20: Mar | B20: PPC/26562 | C20: FORTLEV INDUSTRIA E COMERCIO DE PLASTICOS LTDA | D20: 1001002006 | E20: =_xlfn.XLOOKUP(D20,'Detalhamento - G200'!A:A,'Detalhamento - G200'!B:B,0) -> CONTENÇÕES | F20: 10620.67 | G20: CLSF/200-3-039 | H20: =IF(G20<>"",0,F20) -> 0
A21: Mar | B21: PPC/26564 | C21: ANTONIO CARDOSO MARTINS | D21: 1001002006 | E21: =_xlfn.XLOOKUP(D21,'Detalhamento - G200'!A:A,'Detalhamento - G200'!B:B,0) -> CONTENÇÕES | F21: 34650 | G21: CLSF/200-3-039 | H21: =IF(G21<>"",0,F21) -> 0
A22: Mar | B22: PPC/26565 | C22: ADUANA COMERCIO DE GEOSSINTETICOS LTDA | D22: 1001002006 | E22: =_xlfn.XLOOKUP(D22,'Detalhamento - G200'!A:A,'Detalhamento - G200'!B:B,0) -> CONTENÇÕES | F22: 4972 | G22: CLSF/200-3-039 | H22: =IF(G22<>"",0,F22) -> 0
A23: Mar | B23: PPC/26595 | C23: GERACAO E ENERGIA SERVICOS E COMERCIO LTDA | D23: 2001001003 | E23: =_xlfn.XLOOKUP(D23,'Detalhamento - G200'!A:A,'Detalhamento - G200'!B:B,0) -> GERADOR BACK-UP | F23: 9000 | H23: =IF(G23<>"",0,F23) -> 9000
A24: Mar | B24: PPC/26618 | C24: BAHIATECH MATERIAIS ELETRICOS LTDA | D24: 2001001002 | E24: =_xlfn.XLOOKUP(D24,'Detalhamento - G200'!A:A,'Detalhamento - G200'!B:B,0) -> IMPLANTAÇÃO DE CANTEIRO - ELETRICA | F24: 6620.16 | H24: =IF(G24<>"",0,F24) -> 6620.16
A25: Mar | B25: PPC/26652 | C25: TRAPICHE MINERACAO LTDA | D25: 1001002006 | E25: =_xlfn.XLOOKUP(D25,'Detalhamento - G200'!A:A,'Detalhamento - G200'!B:B,0) -> CONTENÇÕES | F25: 115500 | G25: CLSF/200-3-039 | H25: =IF(G25<>"",0,F25) -> 0
A26: Mar | B26: PPC/26680 | C26: TERRAM ENGENHARIA DE INFRAESTRUTURA LTDA | D26: 1001002003 | E26: =_xlfn.XLOOKUP(D26,'Detalhamento - G200'!A:A,'Detalhamento - G200'!B:B,0) -> MOVIMENTAÇÃO DE TERRA | F26: 2176885.7 | H26: =IF(G26<>"",0,F26) -> 2176885.7
A27: Mar | B27: PPC/26833 | C27: FORTPEL COMERCIO DE DESCARTAVEIS LTDA | D27: 2001008001 | E27: =_xlfn.XLOOKUP(D27,'Detalhamento - G200'!A:A,'Detalhamento - G200'!B:B,0) -> MATERIAIS DE COPA E LIMPEZA | F27: 1367.37 | H27: =IF(G27<>"",0,F27) -> 1367.37
A28: Mar | B28: PPC/26837 | C28: MARTINS E SILVA COMERCIO DE MERCADORIAS LTDA | D28: 2001008001 | E28: =_xlfn.XLOOKUP(D28,'Detalhamento - G200'!A:A,'Detalhamento - G200'!B:B,0) -> MATERIAIS DE COPA E LIMPEZA | F28: 3114.11 | H28: =IF(G28<>"",0,F28) -> 3114.11
A29: Mar | B29: PPC/26837 | C29: MARTINS E SILVA COMERCIO DE MERCADORIAS LTDA | D29: 1001006003 | E29: =_xlfn.XLOOKUP(D29,'Detalhamento - G200'!A:A,'Detalhamento - G200'!B:B,0) -> POÇO ARTESIANO | F29: 747 | H29: =IF(G29<>"",0,F29) -> 747
A30: Mar | B30: PPC/26877 | C30: CABOS E LAMPADAS COMERCIO DE MATERIAS ELETRICOS DE ALTA E BAIXA TENSAO EIRELI | D30: 2001001002 | E30: =_xlfn.XLOOKUP(D30,'Detalhamento - G200'!A:A,'Detalhamento - G200'!B:B,0) -> IMPLANTAÇÃO DE CANTEIRO - ELETRICA | F30: 183.06 | H30: =IF(G30<>"",0,F30) -> 183.06
A31: Mar | B31: PPC/26904 | C31: ELIZABETH CIMENTOS S/A | D31: 1001002006 | E31: =_xlfn.XLOOKUP(D31,'Detalhamento - G200'!A:A,'Detalhamento - G200'!B:B,0) -> CONTENÇÕES | F31: 115640 | G31: CLSF/200-3-039 | H31: =IF(G31<>"",0,F31) -> 0
A32: Mar | B32: PPC/26916 | C32: ALBERTO JOSE DOS SANTOS | D32: 2001004001 | E32: =_xlfn.XLOOKUP(D32,'Detalhamento - G200'!A:A,'Detalhamento - G200'!B:B,0) -> LOCAÇÃO DE MUNCK | F32: 8800 | H32: =IF(G32<>"",0,F32) -> 8800
A33: Mar | B33: PPC/26921 | C33: F & S MATERIAIS DE CONSTRUCAO EIRELI | D33: 2001001005 | E33: =_xlfn.XLOOKUP(D33,'Detalhamento - G200'!A:A,'Detalhamento - G200'!B:B,0) -> IMPLANTAÇÃO DE CANTEIRO - HIDRÁULICA | F33: 504.3 | H33: =IF(G33<>"",0,F33) -> 504.3
A34: Mar | B34: PPC/26922 | C34: A & A FERRAGEM LTDA | D34: 1002002001 | E34: =_xlfn.XLOOKUP(D34,'Detalhamento - G200'!A:A,'Detalhamento - G200'!B:B,0) -> FUNDAÇÃO | F34: 288 | H34: =IF(G34<>"",0,F34) -> 288
A35: Mar | B35: PPC/26925 | C35: TRANSPOL - DERIVADOS DE PETROLEO LTDA | D35: 1001002003 | E35: =_xlfn.XLOOKUP(D35,'Detalhamento - G200'!A:A,'Detalhamento - G200'!B:B,0) -> MOVIMENTAÇÃO DE TERRA | F35: 1380324.5 | G35: CLSF/200-3-015 | H35: =IF(G35<>"",0,F35) -> 0
A36: Mar | B36: PPC/26926 | C36: TRANSPORTADORA DE DIESEL CAVALO MARINHO LTDA | D36: 1001002003 | E36: =_xlfn.XLOOKUP(D36,'Detalhamento - G200'!A:A,'Detalhamento - G200'!B:B,0) -> MOVIMENTAÇÃO DE TERRA | F36: 1380324.5 | G36: CLSF/200-3-015 | H36: =IF(G36<>"",0,F36) -> 0
A37: Mar | B37: PPC/26929 | C37: PEDREIRAS CARANGI LTDA | D37: 1001002006 | E37: =_xlfn.XLOOKUP(D37,'Detalhamento - G200'!A:A,'Detalhamento - G200'!B:B,0) -> CONTENÇÕES | F37: 7920 | G37: CLSF/200-3-039 | H37: =IF(G37<>"",0,F37) -> 0
A38: Mar | B38: PPC/26929 | C38: PEDREIRAS CARANGI LTDA | D38: 1001002003 | E38: =_xlfn.XLOOKUP(D38,'Detalhamento - G200'!A:A,'Detalhamento - G200'!B:B,0) -> MOVIMENTAÇÃO DE TERRA | F38: 13580 | H38: =IF(G38<>"",0,F38) -> 13580
A39: Mar | B39: PPC/26929 | C39: PEDREIRAS CARANGI LTDA | D39: 1001002003 | E39: =_xlfn.XLOOKUP(D39,'Detalhamento - G200'!A:A,'Detalhamento - G200'!B:B,0) -> MOVIMENTAÇÃO DE TERRA | F39: 71780 | H39: =IF(G39<>"",0,F39) -> 71780
A40: Mar | B40: PPC/26936 | C40: PARATEC - PARA RAIOS E ACESSORIOS LTDA | D40: 1001003002 | E40: =_xlfn.XLOOKUP(D40,'Detalhamento - G200'!A:A,'Detalhamento - G200'!B:B,0) -> SUPERESTRUTURA GALPÃO | F40: 5933 | H40: =IF(G40<>"",0,F40) -> 5933
A41: Mar | B41: PPC/26949 | C41: LESSA EVENTOS LTDA | D41: 1001001002 | E41: =_xlfn.XLOOKUP(D41,'Detalhamento - G200'!A:A,'Detalhamento - G200'!B:B,0) -> ENSAIOS E CONSULTORIAS | F41: 680 | H41: =IF(G41<>"",0,F41) -> 680 | I41: LCL
A42: Mar | B42: PPC/26949 | C42: LESSA EVENTOS LTDA | D42: 1001002003 | E42: =_xlfn.XLOOKUP(D42,'Detalhamento - G200'!A:A,'Detalhamento - G200'!B:B,0) -> MOVIMENTAÇÃO DE TERRA | F42: 7035 | H42: =IF(G42<>"",0,F42) -> 7035 | I42: MAGALHÃES
A43: Mar | B43: PPC/26949 | C43: LESSA EVENTOS LTDA | D43: 1001001002 | E43: =_xlfn.XLOOKUP(D43,'Detalhamento - G200'!A:A,'Detalhamento - G200'!B:B,0) -> ENSAIOS E CONSULTORIAS | F43: 880 | H43: =IF(G43<>"",0,F43) -> 880 | I43: GEO2
A44: Mar | B44: PPC/26949 | C44: LESSA EVENTOS LTDA | D44: 1001001002 | E44: =_xlfn.XLOOKUP(D44,'Detalhamento - G200'!A:A,'Detalhamento - G200'!B:B,0) -> ENSAIOS E CONSULTORIAS | F44: 920 | G44: CLSF/200-3-022 | H44: =IF(G44<>"",0,F44) -> 0
A45: Mar | B45: PPC/26969 | C45: LITORAL TINTAS COMERCIO MATERIAIS DE CONSTRUCAO EIRELI | D45: 2001001010 | E45: =_xlfn.XLOOKUP(D45,'Detalhamento - G200'!A:A,'Detalhamento - G200'!B:B,0) -> MANUTENÇÃO DE CANTEIRO | F45: 795 | H45: =IF(G45<>"",0,F45) -> 795
A46: Mar | B46: PPC/26993 | C46: MIX MADEIREIRA LTDA | D46: 1002002001 | E46: =_xlfn.XLOOKUP(D46,'Detalhamento - G200'!A:A,'Detalhamento - G200'!B:B,0) -> FUNDAÇÃO | F46: 6635 | H46: =IF(G46<>"",0,F46) -> 6635
A47: Mar | B47: PPC/27039 | C47: VISUALCOR IMPRESSOES E COPIAS LTDA | D47: 2001001006 | E47: =_xlfn.XLOOKUP(D47,'Detalhamento - G200'!A:A,'Detalhamento - G200'!B:B,0) -> IMPLANTAÇÃO DE CANTEIRO - CIVIL | F47: 1130 | H47: =IF(G47<>"",0,F47) -> 1130
A48: Mar | B48: PPC/27045 | C48: LIGUE COMERCIO DE GEOSSINTETICOS LTDA | D48: 1001002003 | E48: =_xlfn.XLOOKUP(D48,'Detalhamento - G200'!A:A,'Detalhamento - G200'!B:B,0) -> MOVIMENTAÇÃO DE TERRA | F48: 3528.25 | H48: =IF(G48<>"",0,F48) -> 3528.25
A49: Mar | B49: PPC/27045 | C49: LIGUE COMERCIO DE GEOSSINTETICOS LTDA | D49: 1001002006 | E49: =_xlfn.XLOOKUP(D49,'Detalhamento - G200'!A:A,'Detalhamento - G200'!B:B,0) -> CONTENÇÕES | F49: 3570.95 | G49: CLSF/200-3-039 | H49: =IF(G49<>"",0,F49) -> 0
A50: Abril | B50: PPC/27093 | C50: BMD TEXTEIS LTDA | D50: 1001002006 | E50: =_xlfn.XLOOKUP(D50,'Detalhamento - G200'!A:A,'Detalhamento - G200'!B:B,0) -> CONTENÇÕES | F50: 1162501.9 | G50: CLSF/200-3-039 | H50: =IF(G50<>"",0,F50) -> 0
A51: Abril | B51: PPC/27094 | C51: MACCAFERRI DO BRASIL LTDA | D51: 1001002006 | E51: =_xlfn.XLOOKUP(D51,'Detalhamento - G200'!A:A,'Detalhamento - G200'!B:B,0) -> CONTENÇÕES | F51: 60984 | G51: CLSF/200-3-039 | H51: =IF(G51<>"",0,F51) -> 0
A52: Abril | B52: PPC/27095 | C52: MACCAFERRI SKAPS INDUSTRIA E COMERCIO DE ARTEFATOS PLASTICOS LTDA | D52: 1001002006 | E52: =_xlfn.XLOOKUP(D52,'Detalhamento - G200'!A:A,'Detalhamento - G200'!B:B,0) -> CONTENÇÕES | F52: 49953.7 | G52: CLSF/200-3-039 | H52: =IF(G52<>"",0,F52) -> 0
A53: Abril | B53: PPC/27127 | C53: OMEGA FERRAMENTAS E MAQUINAS LTDA | D53: 2001006013 | E53: =_xlfn.XLOOKUP(D53,'Detalhamento - G200'!A:A,'Detalhamento - G200'!B:B,0) -> BIG BAG | F53: 2813.3 | H53: =IF(G53<>"",0,F53) -> 2813.3
A54: Abril | B54: PPC/27148 | C54: QUALYSAN LOCACAO DE BENS MOVEIS EIRELI | D54: 2001006002 | E54: =_xlfn.XLOOKUP(D54,'Detalhamento - G200'!A:A,'Detalhamento - G200'!B:B,0) -> LIMPA FOSSA | F54: 51180 | H54: =IF(G54<>"",0,F54) -> 51180
A55: Abril | B55: PPC/27178 | C55: FABRICK - FABRICACAO DE PRE MOLDADOS S.A. | D55: 1002002001 | E55: =_xlfn.XLOOKUP(D55,'Detalhamento - G200'!A:A,'Detalhamento - G200'!B:B,0) -> FUNDAÇÃO | F55: 4625 | H55: =IF(G55<>"",0,F55) -> 4625
A56: Abril | B56: PPC/27178 | C56: FABRICK - FABRICACAO DE PRE MOLDADOS S.A. | D56: 2001001006 | E56: =_xlfn.XLOOKUP(D56,'Detalhamento - G200'!A:A,'Detalhamento - G200'!B:B,0) -> IMPLANTAÇÃO DE CANTEIRO - CIVIL | F56: 4440 | H56: =IF(G56<>"",0,F56) -> 4440
A57: Abril | B57: PPC/27179 | C57: ATACADAO DO PAPEL LTDA | D57: 2001008001 | E57: =_xlfn.XLOOKUP(D57,'Detalhamento - G200'!A:A,'Detalhamento - G200'!B:B,0) -> MATERIAIS DE COPA E LIMPEZA | F57: 1062 | H57: =IF(G57<>"",0,F57) -> 1062
A58: Abril | B58: PPC/27180 | C58: HILARIO DE SANTANA MOREIRA EIRELI | D58: 2001001005 | E58: =_xlfn.XLOOKUP(D58,'Detalhamento - G200'!A:A,'Detalhamento - G200'!B:B,0) -> IMPLANTAÇÃO DE CANTEIRO - HIDRÁULICA | F58: 1464.68 | H58: =IF(G58<>"",0,F58) -> 1464.68
A59: Abril | B59: PPC/27188 | C59: VISUALCOR IMPRESSOES E COPIAS LTDA | D59: 2001005002 | E59: =_xlfn.XLOOKUP(D59,'Detalhamento - G200'!A:A,'Detalhamento - G200'!B:B,0) -> EPC GERAL E COMUNICAÇÃO VISUAL | F59: 5090.4 | H59: =IF(G59<>"",0,F59) -> 5090.4
A60: Abril | B60: PPC/27188 | C60: VISUALCOR IMPRESSOES E COPIAS LTDA | D60: 2001021001 | E60: =_xlfn.XLOOKUP(D60,'Detalhamento - G200'!A:A,'Detalhamento - G200'!B:B,0) -> PLOTAGEM | F60: 360 | H60: =IF(G60<>"",0,F60) -> 360
A61: Abril | B61: PPC/27292 | C61: ZERO71 MADEIREIRA LTDA | D61: 2001001006 | E61: =_xlfn.XLOOKUP(D61,'Detalhamento - G200'!A:A,'Detalhamento - G200'!B:B,0) -> IMPLANTAÇÃO DE CANTEIRO - CIVIL | F61: 11747.5 | H61: =IF(G61<>"",0,F61) -> 11747.5
A62: Abril | B62: PPC/27307 | C62: SAARA LOCACAO DE TENDAS EIRELI | D62: 2001001007 | E62: =_xlfn.XLOOKUP(D62,'Detalhamento - G200'!A:A,'Detalhamento - G200'!B:B,0) -> LOCAÇÃO DE TOLDO | F62: 1500 | H62: =IF(G62<>"",0,F62) -> 1500
A63: Abril | B63: PPC/27315 | C63: ALBERTO JOSE DOS SANTOS | D63: 2001004001 | E63: =_xlfn.XLOOKUP(D63,'Detalhamento - G200'!A:A,'Detalhamento - G200'!B:B,0) -> LOCAÇÃO DE MUNCK | F63: 36042.8 | H63: =IF(G63<>"",0,F63) -> 36042.8
A64: Abril | B64: PPC/27356 | C64: LITORAL TINTAS COMERCIO MATERIAIS DE CONSTRUCAO EIRELI | D64: 2001001006 | E64: =_xlfn.XLOOKUP(D64,'Detalhamento - G200'!A:A,'Detalhamento - G200'!B:B,0) -> IMPLANTAÇÃO DE CANTEIRO - CIVIL | F64: 490 | H64: =IF(G64<>"",0,F64) -> 490
... A74: Abril | B74: PPC/27418 | C74: VEDAMAX INDUSTRIA LTDA | D74: 1002002001 | E74: =_xlfn.XLOOKUP(D74,'Detalhamento - G200'!A:A,'Detalhamento - G200'!B:B,0) -> FUNDAÇÃO | F74: 330 | H74: =IF(G74<>"",0,F74) -> 330
A75: Abril | B75: PPC/27430 | C75: BAHIA CONTAINERS LOCACAO E COMERCIO EIRELI | D75: 1001002006 | E75: =_xlfn.XLOOKUP(D75,'Detalhamento - G200'!A:A,'Detalhamento - G200'!B:B,0) -> CONTENÇÕES | F75: 4100 | G75: CLSF/200-3-039 | H75: =IF(G75<>"",0,F75) -> 0
A76: Abril | B76: PPC/27440 | C76: TERRAM ENGENHARIA DE INFRAESTRUTURA LTDA | D76: 1001002002 | E76: =_xlfn.XLOOKUP(D76,'Detalhamento - G200'!A:A,'Detalhamento - G200'!B:B,0) -> MOVIMENTO DE TERRA - ESCOPO MÍNIMO | F76: 4636906.6 | H76: =IF(G76<>"",0,F76) -> 4636906.6
A77: Abril | B77: PPC/27444 | C77: SOLOBAHIA ENGENHARIA E TECNOLOGIA LTDA | D77: 1001001002 | E77: =_xlfn.XLOOKUP(D77,'Detalhamento - G200'!A:A,'Detalhamento - G200'!B:B,0) -> ENSAIOS E CONSULTORIAS | F77: 30899.2 | H77: =IF(G77<>"",0,F77) -> 30899.2
A78: Abril | B78: PPC/27477 | C78: LESSA EVENTOS LTDA | D78: 1001001002 | E78: =_xlfn.XLOOKUP(D78,'Detalhamento - G200'!A:A,'Detalhamento - G200'!B:B,0) -> ENSAIOS E CONSULTORIAS | F78: 1024.8 | G78: CLSF/200-3-014 | H78: =IF(G78<>"",0,F78) -> 0
A79: Abril | B79: PPC/27477 | C79: LESSA EVENTOS LTDA | D79: 1001002003 | E79: =_xlfn.XLOOKUP(D79,'Detalhamento - G200'!A:A,'Detalhamento - G200'!B:B,0) -> MOVIMENTAÇÃO DE TERRA | F79: 5255.9 | G79: CLSF/200-3-015 | H79: =IF(G79<>"",0,F79) -> 0
A80: Abril | B80: PPC/27477 | C80: LESSA EVENTOS LTDA | D80: 1001001002 | E80: =_xlfn.XLOOKUP(D80,'Detalhamento - G200'!A:A,'Detalhamento - G200'!B:B,0) -> ENSAIOS E CONSULTORIAS | F80: 1024.8 | G80: CLSF/200-3-016 | H80: =IF(G80<>"",0,F80) -> 0
A81: Abril | B81: PPC/27477 | C81: LESSA EVENTOS LTDA | D81: 1001001002 | E81: =_xlfn.XLOOKUP(D81,'Detalhamento - G200'!A:A,'Detalhamento - G200'!B:B,0) -> ENSAIOS E CONSULTORIAS | F81: 427 | G81: CLSF/200-3-016 | H81: =IF(G81<>"",0,F81) -> 0
A82: Abril | B82: PPC/27483 | C82: ARCELORMITTAL BRASIL S.A. | D82: 1002002001 | E82: =_xlfn.XLOOKUP(D82,'Detalhamento - G200'!A:A,'Detalhamento - G200'!B:B,0) -> FUNDAÇÃO | F82: 1000000 | H82: =IF(G82<>"",0,F82) -> 1000000
A83: Abril | B83: PPC/27484 | C83: QUALYSAN LOCACAO DE BENS MOVEIS EIRELI | D83: 2001006002 | E83: =_xlfn.XLOOKUP(D83,'Detalhamento - G200'!A:A,'Detalhamento - G200'!B:B,0) -> LIMPA FOSSA | F83: =56410 -> 56410 | H83: =IF(G83<>"",0,F83) -> 56410
A84: Abril | B84: PPC/27562 | C84: FORMATO TRANSPORTES LTDA | D84: 2001010001 | E84: =_xlfn.XLOOKUP(D84,'Detalhamento - G200'!A:A,'Detalhamento - G200'!B:B,0) -> FRETE E CARRETO | F84: =2301.03 -> 2301.03 | H84: =IF(G84<>"",0,F84) -> 2301.03
A85: Abril | B85: PPC/27563 | C85: OMEGA FERRAMENTAS E MAQUINAS LTDA | D85: 1001002003 | E85: =_xlfn.XLOOKUP(D85,'Detalhamento - G200'!A:A,'Detalhamento - G200'!B:B,0) -> MOVIMENTAÇÃO DE TERRA | F85: 15840 | H85: =IF(G85<>"",0,F85) -> 15840
A86: Abril | B86: PPC/27567 | C86: PEDREIRAS CARANGI LTDA | D86: 1001002003 | E86: =_xlfn.XLOOKUP(D86,'Detalhamento - G200'!A:A,'Detalhamento - G200'!B:B,0) -> MOVIMENTAÇÃO DE TERRA | F86: =48500 -> 48500 | H86: =IF(G86<>"",0,F86) -> 48500
A87: Abril | B87: PPC/27570 | C87: SETTA INDUSTRIA ELETRICA LTDA | D87: 2001001002 | E87: =_xlfn.XLOOKUP(D87,'Detalhamento - G200'!A:A,'Detalhamento - G200'!B:B,0) -> IMPLANTAÇÃO DE CANTEIRO - ELETRICA | F87: 15598 | H87: =IF(G87<>"",0,F87) -> 15598
A88: Abril | B88: PPC/27574 | C88: TUPER S/A | D88: 1004001003 | E88: =_xlfn.XLOOKUP(D88,'Detalhamento - G200'!A:A,'Detalhamento - G200'!B:B,0) -> AUMENTO DO LUX DA ÁREA EXTERNA | F88: 5949.6825 | G88: CLSF/200-3-034 | H88: =IF(G88<>"",0,F88) -> 0
A89: Abril | B89: PPC/27574 | C89: TUPER S/A | D89: 1001004010 | E89: =_xlfn.XLOOKUP(D89,'Detalhamento - G200'!A:A,'Detalhamento - G200'!B:B,0) -> ÁREA DE LAZER | F89: 10172.72 | G89: CLSF/200-3-034 | H89: =IF(G89<>"",0,F89) -> 0
A90: Abril | B90: PPC/27574 | C90: TUPER S/A | D90: 1001004006 | E90: =_xlfn.XLOOKUP(D90,'Detalhamento - G200'!A:A,'Detalhamento - G200'!B:B,0) -> SANITÁRIOS EXTERNOS AO GALPÃO | F90: 10028.87 | G90: CLSF/200-3-034 | H90: =IF(G90<>"",0,F90) -> 0
A91: Abril | B91: PPC/27574 | C91: TUPER S/A | D91: 1001004001 | E91: =_xlfn.XLOOKUP(D91,'Detalhamento - G200'!A:A,'Detalhamento - G200'!B:B,0) -> PORTARIA / COBERTURA DA ECLUSA | F91: 13304.82 | G91: CLSF/200-3-034 | H91: =IF(G91<>"",0,F91) -> 0
A92: Abril | B92: PPC/27574 | C92: TUPER S/A | D92: 1001004002 | E92: =_xlfn.XLOOKUP(D92,'Detalhamento - G200'!A:A,'Detalhamento - G200'!B:B,0) -> APOIO (VESTIÁRIO + REFEITÓRIO) | F92: 24982.072 | G92: CLSF/200-3-034 | H92: =IF(G92<>"",0,F92) -> 0
A93: Abril | B93: PPC/27574 | C93: TUPER S/A | D93: 1001004007 | E93: =_xlfn.XLOOKUP(D93,'Detalhamento - G200'!A:A,'Detalhamento - G200'!B:B,0) -> PASSARELA DE PEDESTRES / COBERTURA DE ESTACIONAMENTO | F93: 21295.416 | G93: CLSF/200-3-034 | H93: =IF(G93<>"",0,F93) -> 0
A94: Abril | B94: PPC/27574 | C94: TUPER S/A | D94: 1001004005 | E94: =_xlfn.XLOOKUP(D94,'Detalhamento - G200'!A:A,'Detalhamento - G200'!B:B,0) -> UTILIDADES | F94: 3726.1726 | G94: CLSF/200-3-034 | H94: =IF(G94<>"",0,F94) -> 0
A95: Abril | B95: PPC/27574 | C95: TUPER S/A | D95: 1001005001 | E95: =_xlfn.XLOOKUP(D95,'Detalhamento - G200'!A:A,'Detalhamento - G200'!B:B,0) -> ELETRICA, HIDRÁULICA E COMBATE A INCÊNDIO - MEP | F95: 762657.04 | G95: CLSF/200-3-034 | H95: =IF(G95<>"",0,F95) -> 0
A96: Abril | B96: PPC/27574 | C96: TUPER S/A | D96: 1002003001 | E96: =_xlfn.XLOOKUP(D96,'Detalhamento - G200'!A:A,'Detalhamento - G200'!B:B,0) -> ELETRICA, HIDRÁULICA E COMBATE A INCÊNDIO | F96: 777649.57 | G96: CLSF/200-3-034 | H96: =IF(G96<>"",0,F96) -> 0
A97: Abril | B97: PPC/27578 | C97: M ANDRADE MAQUINAS E EQUIPAMENTOS EIRELI | D97: 2001004002 | E97: =_xlfn.XLOOKUP(D97,'Detalhamento - G200'!A:A,'Detalhamento - G200'!B:B,0) -> LOCAÇÃO DE BOBCAT | F97: =11900 -> 11900 | H97: =IF(G97<>"",0,F97) -> 11900
A98: Abril | B98: PPC/27591 | C98: FERROPRONTO LTDA | D98: 1002002001 | E98: =_xlfn.XLOOKUP(D98,'Detalhamento - G200'!A:A,'Detalhamento - G200'!B:B,0) -> FUNDAÇÃO | F98: 200000 | H98: =IF(G98<>"",0,F98) -> 200000
A99: Abril | B99: PPC/27608 | C99: TRANSPORTADORA DE DIESEL CAVALO MARINHO LTDA | D99: 2001004004 | E99: =_xlfn.XLOOKUP(D99,'Detalhamento - G200'!A:A,'Detalhamento - G200'!B:B,0) -> DIESEL | F99: 2406.39 | H99: =IF(G99<>"",0,F99) -> 2406.39
A100: Abril | B100: PPC/27630 | C100: CL COMERCIO E SERVICOS DE EQUIPAMENTOS ELETRICOS LTDA | D100: 1001005001 | E100: =_xlfn.XLOOKUP(D100,'Detalhamento - G200'!A:A,'Detalhamento - G200'!B:B,0) -> ELETRICA, HIDRÁULICA E COMBATE A INCÊNDIO - MEP | F100: =45500 -> 45500 | G100: CLSF/200-3-034 | H100: =IF(G100<>"",0,F100) -> 0
A101: Abril | B101: PPC/27631 | C101: COBREMACK INDUSTRIA DE CONDUTORES ELETRICOS EIRELI | D101: 1001005001 | E101: =_xlfn.XLOOKUP(D101,'Detalhamento - G200'!A:A,'Detalhamento - G200'!B:B,0) -> ELETRICA, HIDRÁULICA E COMBATE A INCÊNDIO - MEP | F101: =61746.03 -> 61746.03 | G101: CLSF/200-3-034 | H101: =IF(G101<>"",0,F101) -> 0
A102: Abril | B102: PPC/27632 | C102: COBREMACK INDUSTRIA DE CONDUTORES ELETRICOS EIRELI | D102: 1001005001 | E102: =_xlfn.XLOOKUP(D102,'Detalhamento - G200'!A:A,'Detalhamento - G200'!B:B,0) -> ELETRICA, HIDRÁULICA E COMBATE A INCÊNDIO - MEP | F102: 145790.65 | G102: CLSF/200-3-034 | H102: =IF(G102<>"",0,F102) -> 0
A103: Abril | B103: PPC/27633 | C103: ELETROPOLL ELETRODUTOS METALICOS LTDA | D103: 1001005001 | E103: =_xlfn.XLOOKUP(D103,'Detalhamento - G200'!A:A,'Detalhamento - G200'!B:B,0) -> ELETRICA, HIDRÁULICA E COMBATE A INCÊNDIO - MEP | F103: 535492.73 | G103: CLSF/200-3-034 | H103: =IF(G103<>"",0,F103) -> 0
A104: Abril | B104: PPC/27633 | C104: ELETROPOLL ELETRODUTOS METALICOS LTDA | D104: 1002003001 | E104: =_xlfn.XLOOKUP(D104,'Detalhamento - G200'!A:A,'Detalhamento - G200'!B:B,0) -> ELETRICA, HIDRÁULICA E COMBATE A INCÊNDIO | F104: 535492.73 | G104: CLSF/200-3-034 | H104: =IF(G104<>"",0,F104) -> 0
A105: Abril | B105: PPC/27634 | C105: INDUSTRIA DE TRANSFORMADORES ITAIPU LTDA | D105: 1001005001 | E105: =_xlfn.XLOOKUP(D105,'Detalhamento - G200'!A:A,'Detalhamento - G200'!B:B,0) -> ELETRICA, HIDRÁULICA E COMBATE A INCÊNDIO - MEP | F105: 214500.24 | G105: CLSF/200-3-034 | H105: =IF(G105<>"",0,F105) -> 0
A106: Abril | B106: PPC/27635 | C106: LOGICA PERFIL INDUSTRIA E COMERCIO LTDA | D106: 1001005001 | E106: =_xlfn.XLOOKUP(D106,'Detalhamento - G200'!A:A,'Detalhamento - G200'!B:B,0) -> ELETRICA, HIDRÁULICA E COMBATE A INCÊNDIO - MEP | F106: 44136.4 | G106: CLSF/200-3-034 | H106: =IF(G106<>"",0,F106) -> 0
A107: Abril | B107: PPC/27636 | C107: MT COMERCIAL ELETRICA LTDA | D107: 1001005001 | E107: =_xlfn.XLOOKUP(D107,'Detalhamento - G200'!A:A,'Detalhamento - G200'!B:B,0) -> ELETRICA, HIDRÁULICA E COMBATE A INCÊNDIO - MEP | F107: 78094 | G107: CLSF/200-3-034 | H107: =IF(G107<>"",0,F107) -> 0
A108: Abril | B108: PPC/27637 | C108: INTERNATIONAL INDUSTRIA AUTOMOTIVA DA AMERICA DO SUL LTDA. | D108: 1002003001 | E108: =_xlfn.XLOOKUP(D108,'Detalhamento - G200'!A:A,'Detalhamento - G200'!B:B,0) -> ELETRICA, HIDRÁULICA E COMBATE A INCÊNDIO | F108: 322894.56 | G108: CLSF/200-3-034 | H108: =IF(G108<>"",0,F108) -> 0
A109: Abril | B109: PPC/27638 | C109: WEG EQUIPAMENTOS ELETRICOS S/A | D109: 1001005001 | E109: =_xlfn.XLOOKUP(D109,'Detalhamento - G200'!A:A,'Detalhamento - G200'!B:B,0) -> ELETRICA, HIDRÁULICA E COMBATE A INCÊNDIO - MEP | F109: 350538 | G109: CLSF/200-3-034 | H109: =IF(G109<>"",0,F109) -> 0
A110: Abril | B110: PPC/27641 | C110: SOLUCAO TOLDOS EIRELI | D110: 2001001007 | E110: =_xlfn.XLOOKUP(D110,'Detalhamento - G200'!A:A,'Detalhamento - G200'!B:B,0) -> LOCAÇÃO DE TOLDO | F110: 500 | H110: =IF(G110<>"",0,F110) -> 500
A111: Abril | B111: PPC/27642 | C111: SOLUCAO TOLDOS EIRELI | D111: 2001001007 | E111: =_xlfn.XLOOKUP(D111,'Detalhamento - G200'!A:A,'Detalhamento - G200'!B:B,0) -> LOCAÇÃO DE TOLDO | F111: 3150 | H111: =IF(G111<>"",0,F111) -> 3150
A112: Abril | B112: PPC/27673 | C112: VISUALCOR IMPRESSOES E COPIAS LTDA | D112: 2001005002 | E112: =_xlfn.XLOOKUP(D112,'Detalhamento - G200'!A:A,'Detalhamento - G200'!B:B,0) -> EPC GERAL E COMUNICAÇÃO VISUAL | F112: 750 | H112: =IF(G112<>"",0,F112) -> 750
...

Sheet Gestão de Contratos
B2: Instruções: | C2: No Sienge (Suprimentos / Contratos e Medições / Relatórios / Contratos / Faturamentos diretos);
C3: Obras 152/ Consultar / Gerar relatório excel;
B4: Observação: | C4: Esta planilha serva para a aba "analítico" não duplicar os custos, ou seja, para não associar as notas como uma nova contratação e estourar um saldo já contratado.
B13: CONTRATO | C13: CREDOR | D13: FATURAMENTO DIRETO | E13: FATURAMENTO CREDOR | F13: VRL. CONTRATO SIENGE | G13: VLR. CONTRATO JURÍDICO | H13: CHECK | I13: FATURADO CREDOR
B14: {=_xlfn.UNIQUE('Contratos - G200'!C14:C4990)} -> CLSF/200-3-000 | C14: {=_xlfn.XLOOKUP(B14,'Contratos - G200'!C:C,'Contratos - G200'!D:D,X)} -> QPC ENGENHARIA LTDA | D14: 0 | E14: 58566362 | F14: =SUMIF('Contratos - G200'!C:C,'Gestão de Contratos'!B14,'Contratos - G200'!J:J) -> 58566362 | G14: 58566362 | H14: =SUM(D14:E14)=F14 -> TRUE | I14: =SUMIF('Notas fiscais - G200'!W9:W4894,'Gestão de Contratos'!B14,'Notas fiscais - G200'!T9:T4894) -> 19685993
B15: CLSF/200-3-001 | C15: {=_xlfn.XLOOKUP(B15,'Contratos - G200'!C:C,'Contratos - G200'!D:D,X)} -> DPE ARQUITETURA E ENGENHARIA S/S | D15: 0 | E15: 450000 | F15: =SUMIF('Contratos - G200'!C:C,'Gestão de Contratos'!B15,'Contratos - G200'!J:J) -> 450000 | G15: 450000 | H15: =SUM(D15:E15)=F15 -> TRUE | I15: =SUMIF('Notas fiscais - G200'!W10:W4895,'Gestão de Contratos'!B15,'Notas fiscais - G200'!T10:T4895) -> 125400
B16: CLSF/200-3-002 | C16: {=_xlfn.XLOOKUP(B16,'Contratos - G200'!C:C,'Contratos - G200'!D:D,X)} -> ARQUITETURA JAPI PROJETOS E CONSULTORIA EIRELI | D16: 0 | E16: 472594.69 | F16: =SUMIF('Contratos - G200'!C:C,'Gestão de Contratos'!B16,'Contratos - G200'!J:J) -> 472594.69 | G16: 472594.69 | H16: =SUM(D16:E16)=F16 -> TRUE | I16: =SUMIF('Notas fiscais - G200'!W11:W4896,'Gestão de Contratos'!B16,'Notas fiscais - G200'!T11:T4896) -> 126368.28
B17: CLSF/200-3-003 | C17: {=_xlfn.XLOOKUP(B17,'Contratos - G200'!C:C,'Contratos - G200'!D:D,X)} -> DO VAL ENGENHARIA CONSULTIVA SOCIEDADE SIMPLES | D17: 0 | E17: 100000 | F17: =SUMIF('Contratos - G200'!C:C,'Gestão de Contratos'!B17,'Contratos - G200'!J:J) -> 100000 | G17: 100000 | H17: =SUM(D17:E17)=F17 -> TRUE | I17: =SUMIF('Notas fiscais - G200'!W12:W4897,'Gestão de Contratos'!B17,'Notas fiscais - G200'!T12:T4897) -> 0
B18: CLSF/200-3-004 | C18: {=_xlfn.XLOOKUP(B18,'Contratos - G200'!C:C,'Contratos - G200'!D:D,X)} -> LPE ENGENHARIA E CONSULTORIA LTDA | D18: 0 | E18: 244000 | F18: =SUMIF('Contratos - G200'!C:C,'Gestão de Contratos'!B18,'Contratos - G200'!J:J) -> 244000 | G18: 244000 | H18: =SUM(D18:E18)=F18 -> TRUE | I18: =SUMIF('Notas fiscais - G200'!W13:W4898,'Gestão de Contratos'!B18,'Notas fiscais - G200'!T13:T4898) -> 122000
B19: CLSF/200-3-005 | C19: {=_xlfn.XLOOKUP(B19,'Contratos - G200'!C:C,'Contratos - G200'!D:D,X)} -> T.T.C. ENGENHARIA DE TRAFEGO E DE TRANSPORTES LTDA | D19: 0 | E19: 9200 | F19: =SUMIF('Contratos - G200'!C:C,'Gestão de Contratos'!B19,'Contratos - G200'!J:J) -> 9200 | G19: 9200 | H19: =SUM(D19:E19)=F19 -> TRUE | I19: =SUMIF('Notas fiscais - G200'!W14:W4899,'Gestão de Contratos'!B19,'Notas fiscais - G200'!T14:T4899) -> 0
B20: CLSF/200-3-006 | C20: {=_xlfn.XLOOKUP(B20,'Contratos - G200'!C:C,'Contratos - G200'!D:D,X)} -> REV1 PROJETOS INTEGRADOS LTDA | D20: 0 | E20: 16917 | F20: =SUMIF('Contratos - G200'!C:C,'Gestão de Contratos'!B20,'Contratos - G200'!J:J) -> 16917 | G20: 16917 | H20: =SUM(D20:E20)=F20 -> TRUE | I20: =SUMIF('Notas fiscais - G200'!W15:W4900,'Gestão de Contratos'!B20,'Notas fiscais - G200'!T15:T4900) -> 10457.63
B21: CLSF/200-3-007 | C21: {=_xlfn.XLOOKUP(B21,'Contratos - G200'!C:C,'Contratos - G200'!D:D,X)} -> NUCLEORA PLANEJAMENTO, ASSESSORIA E DESENVOLVIMENTO COMERCIAL LTDA | D21: 0 | E21: 45000 | F21: =SUMIF('Contratos - G200'!C:C,'Gestão de Contratos'!B21,'Contratos - G200'!J:J) -> 45000 | G21: 45000 | H21: =SUM(D21:E21)=F21 -> TRUE | I21: =SUMIF('Notas fiscais - G200'!W16:W4901,'Gestão de Contratos'!B21,'Notas fiscais - G200'!T16:T4901) -> 13500
B22: CLSF/200-3-008 | C22: {=_xlfn.XLOOKUP(B22,'Contratos - G200'!C:C,'Contratos - G200'!D:D,X)} -> KAIZ ENGENHARIA LTDA | D22: 0 | E22: 64300 | F22: =SUMIF('Contratos - G200'!C:C,'Gestão de Contratos'!B22,'Contratos - G200'!J:J) -> 64300 | G22: 64300 | H22: =SUM(D22:E22)=F22 -> TRUE | I22: =SUMIF('Notas fiscais - G200'!W17:W4902,'Gestão de Contratos'!B22,'Notas fiscais - G200'!T17:T4902) -> 0
B23: CLSF/200-3-009 | C23: {=_xlfn.XLOOKUP(B23,'Contratos - G200'!C:C,'Contratos - G200'!D:D,X)} -> KAIZ ENGENHARIA LTDA | D23: 0 | E23: 68300 | F23: =SUMIF('Contratos - G200'!C:C,'Gestão de Contratos'!B23,'Contratos - G200'!J:J) -> 68300 | G23: 68300 | H23: =SUM(D23:E23)=F23 -> TRUE | I23: =SUMIF('Notas fiscais - G200'!W18:W4903,'Gestão de Contratos'!B23,'Notas fiscais - G200'!T18:T4903) -> 22220.27
B24: CLSF/200-3-010 | C24: {=_xlfn.XLOOKUP(B24,'Contratos - G200'!C:C,'Contratos - G200'!D:D,X)} -> VENDRAMINI ENGENHARIA LTDA | D24: 0 | E24: 0 | F24: =SUMIF('Contratos - G200'!C:C,'Gestão de Contratos'!B24,'Contratos - G200'!J:J) -> 0 | G24: 1316000 | H24: =SUM(D24:E24)=F24 -> TRUE | I24: =SUMIF('Notas fiscais - G200'!W19:W4904,'Gestão de Contratos'!B24,'Notas fiscais - G200'!T19:T4904) -> 275000
B25: CLSF/200-3-011 | C25: {=_xlfn.XLOOKUP(B25,'Contratos - G200'!C:C,'Contratos - G200'!D:D,X)} -> DO VAL ENGENHARIA CONSULTIVA SOCIEDADE SIMPLES | D25: 0 | E25: 87000 | F25: =SUMIF('Contratos - G200'!C:C,'Gestão de Contratos'!B25,'Contratos - G200'!J:J) -> 87000 | G25: 87000 | H25: =SUM(D25:E25)=F25 -> TRUE | I25: =SUMIF('Notas fiscais - G200'!W20:W4905,'Gestão de Contratos'!B25,'Notas fiscais - G200'!T20:T4905) -> 34800
B26: CLSF/200-3-012 | C26: {=_xlfn.XLOOKUP(B26,'Contratos - G200'!C:C,'Contratos - G200'!D:D,X)} -> GEOTECHNIQUE CONSULTORIA E ENGENHARIA LTDA | D26: 0 | E26: 250380 | F26: =SUMIF('Contratos - G200'!C:C,'Gestão de Contratos'!B26,'Contratos - G200'!J:J) -> 250380 | G26: 250380 | H26: =SUM(D26:E26)=F26 -> TRUE | I26: =SUMIF('Notas fiscais - G200'!W21:W4906,'Gestão de Contratos'!B26,'Notas fiscais - G200'!T21:T4906) -> 0
... B32: CLSF/200-3-018 | C32: {=_xlfn.XLOOKUP(B32,'Contratos - G200'!C:C,'Contratos - G200'!D:D,X)} -> FF INFRA E ENGENHARIA LTDA | D32: 221200 | E32: 94800 | F32: =SUMIF('Contratos - G200'!C:C,'Gestão de Contratos'!B32,'Contratos - G200'!J:J) -> 316000 | G32: 316000 | H32: =SUM(D32:E32)=F32 -> TRUE | I32: =SUMIF('Notas fiscais - G200'!W27:W4912,'Gestão de Contratos'!B32,'Notas fiscais - G200'!T27:T4912) -> 46728.1
B33: CLSF/200-3-019 | C33: {=_xlfn.XLOOKUP(B33,'Contratos - G200'!C:C,'Contratos - G200'!D:D,X)} -> AQUAGEO PROJETOS E PERFURACOES LTDA | D33: 0 | E33: =286456.27-66003.27 -> 220453 | F33: =SUMIF('Contratos - G200'!C:C,'Gestão de Contratos'!B33,'Contratos - G200'!J:J) -> 286456.27 | G33: 286456.27 | H33: =SUM(D33:E33)=F33 -> FALSE | I33: =SUMIF('Notas fiscais - G200'!W28:W4913,'Gestão de Contratos'!B33,'Notas fiscais - G200'!T28:T4913) -> 136066.73
B34: CLSF/200-3-020 | C34: {=_xlfn.XLOOKUP(B34,'Contratos - G200'!C:C,'Contratos - G200'!D:D,X)} -> SPM ENGENHARIA SOCIEDADE SIMPLES LTDA. | D34: 0 | E34: 0 | F34: =SUMIF('Contratos - G200'!C:C,'Gestão de Contratos'!B34,'Contratos - G200'!J:J) -> 0 | G34: 568700 | H34: =SUM(D34:E34)=F34 -> TRUE | I34: =SUMIF('Notas fiscais - G200'!W29:W4914,'Gestão de Contratos'!B34,'Notas fiscais - G200'!T29:T4914) -> 142175
B35: CLSF/200-3-021 | C35: {=_xlfn.XLOOKUP(B35,'Contratos - G200'!C:C,'Contratos - G200'!D:D,X)} -> LAEROMEC - SOLUCOES EM ENGENHARIA LTDA | D35: 0 | E35: 0 | F35: =SUMIF('Contratos - G200'!C:C,'Gestão de Contratos'!B35,'Contratos - G200'!J:J) -> 0 | G35: 31300 | H35: =SUM(D35:E35)=F35 -> TRUE | I35: =SUMIF('Notas fiscais - G200'!W30:W4915,'Gestão de Contratos'!B35,'Notas fiscais - G200'!T30:T4915) -> 15650
B36: CLSF/200-3-022 | C36: {=_xlfn.XLOOKUP(B36,'Contratos - G200'!C:C,'Contratos - G200'!D:D,X)} -> SOLOBAHIA ENGENHARIA E TECNOLOGIA LTDA | D36: 0 | E36: 141411.45 | F36: =SUMIF('Contratos - G200'!C:C,'Gestão de Contratos'!B36,'Contratos - G200'!J:J) -> 141411.45 | G36: 141411.45 | H36: =SUM(D36:E36)=F36 -> TRUE | I36: =SUMIF('Notas fiscais - G200'!W31:W4916,'Gestão de Contratos'!B36,'Notas fiscais - G200'!T31:T4916) -> 37451.69
B37: CLSF/200-3-023 | C37: {=_xlfn.XLOOKUP(B37,'Contratos - G200'!C:C,'Contratos - G200'!D:D,X)} -> LESSA EVENTOS LTDA | D37: 0 | E37: 1808700.4 | F37: =SUMIF('Contratos - G200'!C:C,'Gestão de Contratos'!B37,'Contratos - G200'!J:J) -> 1808700.4 | G37: 1808700.4 | H37: =SUM(D37:E37)=F37 -> TRUE | I37: =SUMIF('Notas fiscais - G200'!W32:W4917,'Gestão de Contratos'!B37,'Notas fiscais - G200'!T32:T4917) -> 75495.05
B38: CLSF/200-3-024 | C38: {=_xlfn.XLOOKUP(B38,'Contratos - G200'!C:C,'Contratos - G200'!D:D,X)} -> BOME EMPREENDIMENTOS E SERVICOS LTDA | D38: 0 | E38: 1304518.2 | F38: =SUMIF('Contratos - G200'!C:C,'Gestão de Contratos'!B38,'Contratos - G200'!J:J) -> 1304518.2 | G38: 1304518.2 | H38: =SUM(D38:E38)=F38 -> TRUE | I38: =SUMIF('Notas fiscais - G200'!W33:W4918,'Gestão de Contratos'!B38,'Notas fiscais - G200'!T33:T4918) -> 58979.88
B39: CLSF/200-3-025 | C39: {=_xlfn.XLOOKUP(B39,'Contratos - G200'!C:C,'Contratos - G200'!D:D,X)} -> LEONARDO SANTOS GONCALVES PRODUCAO E SOLUCOES EM VIDEOS | D39: 0 | E39: 32200 | F39: =SUMIF('Contratos - G200'!C:C,'Gestão de Contratos'!B39,'Contratos - G200'!J:J) -> 32200 | G39: 32200 | H39: =SUM(D39:E39)=F39 -> TRUE | I39: =SUMIF('Notas fiscais - G200'!W34:W4919,'Gestão de Contratos'!B39,'Notas fiscais - G200'!T34:T4919) -> 4600
B40: CLSF/200-3-026 | C40: {=_xlfn.XLOOKUP(B40,'Contratos - G200'!C:C,'Contratos - G200'!D:D,X)} -> SOFTCOMP COMERCIO SERVICOS TELECOMUNICACOES E INFORMATICA EIRELI | D40: 0 | E40: 43750 | F40: =SUMIF('Contratos - G200'!C:C,'Gestão de Contratos'!B40,'Contratos - G200'!J:J) -> 43750 | G40: 43750 | H40: =SUM(D40:E40)=F40 -> TRUE | I40: =SUMIF('Notas fiscais - G200'!W35:W4920,'Gestão de Contratos'!B40,'Notas fiscais - G200'!T35:T4920) -> 4200
B41: CLSF/200-3-027 | C41: {=_xlfn.XLOOKUP(B41,'Contratos - G200'!C:C,'Contratos - G200'!D:D,X)} -> AMARAL GERENCIAMENTO DE RESIDUOS LTDA | D41: 0 | E41: 163230 | F41: =SUMIF('Contratos - G200'!C:C,'Gestão de Contratos'!B41,'Contratos - G200'!J:J) -> 163230 | G41: 163230 | H41: =SUM(D41:E41)=F41 -> TRUE | I41: =SUMIF('Notas fiscais - G200'!W36:W4921,'Gestão de Contratos'!B41,'Notas fiscais - G200'!T36:T4921) -> 6280
B42: CLSF/200-3-028 | C42: {=_xlfn.XLOOKUP(B42,'Contratos - G200'!C:C,'Contratos - G200'!D:D,X)} -> BIOFUTURO ENGENHARIA E SOLUCOES AMBIENTAIS EIRELI | D42: 864100 | E42: =350000+63900 -> 413900 | F42: =SUMIF('Contratos - G200'!C:C,'Gestão de Contratos'!B42,'Contratos - G200'!J:J) -> 1278000 | G42: 1278000 | H42: =SUM(D42:E42)=F42 -> TRUE | I42: =SUMIF('Notas fiscais - G200'!W37:W4922,'Gestão de Contratos'!B42,'Notas fiscais - G200'!T37:T4922) -> 350000
B43: CLSF/200-3-029 | C43: {=_xlfn.XLOOKUP(B43,'Contratos - G200'!C:C,'Contratos - G200'!D:D,X)} -> TRANSDADOS INTERNET LTDA | D43: 0 | E43: 11200 | F43: =SUMIF('Contratos - G200'!C:C,'Gestão de Contratos'!B43,'Contratos - G200'!J:J) -> 11200 | G43: 11200 | H43: =SUM(D43:E43)=F43 -> TRUE | I43: =SUMIF('Notas fiscais - G200'!W38:W4923,'Gestão de Contratos'!B43,'Notas fiscais - G200'!T38:T4923) -> 800
B44: CLSF/200-3-030 | C44: {=_xlfn.XLOOKUP(B44,'Contratos - G200'!C:C,'Contratos - G200'!D:D,X)} -> LC ADIA - LOCACAO DE VEICULOS LTDA | D44: 0 | E44: 1895760 | F44: =SUMIF('Contratos - G200'!C:C,'Gestão de Contratos'!B44,'Contratos - G200'!J:J) -> 1895760 | G44: 1895760 | H44: =SUM(D44:E44)=F44 -> TRUE | I44: =SUMIF('Notas fiscais - G200'!W39:W4924,'Gestão de Contratos'!B44,'Notas fiscais - G200'!T39:T4924) -> 46165.38
B45: CLSF/200-3-031 | C45: {=_xlfn.XLOOKUP(B45,'Contratos - G200'!C:C,'Contratos - G200'!D:D,X)} -> KOPRON DO BRASIL COMERCIO E INDUSTRIA DE EQUIPAMENTOS DE LOGISTICA LTDA | D45: 337100 | E45: 3262900 | F45: =SUMIF('Contratos - G200'!C:C,'Gestão de Contratos'!B45,'Contratos - G200'!J:J) -> 3600000 | G45: 3600000 | H45: =SUM(D45:E45)=F45 -> TRUE | I45: =SUMIF('Notas fiscais - G200'!W40:W4925,'Gestão de Contratos'!B45,'Notas fiscais - G200'!T40:T4925) -> 2760469.1
B46: CLSF/200-3-032 | C46: {=_xlfn.XLOOKUP(B46,'Contratos - G200'!C:C,'Contratos - G200'!D:D,X)} -> ROTULA METALURGICA LTDA | D46: =10410893.24+5363187.43 -> 15774081 | E46: =26365249.11+2929472.13 -> 29294721 | F46: =SUMIF('Contratos - G200'!C:C,'Gestão de Contratos'!B46,'Contratos - G200'!J:J) -> 45068802 | G46: 45068802 | H46: =SUM(D46:E46)=F46 -> TRUE | I46: =SUMIF('Notas fiscais - G200'!W41:W4926,'Gestão de Contratos'!B46,'Notas fiscais - G200'!T41:T4926) -> 18027521
B47: CLSF/200-3-033 | C47: {=_xlfn.XLOOKUP(B47,'Contratos - G200'!C:C,'Contratos - G200'!D:D,X)} -> T & A CONSTRUCAO PRE-FABRICADA S/A | D47: =55318464.52+13107641.16 -> 68426106 | E47: =3175000+7790000+1312000 -> 12277000 | F47: =SUMIF('Contratos - G200'!C:C,'Gestão de Contratos'!B47,'Contratos - G200'!J:J) -> 80703106 | G47: 80703106 | H47: =SUM(D47:E47)=F47 -> FALSE | I47: =SUMIF('Notas fiscais - G200'!W42:W4927,'Gestão de Contratos'!B47,'Notas fiscais - G200'!T42:T4927) -> 21742126
B48: CLSF/200-3-034 | C48: {=_xlfn.XLOOKUP(B48,'Contratos - G200'!C:C,'Contratos - G200'!D:D,X)} -> ARTEMP ENGENHARIA DE INSTALAÇÕES LTDA | D48: 23500000 | E48: 25916467 | F48: =SUMIF('Contratos - G200'!C:C,'Gestão de Contratos'!B48,'Contratos - G200'!J:J) -> 49416467 | G48: 49416467 | H48: =SUM(D48:E48)=F48 -> TRUE | I48: =SUMIF('Notas fiscais - G200'!W43:W4928,'Gestão de Contratos'!B48,'Notas fiscais - G200'!T43:T4928) -> 15093475
B49: CLSF/200-3-035 | C49: {=_xlfn.XLOOKUP(B49,'Contratos - G200'!C:C,'Contratos - G200'!D:D,X)} -> ENTEL COMERCIO E SERVICOS LTDA | D49: 0 | E49: 28020 | F49: =SUMIF('Contratos - G200'!C:C,'Gestão de Contratos'!B49,'Contratos - G200'!J:J) -> 28020 | G49: 28020 | H49: =SUM(D49:E49)=F49 -> TRUE | I49: =SUMIF('Notas fiscais - G200'!W44:W4929,'Gestão de Contratos'!B49,'Notas fiscais - G200'!T44:T4929) -> 3622.6
B50: CLSF/200-3-036 | C50: {=_xlfn.XLOOKUP(B50,'Contratos - G200'!C:C,'Contratos - G200'!D:D,X)} -> THYSSENKRUPP ELEVADORES AS | D50: 0 | E50: 171000 | F50: =SUMIF('Contratos - G200'!C:C,'Gestão de Contratos'!B50,'Contratos - G200'!J:J) -> 171000 | G50: 171000 | H50: =SUM(D50:E50)=F50 -> TRUE | I50: =SUMIF('Notas fiscais - G200'!W45:W4930,'Gestão de Contratos'!B50,'Notas fiscais - G200'!T45:T4930) -> 43605
B51: CLSF/200-3-037 | C51: {=_xlfn.XLOOKUP(B51,'Contratos - G200'!C:C,'Contratos - G200'!D:D,X)} -> KAIZ ENGENHARIA LTDA | D51: 0 | E51: 38000 | F51: =SUMIF('Contratos - G200'!C:C,'Gestão de Contratos'!B51,'Contratos - G200'!J:J) -> 38000 | G51: 38000 | H51: =SUM(D51:E51)=F51 -> TRUE | I51: =SUMIF('Notas fiscais - G200'!W46:W4931,'Gestão de Contratos'!B51,'Notas fiscais - G200'!T46:T4931) -> 0
B52: CLSF/200-3-038 | C52: {=_xlfn.XLOOKUP(B52,'Contratos - G200'!C:C,'Contratos - G200'!D:D,X)} -> SOTEC FABRICACAO DE ESTRUTURAS METALICAS E SERVICOS LTDA | D52: 2000000.4 | E52: 500000.09 | F52: =SUMIF('Contratos - G200'!C:C,'Gestão de Contratos'!B52,'Contratos - G200'!J:J) -> 2500000.5 | G52: 2500000.5 | H52: =SUM(D52:E52)=F52 -> TRUE | I52: =SUMIF('Notas fiscais - G200'!W47:W4932,'Gestão de Contratos'!B52,'Notas fiscais - G200'!T47:T4932) -> 500000.09
B53: CLSF/200-3-039 | C53: {=_xlfn.XLOOKUP(B53,'Contratos - G200'!C:C,'Contratos - G200'!D:D,X)} -> VOC ENGENHARIA E CONSTRUCAO LTDA | D53: 3464956.6 | E53: 1968054.6 | F53: =SUMIF('Contratos - G200'!C:C,'Gestão de Contratos'!B53,'Contratos - G200'!J:J) -> 5433011.2 | G53: 5433011.2 | H53: =SUM(D53:E53)=F53 -> FALSE | I53: =SUMIF('Notas fiscais - G200'!W48:W4933,'Gestão de Contratos'!B53,'Notas fiscais - G200'!T48:T4933) -> 1245656.5
B54: CLSF/200-3-040 | C54: {=_xlfn.XLOOKUP(B54,'Contratos - G200'!C:C,'Contratos - G200'!D:D,X)} -> GEOTECHNIQUE CONSULTORIA E ENGENHARIA LTDA | D54: 0 | E54: 175000 | F54: =SUMIF('Contratos - G200'!C:C,'Gestão de Contratos'!B54,'Contratos - G200'!J:J) -> 175000 | G54: 175000 | H54: =SUM(D54:E54)=F54 -> TRUE | I54: =SUMIF('Notas fiscais - G200'!W49:W4934,'Gestão de Contratos'!B54,'Notas fiscais - G200'!T49:T4934) -> 0
B55: CLSF/200-3-041 | C55: {=_xlfn.XLOOKUP(B55,'Contratos - G200'!C:C,'Contratos - G200'!D:D,X)} -> DIPAWA NORDESTE INDÚSTRIA COMÉRCIO E CONSTRUTORA LTDA | D55: 0 | E55: 799000 | F55: =SUMIF('Contratos - G200'!C:C,'Gestão de Contratos'!B55,'Contratos - G200'!J:J) -> 799000 | G55: 799000 | H55: =SUM(D55:E55)=F55 -> TRUE | I55: =SUMIF('Notas fiscais - G200'!W50:W4935,'Gestão de Contratos'!B55,'Notas fiscais - G200'!T50:T4935) -> 639200
B56: CLSF/200-3-042 | C56: {=_xlfn.XLOOKUP(B56,'Contratos - G200'!C:C,'Contratos - G200'!D:D,X)} -> ARTEMP ENGENHARIA TERMICA LTDA | D56: 17500000 | E56: 25636407 | F56: =SUMIF('Contratos - G200'!C:C,'Gestão de Contratos'!B56,'Contratos - G200'!J:J) -> 43136407 | G56: 43136407 | H56: =SUM(D56:E56)=F56 -> TRUE | I56: =SUMIF('Notas fiscais - G200'!W51:W4936,'Gestão de Contratos'!B56,'Notas fiscais - G200'!T51:T4936) -> 8972742.3
B57: CLSF/200-3-043 | C57: {=_xlfn.XLOOKUP(B57,'Contratos - G200'!C:C,'Contratos - G200'!D:D,X)} -> NEOSONDA ENGENHARIA LTDA | D57: 0 | E57: 1528000.4 | F57: =SUMIF('Contratos - G200'!C:C,'Gestão de Contratos'!B57,'Contratos - G200'!J:J) -> 240500 | G57: 1528000.4 | H57: =SUM(D57:E57)=F57 -> FALSE | I57: =SUMIF('Notas fiscais - G200'!W52:W4937,'Gestão de Contratos'!B57,'Notas fiscais - G200'!T52:T4937) -> 0
B58: CLSF/200-3-044 | C58: {=_xlfn.XLOOKUP(B58,'Contratos - G200'!C:C,'Contratos - G200'!D:D,X)} -> PRESOTTO SERVICOS DE ENGENHARIA LTDA | D58: 345221.23 | E58: 230147.48 | F58: =SUMIF('Contratos - G200'!C:C,'Gestão de Contratos'!B58,'Contratos - G200'!J:J) -> 0 | G58: 575368.71 | H58: =SUM(D58:E58)=F58 -> FALSE | I58: =SUMIF('Notas fiscais - G200'!W53:W4938,'Gestão de Contratos'!B58,'Notas fiscais - G200'!T53:T4938) -> 0
B59: CLSF/200-3-045 | C59: {=_xlfn.XLOOKUP(B59,'Contratos - G200'!C:C,'Contratos - G200'!D:D,X)} -> TGEO SERVICOS DE ENGENHARIA E GEOLOGIA LTDA | D59: 0 | E59: 240500 | F59: =SUMIF('Contratos - G200'!C:C,'Gestão de Contratos'!B59,'Contratos - G200'!J:J) -> 120150 | G59: 240500 | H59: =SUM(D59:E59)=F59 -> FALSE | I59: =SUMIF('Notas fiscais - G200'!W54:W4939,'Gestão de Contratos'!B59,'Notas fiscais - G200'!T54:T4939) -> 0
... B61: CLSF/200-3-048 | C61: {=_xlfn.XLOOKUP(B61,'Contratos - G200'!C:C,'Contratos - G200'!D:D,X)} -> TM HIDRO SERVICOS DE PREPARACAO DE TERRENOS E TERRAPLANAGEM LTDA. | D61: 0 | E61: 34188.05 | F61: =SUMIF('Contratos - G200'!C:C,'Gestão de Contratos'!B61,'Contratos - G200'!J:J) -> 575368.71 | G61: 34188.05 | H61: =SUM(D61:E61)=F61 -> FALSE | I61: =SUMIF('Notas fiscais - G200'!W56:W4941,'Gestão de Contratos'!B61,'Notas fiscais - G200'!T56:T4941) -> 0
B62: CLSF/200-3-052
B63: CLSF/200-3-053
B64: CLSF/200-3-054
B65: CLSF/200-3-055
B66: CT-LSFG200-047
B67: 0

Sheet Contratos - G200
C2: Instruções: | D2: No Sienge (Suprimentos / Contratos e Medições / Relatórios / Contratos / Faturamentos diretos); | I2: No Sienge (Suprimentos / Contratos e Medições / Relatórios / Contratos / Faturamentos diretos);
D3: Obras 152/ Consultar / Gerar relatório excel; | I3: Obras 152/ Consultar / Gerar relatório excel;
C4: Observação: | D4: Esta planilha serva para a aba "analítico" não duplicar os custos, ou seja, para não associar as notas como uma nova contratação e estourar um saldo já contratado. | I4: Esta planilha serva para a aba "analítico" não duplicar os custos, ou seja, para não associar as notas como uma nova contratação e estourar um saldo já contratado.
E11: TOTAL | G11: =SUBTOTAL(9,G14:G1048576) -> 3.263279e+08 | I11: =G11-J11 -> 2141000 | J11: =SUBTOTAL(9,J14:J1048576) -> 3.241869e+08
C13: CONTRATO | D13: CREDOR | E13: APROPRIAÇÃO | F13: DESCRIÇÃO DA EAP | G13: VALOR | H13: ESCOPO DO CONTRATO | I13: VÍNCULO DE FATURAMENTO DIRETO | J13: VALOR À CONSIDERAR
B14: CT-LSFG200-000 | C14: CLSF/200-3-000 | D14: QPC ENGENHARIA LTDA | E14: 2001025001 | F14: =_xlfn.XLOOKUP(E14,'Detalhamento - G200'!A:A,'Detalhamento - G200'!B:B,0) -> DESPESAS INDIRETAS DE OBRA, CANTEIRO, INSTALAÇÕES PROVISÓRIAS - FATURAMENTO QPC | G14: 2000000 | H14: EXECUÇÃO DO PMG | J14: =IF(I14<>"",0,G14) -> 2000000
B15: CT-LSFG200-000 | C15: CLSF/200-3-000 | D15: QPC ENGENHARIA LTDA | E15: 2001025002 | F15: =_xlfn.XLOOKUP(E15,'Detalhamento - G200'!A:A,'Detalhamento - G200'!B:B,0) -> DESPESAS INDIRETAS DE OBRA - DESEMBOLSO CANTEIRO DE OBRAS | G15: 300000 | H15: EXECUÇÃO DO PMG | J15: =IF(I15<>"",0,G15) -> 300000
B16: CT-LSFG200-000 | C16: CLSF/200-3-000 | D16: QPC ENGENHARIA LTDA | E16: 2002001001 | F16: =_xlfn.XLOOKUP(E16,'Detalhamento - G200'!A:A,'Detalhamento - G200'!B:B,0) -> SALÁRIOS, DISSÍDIO/REAJUSTE E AJUDA DE CUSTO | G16: 19609894 | H16: EXECUÇÃO DO PMG | J16: =IF(I16<>"",0,G16) -> 19609894
B17: CT-LSFG200-000 | C17: CLSF/200-3-000 | D17: QPC ENGENHARIA LTDA | E17: 2003001001 | F17: =_xlfn.XLOOKUP(E17,'Detalhamento - G200'!A:A,'Detalhamento - G200'!B:B,0) -> FEE | G17: 36656469 | H17: EXECUÇÃO DO PMG | J17: =IF(I17<>"",0,G17) -> 36656469
B18: CT-LSFG200-001 | C18: CLSF/200-3-001 | D18: DPE ARQUITETURA E ENGENHARIA S/S | E18: 1001001001 | F18: =_xlfn.XLOOKUP(E18,'Detalhamento - G200'!A:A,'Detalhamento - G200'!B:B,0) -> PROJETOS | G18: 450000 | H18: PROJETO DE INSTALAÇÕES | J18: =IF(I18<>"",0,G18) -> 450000
B19: CT-LSFG200-002 | C19: CLSF/200-3-002 | D19: ARQUITETURA JAPI PROJETOS E CONSULTORIA EIRELI | E19: 1001001001 | F19: =_xlfn.XLOOKUP(E19,'Detalhamento - G200'!A:A,'Detalhamento - G200'!B:B,0) -> PROJETOS | G19: 472594.69 | H19: PROJETO DE ARQUITETURA | J19: =IF(I19<>"",0,G19) -> 472594.69
B20: CT-LSFG200-003 | C20: CLSF/200-3-003 | D20: DO VAL ENGENHARIA CONSULTIVA SOCIEDADE SIMPLES | E20: 1001001001 | F20: =_xlfn.XLOOKUP(E20,'Detalhamento - G200'!A:A,'Detalhamento - G200'!B:B,0) -> PROJETOS | G20: 100000 | H20: CQP FUNDAÇÃO E CONTENÇÃO | J20: =IF(I20<>"",0,G20) -> 100000
B21: CT-LSFG200-004 | C21: CLSF/200-3-004 | D21: LPE ENGENHARIA E CONSULTORIA LTDA | E21: 1001001001 | F21: =_xlfn.XLOOKUP(E21,'Detalhamento - G200'!A:A,'Detalhamento - G200'!B:B,0) -> PROJETOS | G21: 244000 | H21: PROJETO DE PISO DE CONCRETO | J21: =IF(I21<>"",0,G21) -> 244000
B22: CT-LSFG200-005 | C22: CLSF/200-3-005 | D22: T.T.C. ENGENHARIA DE TRAFEGO E DE TRANSPORTES LTDA | E22: 1001001001 | F22: =_xlfn.XLOOKUP(E22,'Detalhamento - G200'!A:A,'Detalhamento - G200'!B:B,0) -> PROJETOS | G22: 9200 | H22: PROJETO DE SINALIZAÇÃO VIÁRIA | J22: =IF(I22<>"",0,G22) -> 9200
B23: CT-LSFG200-006 | C23: CLSF/200-3-006 | D23: REV1 PROJETOS INTEGRADOS LTDA | E23: 1001001001 | F23: =_xlfn.XLOOKUP(E23,'Detalhamento - G200'!A:A,'Detalhamento - G200'!B:B,0) -> PROJETOS | G23: 16917 | H23: PROJETO DE EPC | J23: =IF(I23<>"",0,G23) -> 16917
B24: CT-LSFG200-007 | C24: CLSF/200-3-007 | D24: NUCLEORA PLANEJAMENTO, ASSESSORIA E DESENVOLVIMENTO COMERCIAL LTDA | E24: 1001001001 | F24: =_xlfn.XLOOKUP(E24,'Detalhamento - G200'!A:A,'Detalhamento - G200'!B:B,0) -> PROJETOS | G24: 45000 | H24: PROJETO DE COZINHA INDUSTRIAL | J24: =IF(I24<>"",0,G24) -> 45000
B25: CT-LSFG200-008 | C25: CLSF/200-3-008 | D25: KAIZ ENGENHARIA LTDA | E25: 1001001001 | F25: =_xlfn.XLOOKUP(E25,'Detalhamento - G200'!A:A,'Detalhamento - G200'!B:B,0) -> PROJETOS | G25: 64300 | H25: CQP PRÉ FABRICADO | J25: =IF(I25<>"",0,G25) -> 64300
B26: CT-LSFG200-009 | C26: CLSF/200-3-009 | D26: KAIZ ENGENHARIA LTDA | E26: 1001001001 | F26: =_xlfn.XLOOKUP(E26,'Detalhamento - G200'!A:A,'Detalhamento - G200'!B:B,0) -> PROJETOS | G26: 68300 | H26: PROJETOS ESTRUTURAS DE CONCRETO (IN-LOCO) E ALVENARIAS | J26: =IF(I26<>"",0,G26) -> 68300
B27: CT-LSFG200-010 | C27: CLSF/200-3-010 | D27: VENDRAMINI ENGENHARIA LTDA | E27: 1001003001 | F27: =_xlfn.XLOOKUP(E27,'Detalhamento - G200'!A:A,'Detalhamento - G200'!B:B,0) -> FUNDAÇÃO GALPÃO | G27: 1117668.8 | H27: PROJETO DE ESTRUTURAS PRÉ-FABRICADAS DE CONCRETO | I27: CLSF/200-3-033 | J27: =IF(I27<>"",0,G27) -> 0
B28: CT-LSFG200-010 | C28: CLSF/200-3-010 | D28: VENDRAMINI ENGENHARIA LTDA | E28: 1001003002 | F28: =_xlfn.XLOOKUP(E28,'Detalhamento - G200'!A:A,'Detalhamento - G200'!B:B,0) -> SUPERESTRUTURA GALPÃO | G28: 41644.8 | H28: PROJETO DE ESTRUTURAS PRÉ-FABRICADAS DE CONCRETO | I28: CLSF/200-3-033 | J28: =IF(I28<>"",0,G28) -> 0
B29: CT-LSFG200-010 | C29: CLSF/200-3-010 | D29: VENDRAMINI ENGENHARIA LTDA | E29: 1002002002 | F29: =_xlfn.XLOOKUP(E29,'Detalhamento - G200'!A:A,'Detalhamento - G200'!B:B,0) -> SUPERESTRUTURA | G29: 156686.4 | H29: PROJETO DE ESTRUTURAS PRÉ-FABRICADAS DE CONCRETO | I29: CLSF/200-3-033 | J29: =IF(I29<>"",0,G29) -> 0
B30: CT-LSFG200-011 | C30: CLSF/200-3-011 | D30: DO VAL ENGENHARIA CONSULTIVA SOCIEDADE SIMPLES | E30: 1001001001 | F30: =_xlfn.XLOOKUP(E30,'Detalhamento - G200'!A:A,'Detalhamento - G200'!B:B,0) -> PROJETOS | G30: 87000 | H30: PROJETO DE FUNDAÇÃO PROFUNDA - GALPÃO | J30: =IF(I30<>"",0,G30) -> 87000
B31: CT-LSFG200-012 | C31: CLSF/200-3-012 | D31: GEOTECHNIQUE CONSULTORIA E ENGENHARIA LTDA | E31: 1001001001 | F31: =_xlfn.XLOOKUP(E31,'Detalhamento - G200'!A:A,'Detalhamento - G200'!B:B,0) -> PROJETOS | G31: 250380 | H31: PROJETO DE TERRAPLANAGEM / FUNDAÇÃO/ DRENAGEM / CONTENÇÃO | J31: =IF(I31<>"",0,G31) -> 250380
B32: CT-LSFG200-013 | C32: CLSF/200-3-013 | D32: VENDRAMINI ENGENHARIA LTDA | E32: 1001001001 | F32: =_xlfn.XLOOKUP(E32,'Detalhamento - G200'!A:A,'Detalhamento - G200'!B:B,0) -> PROJETOS | G32: 153000 | H32: CQP METÁLICA | J32: =IF(I32<>"",0,G32) -> 153000
B33: CT-LSFG200-014 | C33: CLSF/200-3-014 | D33: LCL GEOTECNIA E SONDAGEM LTDA | E33: 1001001002 | F33: =_xlfn.XLOOKUP(E33,'Detalhamento - G200'!A:A,'Detalhamento - G200'!B:B,0) -> ENSAIOS E CONSULTORIAS | G33: 919769.9 | H33: CONTROLE TECNOLÓGICO DE SOLOS | J33: =IF(I33<>"",0,G33) -> 919769.9
B34: CT-LSFG200-015 | C34: CLSF/200-3-015 | D34: MAGALHAES JUNIOR LOCACAO E SERVICOS LTDA | E34: 1001002003 | F34: =_xlfn.XLOOKUP(E34,'Detalhamento - G200'!A:A,'Detalhamento - G200'!B:B,0) -> MOVIMENTAÇÃO DE TERRA | G34: 18314788 | H34: TERRAPLENAGEM | J34: =IF(I34<>"",0,G34) -> 18314788
B35: CT-LSFG200-015 | C35: CLSF/200-3-015 | D35: MAGALHAES JUNIOR LOCACAO E SERVICOS LTDA | E35: 1001002007 | F35: =_xlfn.XLOOKUP(E35,'Detalhamento - G200'!A:A,'Detalhamento - G200'!B:B,0) -> ESCAVAÇÃO NO TARDOZ | G35: 800400.01 | H35: TERRAPLENAGEM | J35: =IF(I35<>"",0,G35) -> 800400.01
B36: CT-LSFG200-016 | C36: CLSF/200-3-016 | D36: GEO2 ENGENHARIA LTDA | E36: 1001001002 | F36: =_xlfn.XLOOKUP(E36,'Detalhamento - G200'!A:A,'Detalhamento - G200'!B:B,0) -> ENSAIOS E CONSULTORIAS | G36: 732314.04 | H36: TOPOGRAFIA | J36: =IF(I36<>"",0,G36) -> 732314.04
B37: CT-LSFG200-017 | C37: CLSF/200-3-017 | D37: QUALYSAN LOCACAO DE BENS MOVEIS EIRELI | E37: 2001013001 | F37: =_xlfn.XLOOKUP(E37,'Detalhamento - G200'!A:A,'Detalhamento - G200'!B:B,0) -> LOCAÇÃO - SANITÁRIO QUÍMICO | G37: 89600 | H37: LOCAÇÃO DE BANHEIRO QUÍMICO | J37: =IF(I37<>"",0,G37) -> 89600
B38: CT-LSFG200-018 | C38: CLSF/200-3-018 | D38: FF INFRA E ENGENHARIA LTDA | E38: 2001001002 | F38: =_xlfn.XLOOKUP(E38,'Detalhamento - G200'!A:A,'Detalhamento - G200'!B:B,0) -> IMPLANTAÇÃO DE CANTEIRO - ELETRICA | G38: 316000 | H38: LIGAÇÃO DE ENERGIA PROVISÓRIA | J38: =IF(I38<>"",0,G38) -> 316000
B39: CT-LSFG200-019 | C39: CLSF/200-3-019 | D39: AQUAGEO PROJETOS E PERFURACOES LTDA | E39: 1001006003 | F39: =_xlfn.XLOOKUP(E39,'Detalhamento - G200'!A:A,'Detalhamento - G200'!B:B,0) -> POÇO ARTESIANO | G39: 286456.27 | H39: POÇO ARTESIANO | J39: =IF(I39<>"",0,G39) -> 286456.27
B40: CT-LSFG200-020 | C40: CLSF/200-3-020 | D40: SPM ENGENHARIA SOCIEDADE SIMPLES LTDA. | E40: 1003006001 | F40: =_xlfn.XLOOKUP(E40,'Detalhamento - G200'!A:A,'Detalhamento - G200'!B:B,0) -> PROJETOS, CQPS E AS BUILT | G40: 568700 | H40: ELABORAÇÃO DE PROJETO(S) PARA INSTALAÇÕES DE HVAC | I40: CLSF/200-3-042 | J40: =IF(I40<>"",0,G40) -> 0
B41: CT-LSFG200-021 | C41: CLSF/200-3-021 | D41: LAEROMEC - SOLUCOES EM ENGENHARIA LTDA | E41: 1003006001 | F41: =_xlfn.XLOOKUP(E41,'Detalhamento - G200'!A:A,'Detalhamento - G200'!B:B,0) -> PROJETOS, CQPS E AS BUILT | G41: 31300 | H41: ANÁLISE DINÂMICA DOS FLUIDOS COMPUTACIONAL DO PROJETO DE HVAC | I41: CLSF/200-3-042 | J41: =IF(I41<>"",0,G41) -> 0
B42: CT-LSFG200-022 | C42: CLSF/200-3-022 | D42: SOLOBAHIA ENGENHARIA E TECNOLOGIA LTDA | E42: 1001001002 | F42: =_xlfn.XLOOKUP(E42,'Detalhamento - G200'!A:A,'Detalhamento - G200'!B:B,0) -> ENSAIOS E CONSULTORIAS | G42: 141411.45 | H42: SONDAGENS | J42: =IF(I42<>"",0,G42) -> 141411.45
B43: CT-LSFG200-023 | C43: CLSF/200-3-023 | D43: LESSA EVENTOS LTDA | E43: 1001002003 | F43: =_xlfn.XLOOKUP(E43,'Detalhamento - G200'!A:A,'Detalhamento - G200'!B:B,0) -> MOVIMENTAÇÃO DE TERRA | G43: 9586.11 | H43: ALIMENTAÇÃO | J43: =IF(I43<>"",0,G43) -> 9586.11
B44: CT-LSFG200-023 | C44: CLSF/200-3-023 | D44: LESSA EVENTOS LTDA | E44: 1001002006 | F44: =_xlfn.XLOOKUP(E44,'Detalhamento - G200'!A:A,'Detalhamento - G200'!B:B,0) -> CONTENÇÕES | G44: 142887.34 | H44: ALIMENTAÇÃO | J44: =IF(I44<>"",0,G44) -> 142887.34
B45: CT-LSFG200-023 | C45: CLSF/200-3-023 | D45: LESSA EVENTOS LTDA | E45: 1001002008 | F45: =_xlfn.XLOOKUP(E45,'Detalhamento - G200'!A:A,'Detalhamento - G200'!B:B,0) -> DRENAGEM | G45: 190998.76 | H45: ALIMENTAÇÃO | J45: =IF(I45<>"",0,G45) -> 190998.76
B46: CT-LSFG200-023 | C46: CLSF/200-3-023 | D46: LESSA EVENTOS LTDA | E46: 1001003001 | F46: =_xlfn.XLOOKUP(E46,'Detalhamento - G200'!A:A,'Detalhamento - G200'!B:B,0) -> FUNDAÇÃO GALPÃO | G46: 75422.81 | H46: ALIMENTAÇÃO | J46: =IF(I46<>"",0,G46) -> 75422.81
B47: CT-LSFG200-023 | C47: CLSF/200-3-023 | D47: LESSA EVENTOS LTDA | E47: 1001003002 | F47: =_xlfn.XLOOKUP(E47,'Detalhamento - G200'!A:A,'Detalhamento - G200'!B:B,0) -> SUPERESTRUTURA GALPÃO | G47: 4702.62 | H47: ALIMENTAÇÃO | J47: =IF(I47<>"",0,G47) -> 4702.62
B48: CT-LSFG200-023 | C48: CLSF/200-3-023 | D48: LESSA EVENTOS LTDA | E48: 1001003006 | F48: =_xlfn.XLOOKUP(E48,'Detalhamento - G200'!A:A,'Detalhamento - G200'!B:B,0) -> IMPERMEABILIZAÇÃO | G48: 16640.04 | H48: ALIMENTAÇÃO | J48: =IF(I48<>"",0,G48) -> 16640.04
B49: CT-LSFG200-023 | C49: CLSF/200-3-023 | D49: LESSA EVENTOS LTDA | E49: 1001004002 | F49: =_xlfn.XLOOKUP(E49,'Detalhamento - G200'!A:A,'Detalhamento - G200'!B:B,0) -> APOIO (VESTIÁRIO + REFEITÓRIO) | G49: 261538.08 | H49: ALIMENTAÇÃO | J49: =IF(I49<>"",0,G49) -> 261538.08
B50: CT-LSFG200-023 | C50: CLSF/200-3-023 | D50: LESSA EVENTOS LTDA | E50: 1001004005 | F50: =_xlfn.XLOOKUP(E50,'Detalhamento - G200'!A:A,'Detalhamento - G200'!B:B,0) -> UTILIDADES | G50: 26768.77 | H50: ALIMENTAÇÃO | J50: =IF(I50<>"",0,G50) -> 26768.77
B51: CT-LSFG200-023 | C51: CLSF/200-3-023 | D51: LESSA EVENTOS LTDA | E51: 1001004006 | F51: =_xlfn.XLOOKUP(E51,'Detalhamento - G200'!A:A,'Detalhamento - G200'!B:B,0) -> SANITÁRIOS EXTERNOS AO GALPÃO | G51: 189009.19 | H51: ALIMENTAÇÃO | J51: =IF(I51<>"",0,G51) -> 189009.19
B52: CT-LSFG200-023 | C52: CLSF/200-3-023 | D52: LESSA EVENTOS LTDA | E52: 1001006006 | F52: =_xlfn.XLOOKUP(E52,'Detalhamento - G200'!A:A,'Detalhamento - G200'!B:B,0) -> ETE | G52: 18991.35 | H52: ALIMENTAÇÃO | J52: =IF(I52<>"",0,G52) -> 18991.35
B53: CT-LSFG200-023 | C53: CLSF/200-3-023 | D53: LESSA EVENTOS LTDA | E53: 1002002001 | F53: =_xlfn.XLOOKUP(E53,'Detalhamento - G200'!A:A,'Detalhamento - G200'!B:B,0) -> FUNDAÇÃO | G53: 65113.21 | H53: ALIMENTAÇÃO | J53: =IF(I53<>"",0,G53) -> 65113.21
... B116: CT-LSFG200-043 | C116: CLSF/200-3-043 | D116: NEOSONDA ENGENHARIA LTDA | E116: 1001006006 | F116: =_xlfn.XLOOKUP(E116,'Detalhamento - G200'!A:A,'Detalhamento - G200'!B:B,0) -> ETE | G116: 240500 | H116: EXECUÇÃO DE FUNDAÇÃO EM ESTACA RAIZ PARA ETE | J116: =IF(I116<>"",0,G116) -> 240500
B117: CT-LSFG200-044 | C117: CLSF/200-3-044 | D117: PRESOTTO SERVICOS DE ENGENHARIA LTDA | E117: 1003006001 | F117: =_xlfn.XLOOKUP(E117,'Detalhamento - G200'!A:A,'Detalhamento - G200'!B:B,0) -> PROJETOS, CQPS E AS BUILT | G117: 225000 | H117: COMISSIONAMENTO E RELATÓRIO DE CONFORMIDADE | I117: CLSF/200-3-042 | J117: =IF(I117<>"",0,G117) -> 0
B118: CT-LSFG200-045 | C118: CLSF/200-3-045 | D118: TGEO SERVICOS DE ENGENHARIA E GEOLOGIA LTDA | E118: 1001001002 | F118: =_xlfn.XLOOKUP(E118,'Detalhamento - G200'!A:A,'Detalhamento - G200'!B:B,0) -> ENSAIOS E CONSULTORIAS | G118: 120150 | H118: SONDAGEM ROTATIVA E A PERCUSSÃO | J118: =IF(I118<>"",0,G118) -> 120150
B119: CT-LSFG200-046 | C119: CLSF/200-3-046 | D119: LCL GEOTECNIA E SONDAGEM LTDA | E119: 1001001002 | F119: =_xlfn.XLOOKUP(E119,'Detalhamento - G200'!A:A,'Detalhamento - G200'!B:B,0) -> ENSAIOS E CONSULTORIAS | G119: 34188.05 | H119: SONDAGEM ROTATIVA E A PERCUSSÃO | J119: =IF(I119<>"",0,G119) -> 34188.05
B120: CT-LSFG200-048 | C120: CLSF/200-3-048 | D120: TM HIDRO SERVICOS DE PREPARACAO DE TERRENOS E TERRAPLANAGEM LTDA. | E120: 1001002005 | F120: =_xlfn.XLOOKUP(E120,'Detalhamento - G200'!A:A,'Detalhamento - G200'!B:B,0) -> HIDROSSEMEADURA | G120: 575368.71 | H120: REGULARIZAÇÃO, NIVELAMENTO DAS IRREGULARIDADES NAS ÁREAS DOS TALUDES | J120: =IF(I120<>"",0,G120) -> 575368.71
B121: CT-LSFG200-052 | C121: CLSF/200-3-052 | D121: VOC ENGENHARIA E CONSTRUCAO LTDA | E121: 2001001001 | F121: =_xlfn.XLOOKUP(E121,'Detalhamento - G200'!A:A,'Detalhamento - G200'!B:B,0) -> BASE DE OPERACIONAL | G121: 786497.6 | H121: MÃO DE-OBRA PARA MANUTENÇÃO E INSTALAÇÕES DO CANTEIRO DE OBRAS | J121: =IF(I121<>"",0,G121) -> 786497.6
B122: CT-LSFG200-053 | C122: CLSF/200-3-053 | D122: VOC ENGENHARIA E CONSTRUCAO LTDA | E122: 1001004006 | F122: =_xlfn.XLOOKUP(E122,'Detalhamento - G200'!A:A,'Detalhamento - G200'!B:B,0) -> SANITÁRIOS EXTERNOS AO GALPÃO | G122: =(2.6813*8249.02)+(77881.98) -> 100000.08 | H122: SERVIÇOS COMO CAMINHOS DE ACESSO, LINHA DE VIDA, ORGANIZAÇÃO DE BAIAS E PONTOS DE APOIO | J122: =IF(I122<>"",0,G122) -> 100000.08
B123: CT-LSFG200-053 | C123: CLSF/200-3-053 | D123: VOC ENGENHARIA E CONSTRUCAO LTDA | E123: 1001004002 | F123: =_xlfn.XLOOKUP(E123,'Detalhamento - G200'!A:A,'Detalhamento - G200'!B:B,0) -> APOIO (VESTIÁRIO + REFEITÓRIO) | G123: =(16*11221.47)+( 2.4799* 8249.02) -> 200000.26 | H123: SERVIÇOS COMO CAMINHOS DE ACESSO, LINHA DE VIDA, ORGANIZAÇÃO DE BAIAS E PONTOS DE APOIO | J123: =IF(I123<>"",0,G123) -> 200000.26
B124: CT-LSFG200-053 | C124: CLSF/200-3-053 | D124: VOC ENGENHARIA E CONSTRUCAO LTDA | E124: 1001004010 | F124: =_xlfn.XLOOKUP(E124,'Detalhamento - G200'!A:A,'Detalhamento - G200'!B:B,0) -> ÁREA DE LAZER | G124: =6.0613* 8249.02 -> 49999.785 | H124: SERVIÇOS COMO CAMINHOS DE ACESSO, LINHA DE VIDA, ORGANIZAÇÃO DE BAIAS E PONTOS DE APOIO | J124: =IF(I124<>"",0,G124) -> 49999.785
B125: CT-LSFG200-053 | C125: CLSF/200-3-053 | D125: VOC ENGENHARIA E CONSTRUCAO LTDA | E125: 1001004005 | F125: =_xlfn.XLOOKUP(E125,'Detalhamento - G200'!A:A,'Detalhamento - G200'!B:B,0) -> UTILIDADES | G125: =4.7775*8249.02 -> 39409.693 | H125: SERVIÇOS COMO CAMINHOS DE ACESSO, LINHA DE VIDA, ORGANIZAÇÃO DE BAIAS E PONTOS DE APOIO | J125: =IF(I125<>"",0,G125) -> 39409.693
B126: CT-LSFG200-054 | C126: CLSF/200-3-054 | D126: VOC ENGENHARIA E CONSTRUCAO LTDA | E126: 1001002003 | F126: =_xlfn.XLOOKUP(E126,'Detalhamento - G200'!A:A,'Detalhamento - G200'!B:B,0) -> MOVIMENTAÇÃO DE TERRA | G126: 448858.88 | H126: MÃO DE OBRA PARA ATENDIMENTO ÀS ATIVIDADES OPERACIONAIS EM CAMPO, RELACIONADAS À ORIENTAÇÃO DA MOVIMENTAÇÃO DE EQUIPAMENTOS E VEÍCULOS | J126: =IF(I126<>"",0,G126) -> 448858.88
B127: CT-LSFG200-055 | C127: CLSF/200-3-055 | D127: VOC ENGENHARIA E CONSTRUCAO LTDA | E127: 1001002003 | F127: =_xlfn.XLOOKUP(E127,'Detalhamento - G200'!A:A,'Detalhamento - G200'!B:B,0) -> MOVIMENTAÇÃO DE TERRA | G127: 329960.96 | H127: MÃO-DE-OBRA PARA ATENDIMENTO ÀS ATIVIDADES DE OPERAÇÃO, SERVIÇOS DE LIMPEZA E MANUTENÇÃO VIÁRIA | J127: =IF(I127<>"",0,G127) -> 329960.96
B128: CT-LSFG200-047 | C128: CT-LSFG200-047 | D128: CAME DO BRASIL INDUSTRIA, IMP. EXP, COMERCIO E SERVIÇOS DE AUTOMAÇÃO LTDA. | E128: 1001004001 | F128: =_xlfn.XLOOKUP(E128,'Detalhamento - G200'!A:A,'Detalhamento - G200'!B:B,0) -> PORTARIA / COBERTURA DA ECLUSA | G128: 1528000.4 | H128: EXECUÇÃO DE TORNIQUETES, TOTEM, CANCELAS 4 MTS COM LEDS, SEMÁFOROS, BOLLARDS AUTOMÁTICOS | J128: =IF(I128<>"",0,G128) -> 1528000.4

Sheet Projeções - G200
C2: OBRA | D2: G200
C3: INÍCIO
C4: TÉRMINO
C5: RESPONSÁVEL | D5: SÉRGIO COSTA
C7: TOTAIS | D7: =SUM(D10:D201) -> 0 | F7: =SUM(F10:F201) -> -267155.08
D8: =D7='Detalhamento - G200'!G6 -> FALSE | E8: ATUALIZAR AQUI | F8: =F7='Detalhamento - G200'!I6 -> TRUE
B9: APROPRIAÇÃO | C9: DESCRIÇÃO | D9: SALDO | E9: PREVISÃO | F9: PROJEÇÕES | G9: OBSERVAÇÃO
B10: =_xlfn.XLOOKUP(C10,'Detalhamento - G200'!B6:B253,'Detalhamento - G200'!A6:A253,0) -> 1001001001 | C10: PROJETOS | D10: =VLOOKUP(B10,'Detalhamento - G200'!A:G,5,) -> 0 | F10: =D10+E10 -> 0
B11: =_xlfn.XLOOKUP(C11,'Detalhamento - G200'!B7:B254,'Detalhamento - G200'!A7:A254,0) -> 1001001002 | C11: ENSAIOS E CONSULTORIAS | D11: =VLOOKUP(B11,'Detalhamento - G200'!A:G,5,) -> 0 | F11: =D11+E11 -> 0
B12: =_xlfn.XLOOKUP(C12,'Detalhamento - G200'!B8:B255,'Detalhamento - G200'!A8:A255,0) -> 1001002002 | C12: MOVIMENTO DE TERRA - ESCOPO MÍNIMO | D12: =VLOOKUP(B12,'Detalhamento - G200'!A:G,5,) -> 0 | F12: =D12+E12 -> 0
B13: =_xlfn.XLOOKUP(C13,'Detalhamento - G200'!B9:B256,'Detalhamento - G200'!A9:A256,0) -> 1001002003 | C13: MOVIMENTAÇÃO DE TERRA | D13: =VLOOKUP(B13,'Detalhamento - G200'!A:G,5,) -> 0 | F13: =D13+E13 -> 0
B14: =_xlfn.XLOOKUP(C14,'Detalhamento - G200'!B10:B257,'Detalhamento - G200'!A10:A257,0) -> 1001002004 | C14: LINHA DE VIDA MOVEL PARA TALUDES | D14: =VLOOKUP(B14,'Detalhamento - G200'!A:G,5,) -> 0 | F14: =D14+E14 -> 0
B15: =_xlfn.XLOOKUP(C15,'Detalhamento - G200'!B11:B258,'Detalhamento - G200'!A11:A258,0) -> 1001002005 | C15: HIDROSSEMEADURA | D15: =VLOOKUP(B15,'Detalhamento - G200'!A:G,5,) -> 0 | F15: =D15+E15 -> 0
B16: =_xlfn.XLOOKUP(C16,'Detalhamento - G200'!B12:B259,'Detalhamento - G200'!A12:A259,0) -> 1001002006 | C16: CONTENÇÕES | D16: =VLOOKUP(B16,'Detalhamento - G200'!A:G,5,) -> 0 | F16: =D16+E16 -> 0
B17: =_xlfn.XLOOKUP(C17,'Detalhamento - G200'!B13:B260,'Detalhamento - G200'!A13:A260,0) -> 1001002007 | C17: ESCAVAÇÃO NO TARDOZ | D17: =VLOOKUP(B17,'Detalhamento - G200'!A:G,5,) -> 0 | F17: =D17+E17 -> 0
B18: =_xlfn.XLOOKUP(C18,'Detalhamento - G200'!B14:B261,'Detalhamento - G200'!A14:A261,0) -> 1001002008 | C18: DRENAGEM | D18: =VLOOKUP(B18,'Detalhamento - G200'!A:G,5,) -> 0 | F18: =D18+E18 -> 0
B19: =_xlfn.XLOOKUP(C19,'Detalhamento - G200'!B15:B262,'Detalhamento - G200'!A15:A262,0) -> 1001003001 | C19: FUNDAÇÃO GALPÃO | D19: =VLOOKUP(B19,'Detalhamento - G200'!A:G,5,) -> 0 | F19: =D19+E19 -> 0
B20: =_xlfn.XLOOKUP(C20,'Detalhamento - G200'!B16:B263,'Detalhamento - G200'!A16:A263,0) -> 1001003002 | C20: SUPERESTRUTURA GALPÃO | D20: =VLOOKUP(B20,'Detalhamento - G200'!A:G,5,) -> 0 | F20: =D20+E20 -> 0 | G20: PREVISÃO - EQUALIZAÇÃO DO CONTRATO T&A
B21: =_xlfn.XLOOKUP(C21,'Detalhamento - G200'!B17:B264,'Detalhamento - G200'!A17:A264,0) -> 1001003003 | C21: COBERTURA E FECHAMENTO METALICO | D21: =VLOOKUP(B21,'Detalhamento - G200'!A:G,5,) -> 0 | F21: =D21+E21 -> 0
B22: =_xlfn.XLOOKUP(C22,'Detalhamento - G200'!B18:B265,'Detalhamento - G200'!A18:A265,0) -> 1001003004 | C22: PISO DE CONCRETO | D22: =VLOOKUP(B22,'Detalhamento - G200'!A:G,5,) -> 0 | F22: =D22+E22 -> 0
B23: =_xlfn.XLOOKUP(C23,'Detalhamento - G200'!B19:B266,'Detalhamento - G200'!A19:A266,0) -> 1001003005 | C23: ESQUADRIAS E CAIXILHOS | D23: =VLOOKUP(B23,'Detalhamento - G200'!A:G,5,) -> 0 | F23: =D23+E23 -> 0
B24: =_xlfn.XLOOKUP(C24,'Detalhamento - G200'!B20:B267,'Detalhamento - G200'!A20:A267,0) -> 1001003006 | C24: IMPERMEABILIZAÇÃO | D24: =VLOOKUP(B24,'Detalhamento - G200'!A:G,5,) -> 0 | F24: =D24+E24 -> 0
B25: =_xlfn.XLOOKUP(C25,'Detalhamento - G200'!B21:B268,'Detalhamento - G200'!A21:A268,0) -> 1001003007 | C25: REVESTIMENTOS | D25: =VLOOKUP(B25,'Detalhamento - G200'!A:G,5,) -> 0 | F25: =D25+E25 -> 0
B26: =_xlfn.XLOOKUP(C26,'Detalhamento - G200'!B22:B269,'Detalhamento - G200'!A22:A269,0) -> 1001003008 | C26: FORRO | D26: =VLOOKUP(B26,'Detalhamento - G200'!A:G,5,) -> 0 | F26: =D26+E26 -> 0
B27: =_xlfn.XLOOKUP(C27,'Detalhamento - G200'!B23:B270,'Detalhamento - G200'!A23:A270,0) -> 1001003009 | C27: LOUÇAS, METAIS E INSTALAÇÕES DE BANHEIRO | D27: =VLOOKUP(B27,'Detalhamento - G200'!A:G,5,) -> 0 | F27: =D27+E27 -> 0
B28: =_xlfn.XLOOKUP(C28,'Detalhamento - G200'!B24:B271,'Detalhamento - G200'!A24:A271,0) -> 1001003010 | C28: SERRALHERIA GALPÃO | D28: =VLOOKUP(B28,'Detalhamento - G200'!A:G,5,) -> 0 | F28: =D28+E28 -> 0
B29: =_xlfn.XLOOKUP(C29,'Detalhamento - G200'!B25:B272,'Detalhamento - G200'!A25:A272,0) -> 1001003011 | C29: EQUIPAMENTOS GALPÃO | D29: =VLOOKUP(B29,'Detalhamento - G200'!A:G,5,) -> 0 | E29: -646893.62 | F29: =D29+E29 -> -646893.62 | G29: PREVISÃO - GANHO DE CONTRATAÇÃO KOPRON
B30: =_xlfn.XLOOKUP(C30,'Detalhamento - G200'!B26:B273,'Detalhamento - G200'!A26:A273,0) -> 1001003012 | C30: PINTURA GALPÃO | D30: =VLOOKUP(B30,'Detalhamento - G200'!A:G,5,) -> 0 | F30: =D30+E30 -> 0
B31: =_xlfn.XLOOKUP(C31,'Detalhamento - G200'!B27:B274,'Detalhamento - G200'!A27:A274,0) -> 1001003013 | C31: LIMPEZA GALPÃO | D31: =VLOOKUP(B31,'Detalhamento - G200'!A:G,5,) -> 0 | F31: =D31+E31 -> 0
B32: =_xlfn.XLOOKUP(C32,'Detalhamento - G200'!B28:B275,'Detalhamento - G200'!A28:A275,0) -> 1001003014 | C32: COMUNICAÇÃO VISUAL GALPÃO | D32: =VLOOKUP(B32,'Detalhamento - G200'!A:G,5,) -> 0 | F32: =D32+E32 -> 0
B33: =_xlfn.XLOOKUP(C33,'Detalhamento - G200'!B29:B276,'Detalhamento - G200'!A29:A276,0) -> 1001004001 | C33: PORTARIA / COBERTURA DA ECLUSA | D33: =VLOOKUP(B33,'Detalhamento - G200'!A:G,5,) -> 0 | F33: =D33+E33 -> 0
B34: =_xlfn.XLOOKUP(C34,'Detalhamento - G200'!B30:B277,'Detalhamento - G200'!A30:A277,0) -> 1001004002 | C34: APOIO (VESTIÁRIO + REFEITÓRIO) | D34: =VLOOKUP(B34,'Detalhamento - G200'!A:G,5,) -> 0 | F34: =D34+E34 -> 0
B35: =_xlfn.XLOOKUP(C35,'Detalhamento - G200'!B31:B278,'Detalhamento - G200'!A31:A278,0) -> 1001004003 | C35: COBERTURA PEDESTRES | D35: =VLOOKUP(B35,'Detalhamento - G200'!A:G,5,) -> 0 | F35: =D35+E35 -> 0
B36: =_xlfn.XLOOKUP(C36,'Detalhamento - G200'!B32:B279,'Detalhamento - G200'!A32:A279,0) -> 1001004004 | C36: APOIO MOTORISTA | D36: =VLOOKUP(B36,'Detalhamento - G200'!A:G,5,) -> 0 | F36: =D36+E36 -> 0
B37: =_xlfn.XLOOKUP(C37,'Detalhamento - G200'!B33:B280,'Detalhamento - G200'!A33:A280,0) -> 1001004005 | C37: UTILIDADES | D37: =VLOOKUP(B37,'Detalhamento - G200'!A:G,5,) -> 0 | F37: =D37+E37 -> 0
B38: =_xlfn.XLOOKUP(C38,'Detalhamento - G200'!B34:B281,'Detalhamento - G200'!A34:A281,0) -> 1001004006 | C38: SANITÁRIOS EXTERNOS AO GALPÃO | D38: =VLOOKUP(B38,'Detalhamento - G200'!A:G,5,) -> 0 | F38: =D38+E38 -> 0
B39: =_xlfn.XLOOKUP(C39,'Detalhamento - G200'!B35:B282,'Detalhamento - G200'!A35:A282,0) -> 1001004007 | C39: PASSARELA DE PEDESTRES / COBERTURA DE ESTACIONAMENTO | D39: =VLOOKUP(B39,'Detalhamento - G200'!A:G,5,) -> 0 | F39: =D39+E39 -> 0
B40: =_xlfn.XLOOKUP(C40,'Detalhamento - G200'!B36:B283,'Detalhamento - G200'!A36:A283,0) -> 1001004008 | C40: BICICLETÁRIO | D40: =VLOOKUP(B40,'Detalhamento - G200'!A:G,5,) -> 0 | F40: =D40+E40 -> 0
B41: =_xlfn.XLOOKUP(C41,'Detalhamento - G200'!B37:B284,'Detalhamento - G200'!A37:A284,0) -> 1001004009 | C41: LIXO | D41: =VLOOKUP(B41,'Detalhamento - G200'!A:G,5,) -> 0 | F41: =D41+E41 -> 0
B42: =_xlfn.XLOOKUP(C42,'Detalhamento - G200'!B38:B285,'Detalhamento - G200'!A38:A285,0) -> 1001004010 | C42: ÁREA DE LAZER | D42: =VLOOKUP(B42,'Detalhamento - G200'!A:G,5,) -> 0 | F42: =D42+E42 -> 0
B43: =_xlfn.XLOOKUP(C43,'Detalhamento - G200'!B39:B286,'Detalhamento - G200'!A39:A286,0) -> 1001005001 | C43: ELETRICA, HIDRÁULICA E COMBATE A INCÊNDIO - MEP | D43: =VLOOKUP(B43,'Detalhamento - G200'!A:G,5,) -> 0 | E43: -1067074.5 | F43: =D43+E43 -> -1067074.5 | G43: PREVISÃO - GANHO DE CONTRATAÇÃO ARTEMP INSTALAÇÕES
B44: =_xlfn.XLOOKUP(C44,'Detalhamento - G200'!B40:B287,'Detalhamento - G200'!A40:A287,0) -> 1001005002 | C44: SISTEMA DE AR CONDICIONADO E EXAUSTÃO | D44: =VLOOKUP(B44,'Detalhamento - G200'!A:G,5,) -> 0 | F44: =D44+E44 -> 0
B45: =_xlfn.XLOOKUP(C45,'Detalhamento - G200'!B41:B288,'Detalhamento - G200'!A41:A288,0) -> 1001006001 | C45: PAVIMENTAÇÃO EXTERNA | D45: =VLOOKUP(B45,'Detalhamento - G200'!A:G,5,) -> 0 | F45: =D45+E45 -> 0
B46: =_xlfn.XLOOKUP(C46,'Detalhamento - G200'!B42:B289,'Detalhamento - G200'!A42:A289,0) -> 1001006002 | C46: FECHAMENTO PERIMETRAL E PAISAGISMO | D46: =VLOOKUP(B46,'Detalhamento - G200'!A:G,5,) -> 0 | F46: =D46+E46 -> 0
B47: =_xlfn.XLOOKUP(C47,'Detalhamento - G200'!B43:B290,'Detalhamento - G200'!A43:A290,0) -> 1001006003 | C47: POÇO ARTESIANO | D47: =VLOOKUP(B47,'Detalhamento - G200'!A:G,5,) -> 0 | F47: =D47+E47 -> 0 | G47: PREVISÃO - PREVISTO A VENDA DO POÇO E MENOR PERFURAÇÃO CONTRATO AQUAGEO
B48: =_xlfn.XLOOKUP(C48,'Detalhamento - G200'!B44:B291,'Detalhamento - G200'!A44:A291,0) -> 1001006004 | C48: RESERVATÓRIO METÁLICO | D48: =VLOOKUP(B48,'Detalhamento - G200'!A:G,5,) -> 0 | E48: -37000 | F48: =D48+E48 -> -37000 | G48: PREVISÃO - GANHO DE CONTRATAÇÃO DIPAWA
B49: =_xlfn.XLOOKUP(C49,'Detalhamento - G200'!B45:B292,'Detalhamento - G200'!A45:A292,0) -> 1001006005 | C49: FUNDAÇÃO PARA RESERVATÓRIO METÁLICO | D49: =VLOOKUP(B49,'Detalhamento - G200'!A:G,5,) -> 0 | F49: =D49+E49 -> 0
B50: =_xlfn.XLOOKUP(C50,'Detalhamento - G200'!B46:B293,'Detalhamento - G200'!A46:A293,0) -> 1001006006 | C50: ETE | D50: =VLOOKUP(B50,'Detalhamento - G200'!A:G,5,) -> 0 | F50: =D50+E50 -> 0
B51: =_xlfn.XLOOKUP(C51,'Detalhamento - G200'!B47:B294,'Detalhamento - G200'!A47:A294,0) -> 1001006007 | C51: DIVERSOS | D51: =VLOOKUP(B51,'Detalhamento - G200'!A:G,5,) -> 0 | F51: =D51+E51 -> 0
B52: =_xlfn.XLOOKUP(C52,'Detalhamento - G200'!B48:B295,'Detalhamento - G200'!A48:A295,0) -> 1002001001 | C52: PROJETO | D52: =VLOOKUP(B52,'Detalhamento - G200'!A:G,5,) -> 0 | F52: =D52+E52 -> 0
B53: =_xlfn.XLOOKUP(C53,'Detalhamento - G200'!B49:B296,'Detalhamento - G200'!A49:A296,0) -> 1002001002 | C53: ENSAIO E CONSULTORIA | D53: =VLOOKUP(B53,'Detalhamento - G200'!A:G,5,) -> 0 | F53: =D53+E53 -> 0
B54: =_xlfn.XLOOKUP(C54,'Detalhamento - G200'!B50:B297,'Detalhamento - G200'!A50:A297,0) -> 1002002001 | C54: FUNDAÇÃO | D54: =VLOOKUP(B54,'Detalhamento - G200'!A:G,5,) -> 0 | F54: =D54+E54 -> 0
B55: =_xlfn.XLOOKUP(C55,'Detalhamento - G200'!B51:B298,'Detalhamento - G200'!A51:A298,0) -> 1002002002 | C55: SUPERESTRUTURA | D55: =VLOOKUP(B55,'Detalhamento - G200'!A:G,5,) -> 0 | E55: 2472610.9 | F55: =D55+E55 -> 2472610.9 | G55: PREVISÃO - EQUALIZAÇÃO DO CONTRATO T&A
B56: =_xlfn.XLOOKUP(C56,'Detalhamento - G200'!B52:B299,'Detalhamento - G200'!A52:A299,0) -> 1002002003 | C56: CAPEAMENTO | D56: =VLOOKUP(B56,'Detalhamento - G200'!A:G,5,) -> 0 | F56: =D56+E56 -> 0
B57: =_xlfn.XLOOKUP(C57,'Detalhamento - G200'!B53:B300,'Detalhamento - G200'!A53:A300,0) -> 1002002004 | C57: SERRALHERIA | D57: =VLOOKUP(B57,'Detalhamento - G200'!A:G,5,) -> 0 | E57: -247851.13 | F57: =D57+E57 -> -247851.13 | G57: PREVISÃO - GANHO DE CONTRATAÇÃO SOTEC
B58: =_xlfn.XLOOKUP(C58,'Detalhamento - G200'!B54:B301,'Detalhamento - G200'!A54:A301,0) -> 1002002005 | C58: PINTURA | D58: =VLOOKUP(B58,'Detalhamento - G200'!A:G,5,) -> 0 | F58: =D58+E58 -> 0
B59: =_xlfn.XLOOKUP(C59,'Detalhamento - G200'!B55:B302,'Detalhamento - G200'!A55:A302,0) -> 1002002006 | C59: LIMPEZA | D59: =VLOOKUP(B59,'Detalhamento - G200'!A:G,5,) -> 0 | F59: =D59+E59 -> 0
B60: =_xlfn.XLOOKUP(C60,'Detalhamento - G200'!B56:B303,'Detalhamento - G200'!A56:A303,0) -> 1002003001 | C60: ELETRICA, HIDRÁULICA E COMBATE A INCÊNDIO | D60: =VLOOKUP(B60,'Detalhamento - G200'!A:G,5,) -> 0 | F60: =D60+E60 -> 0
B61: =_xlfn.XLOOKUP(C61,'Detalhamento - G200'!B57:B304,'Detalhamento - G200'!A57:A304,0) -> 1003001001 | C61: EQUIPAMENTO | D61: =VLOOKUP(B61,'Detalhamento - G200'!A:G,5,) -> 0 | E61: -892310.27 | F61: =D61+E61 -> -892310.27 | G61: PREVISÃO - GANHO DE CONTRATAÇÃO ARTEMP TÉRMICA
B62: =_xlfn.XLOOKUP(C62,'Detalhamento - G200'!B58:B305,'Detalhamento - G200'!A58:A305,0) -> 1003002001 | C62: CAVALETES HIDRÁULICOS E VÁLVULAS | D62: =VLOOKUP(B62,'Detalhamento - G200'!A:G,5,) -> 0 | F62: =D62+E62 -> 0
B63: =_xlfn.XLOOKUP(C63,'Detalhamento - G200'!B59:B306,'Detalhamento - G200'!A59:A306,0) -> 1003002002 | C63: REDE HIDRÁULICA | D63: =VLOOKUP(B63,'Detalhamento - G200'!A:G,5,) -> 0 | E63: 0.0099999998 | F63: =D63+E63 -> 0.0099999998
B64: =_xlfn.XLOOKUP(C64,'Detalhamento - G200'!B60:B307,'Detalhamento - G200'!A60:A307,0) -> 1003003001 | C64: QUADROS ELÉTRICOS E AUTOMAÇÃO | D64: =VLOOKUP(B64,'Detalhamento - G200'!A:G,5,) -> 0 | F64: =D64+E64 -> 0
B65: =_xlfn.XLOOKUP(C65,'Detalhamento - G200'!B61:B308,'Detalhamento - G200'!A61:A308,0) -> 1003003002 | C65: INTERLIGAÇÕES ELÉTRICAS | D65: =VLOOKUP(B65,'Detalhamento - G200'!A:G,5,) -> 0 | F65: =D65+E65 -> 0
B66: =_xlfn.XLOOKUP(C66,'Detalhamento - G200'!B62:B309,'Detalhamento - G200'!A62:A309,0) -> 1003004001 | C66: REDES DE DUTOS | D66: =VLOOKUP(B66,'Detalhamento - G200'!A:G,5,) -> 0 | E66: 236.38 | F66: =D66+E66 -> 236.38 | G66: EQUALIZAÇÃO ARTEMP TÉRMICA - APROXIMAÇÃO SIENGE
B67: =_xlfn.XLOOKUP(C67,'Detalhamento - G200'!B63:B310,'Detalhamento - G200'!A63:A310,0) -> 1003004002 | C67: DIFUSÃO | D67: =VLOOKUP(B67,'Detalhamento - G200'!A:G,5,) -> 0 | E67: -236.38 | F67: =D67+E67 -> -236.38 | G67: EQUALIZAÇÃO ARTEMP TÉRMICA - APROXIMAÇÃO SIENGE
B68: =_xlfn.XLOOKUP(C68,'Detalhamento - G200'!B64:B311,'Detalhamento - G200'!A64:A311,0) -> 1003005001 | C68: SERVIÇO CIVIL | D68: =VLOOKUP(B68,'Detalhamento - G200'!A:G,5,) -> 0 | F68: =D68+E68 -> 0
B69: =_xlfn.XLOOKUP(C69,'Detalhamento - G200'!B65:B312,'Detalhamento - G200'!A65:A312,0) -> 1003006001 | C69: PROJETOS, CQPS E AS BUILT | D69: =VLOOKUP(B69,'Detalhamento - G200'!A:G,5,) -> 0 | F69: =D69+E69 -> 0
B70: =_xlfn.XLOOKUP(C70,'Detalhamento - G200'!B66:B313,'Detalhamento - G200'!A66:A313,0) -> 1004001001 | C70: POÇO E ALVENARIAS PERIFÉRICAS - ELEVADOR | D70: =VLOOKUP(B70,'Detalhamento - G200'!A:G,5,) -> 0 | F70: =D70+E70 -> 0
B71: =_xlfn.XLOOKUP(C71,'Detalhamento - G200'!B67:B314,'Detalhamento - G200'!A67:A314,0) -> 1004001002 | C71: ELEVADOR MEZANINO | D71: =VLOOKUP(B71,'Detalhamento - G200'!A:G,5,) -> 0 | E71: -9000 | F71: =D71+E71 -> -9000 | G71: GANHO DE CONTRATAÇÃO THYSSENKRUPP
B72: =_xlfn.XLOOKUP(C72,'Detalhamento - G200'!B68:B315,'Detalhamento - G200'!A68:A315,0) -> 1004001003 | C72: AUMENTO DO LUX DA ÁREA EXTERNA | D72: =VLOOKUP(B72,'Detalhamento - G200'!A:G,5,) -> 0 | F72: =D72+E72 -> 0
B73: =_xlfn.XLOOKUP(C73,'Detalhamento - G200'!B69:B316,'Detalhamento - G200'!A69:A316,0) -> 1004001004 | C73: HVAC - COZINHA E REFEITÓRIO | D73: =VLOOKUP(B73,'Detalhamento - G200'!A:G,5,) -> 0 | F73: =D73+E73 -> 0
B74: =_xlfn.XLOOKUP(C74,'Detalhamento - G200'!B70:B317,'Detalhamento - G200'!A70:A317,0) -> 1004001005 | C74: CÂMARA FRIA - COZINHA INDUSTRIAL | D74: =VLOOKUP(B74,'Detalhamento - G200'!A:G,5,) -> 0 | F74: =D74+E74 -> 0
B75: =_xlfn.XLOOKUP(C75,'Detalhamento - G200'!B71:B318,'Detalhamento - G200'!A71:A318,0) -> 1004002001 | C75: INCLUSÃO DE JUNTAS EPÓXIS SEMIRRÍGIDAS EM 100% DAS JUNTAS SERRADAS | D75: =VLOOKUP(B75,'Detalhamento - G200'!A:G,5,) -> 0 | F75: =D75+E75 -> 0
B76: =_xlfn.XLOOKUP(C76,'Detalhamento - G200'!B72:B319,'Detalhamento - G200'!A72:A319,0) -> 1004002002 | C76: AUMENTO DA LARGURA DA RAMPA DE ACESSO DE EMPILHADEIRA DE 4,00 PARA 5,00 M | D76: =VLOOKUP(B76,'Detalhamento - G200'!A:G,5,) -> 0 | F76: =D76+E76 -> 0
B77: =_xlfn.XLOOKUP(C77,'Detalhamento - G200'!B73:B320,'Detalhamento - G200'!A73:A320,0) -> 1004002003 | C77: BOLLARDS DE PROTEÇÃO PARA QUADROS (2 POR QUADRO) | D77: =VLOOKUP(B77,'Detalhamento - G200'!A:G,5,) -> 0 | F77: =D77+E77 -> 0
B78: =_xlfn.XLOOKUP(C78,'Detalhamento - G200'!B74:B321,'Detalhamento - G200'!A74:A321,0) -> 1004002004 | C78: MARQUISE DE ENTRADA MELI - TESTEIRA ACM | D78: =VLOOKUP(B78,'Detalhamento - G200'!A:G,5,) -> 0 | F78: =D78+E78 -> 0
B79: =_xlfn.XLOOKUP(C79,'Detalhamento - G200'!B75:B322,'Detalhamento - G200'!A75:A322,0) -> 1004002005 | C79: MARQUISE DE ENTRADA MELI - FORRO ACM | D79: =VLOOKUP(B79,'Detalhamento - G200'!A:G,5,) -> 0 | F79: =D79+E79 -> 0
B80: =_xlfn.XLOOKUP(C80,'Detalhamento - G200'!B76:B323,'Detalhamento - G200'!A76:A323,0) -> 1004002006 | C80: PASSARELAS DE PEDESTRE/ÔNIBUS - TESTEIRA RAL 5022 | D80: =VLOOKUP(B80,'Detalhamento - G200'!A:G,5,) -> 0 | F80: =D80+E80 -> 0
B81: =_xlfn.XLOOKUP(C81,'Detalhamento - G200'!B77:B324,'Detalhamento - G200'!A77:A324,0) -> 1004002007 | C81: PASSARELAS DE PEDESTRE/ÔNIBUS - CALHA | D81: =VLOOKUP(B81,'Detalhamento - G200'!A:G,5,) -> 0 | F81: =D81+E81 -> 0
B82: =_xlfn.XLOOKUP(C82,'Detalhamento - G200'!B78:B325,'Detalhamento - G200'!A78:A325,0) -> 1004002008 | C82: PASSARELAS DE PEDESTRE/ÔNIBUS - SISTEMA DE DRENAGEM | D82: =VLOOKUP(B82,'Detalhamento - G200'!A:G,5,) -> 0 | F82: =D82+E82 -> 0
B83: =_xlfn.XLOOKUP(C83,'Detalhamento - G200'!B79:B326,'Detalhamento - G200'!A79:A326,0) -> 1004002009 | C83: INCLUSÃO DE EXAUSTÃO E INSUFLAMENTO PARA ÁREAS DE UTENSÍLIOS | D83: =VLOOKUP(B83,'Detalhamento - G200'!A:G,5,) -> 0 | F83: =D83+E83 -> 0
... B88: =_xlfn.XLOOKUP(C88,'Detalhamento - G200'!B84:B331,'Detalhamento - G200'!A84:A331,0) -> 1005001003 | C88: OM 03 - REGULARIZAÇÃO DO LICENCIAMENTO AMBIENTAL | D88: =VLOOKUP(B88,'Detalhamento - G200'!A:G,5,) -> 0 | F88: =D88+E88 -> 0
B89: =_xlfn.XLOOKUP(C89,'Detalhamento - G200'!B82:B329,'Detalhamento - G200'!A82:A329,0) -> 2001001001 | C89: BASE DE OPERACIONAL | D89: =VLOOKUP(B89,'Detalhamento - G200'!A:G,5,) -> 0 | F89: =D89+E89 -> 0
B90: =_xlfn.XLOOKUP(C90,'Detalhamento - G200'!B83:B330,'Detalhamento - G200'!A83:A330,0) -> 2001001002 | C90: IMPLANTAÇÃO DE CANTEIRO - ELETRICA | D90: =VLOOKUP(B90,'Detalhamento - G200'!A:G,5,) -> 0 | E90: 0 | F90: =D90+E90 -> 0
B91: =_xlfn.XLOOKUP(C91,'Detalhamento - G200'!B84:B331,'Detalhamento - G200'!A84:A331,0) -> 2001001003 | C91: GERADOR BACK-UP | D91: =VLOOKUP(B91,'Detalhamento - G200'!A:G,5,) -> 0 | F91: =D91+E91 -> 0
B92: =_xlfn.XLOOKUP(C92,'Detalhamento - G200'!B85:B332,'Detalhamento - G200'!A85:A332,0) -> 2001001004 | C92: LOCAÇÃO DE CONTAINER | D92: =VLOOKUP(B92,'Detalhamento - G200'!A:G,5,) -> 0 | F92: =D92+E92 -> 0
B93: =_xlfn.XLOOKUP(C93,'Detalhamento - G200'!B86:B333,'Detalhamento - G200'!A86:A333,0) -> 2001001005 | C93: IMPLANTAÇÃO DE CANTEIRO - HIDRÁULICA | D93: =VLOOKUP(B93,'Detalhamento - G200'!A:G,5,) -> 0 | F93: =D93+E93 -> 0
B94: =_xlfn.XLOOKUP(C94,'Detalhamento - G200'!B87:B334,'Detalhamento - G200'!A87:A334,0) -> 2001001006 | C94: IMPLANTAÇÃO DE CANTEIRO - CIVIL | D94: =VLOOKUP(B94,'Detalhamento - G200'!A:G,5,) -> 0 | F94: =D94+E94 -> 0
B95: =_xlfn.XLOOKUP(C95,'Detalhamento - G200'!B88:B335,'Detalhamento - G200'!A88:A335,0) -> 2001001007 | C95: LOCAÇÃO DE TOLDO | D95: =VLOOKUP(B95,'Detalhamento - G200'!A:G,5,) -> 0 | F95: =D95+E95 -> 0
B96: =_xlfn.XLOOKUP(C96,'Detalhamento - G200'!B89:B336,'Detalhamento - G200'!A89:A336,0) -> 2001001008 | C96: MOBILIARIO | D96: =VLOOKUP(B96,'Detalhamento - G200'!A:G,5,) -> 0 | F96: =D96+E96 -> 0
B97: =_xlfn.XLOOKUP(C97,'Detalhamento - G200'!B90:B337,'Detalhamento - G200'!A90:A337,0) -> 2001001009 | C97: LAVA RODAS | D97: =VLOOKUP(B97,'Detalhamento - G200'!A:G,5,) -> 0 | F97: =D97+E97 -> 0
B98: =_xlfn.XLOOKUP(C98,'Detalhamento - G200'!B91:B338,'Detalhamento - G200'!A91:A338,0) -> 2001001010 | C98: MANUTENÇÃO DE CANTEIRO | D98: =VLOOKUP(B98,'Detalhamento - G200'!A:G,5,) -> 0 | F98: =D98+E98 -> 0
B99: =_xlfn.XLOOKUP(C99,'Detalhamento - G200'!B92:B339,'Detalhamento - G200'!A92:A339,0) -> 2001002001 | C99: SEGURANÇA PATRIMONIAL - VIGILÂNCIA | D99: =VLOOKUP(B99,'Detalhamento - G200'!A:G,5,) -> 0 | F99: =D99+E99 -> 0
B100: =_xlfn.XLOOKUP(C100,'Detalhamento - G200'!B93:B340,'Detalhamento - G200'!A93:A340,0) -> 2001002002 | C100: MONITORAMENTO TIME LAPSE | D100: =VLOOKUP(B100,'Detalhamento - G200'!A:G,5,) -> 0 | F100: =D100+E100 -> 0
B101: =_xlfn.XLOOKUP(C101,'Detalhamento - G200'!B94:B341,'Detalhamento - G200'!A94:A341,0) -> 2001002003 | C101: CÂMERA DE MONITORAMENTO | D101: =VLOOKUP(B101,'Detalhamento - G200'!A:G,5,) -> 0 | F101: =D101+E101 -> 0
B102: =_xlfn.XLOOKUP(C102,'Detalhamento - G200'!B95:B342,'Detalhamento - G200'!A95:A342,0) -> 2001003001 | C102: TRANSPORTE SSA-LSF | D102: =VLOOKUP(B102,'Detalhamento - G200'!A:G,5,) -> 0 | F102: =D102+E102 -> 0
... B105: =_xlfn.XLOOKUP(C105,'Detalhamento - G200'!B98:B345,'Detalhamento - G200'!A98:A345,0) -> 2001004001 | C105: LOCAÇÃO DE MUNCK | D105: =VLOOKUP(B105,'Detalhamento - G200'!A:G,5,) -> 0 | F105: =D105+E105 -> 0
B106: =_xlfn.XLOOKUP(C106,'Detalhamento - G200'!B99:B346,'Detalhamento - G200'!A99:A346,0) -> 2001004002 | C106: LOCAÇÃO DE BOBCAT | D106: =VLOOKUP(B106,'Detalhamento - G200'!A:G,5,) -> 0 | E106: 213.5 | F106: =D106+E106 -> 213.5 | G106: FATURAMENTO DIRETO A SER DEBITADO DA PRÓXIMA MEDIÇÃO DA MAGALHÃES
B107: =_xlfn.XLOOKUP(C107,'Detalhamento - G200'!B100:B347,'Detalhamento - G200'!A100:A347,0) -> 2001004003 | C107: LOCAÇÃO DE CAMINHÃO PIPA | D107: =VLOOKUP(B107,'Detalhamento - G200'!A:G,5,) -> 0 | F107: =D107+E107 -> 0
B108: =_xlfn.XLOOKUP(C108,'Detalhamento - G200'!B101:B348,'Detalhamento - G200'!A101:A348,0) -> 2001004004 | C108: DIESEL | D108: =VLOOKUP(B108,'Detalhamento - G200'!A:G,5,) -> 0 | F108: =D108+E108 -> 0
...

Sheet Notas fiscais - G200
H2: OBRA | I2: G200
H3: INÍCIO
H4: TÉRMINO
H5: RESPONSÁVEL | I5: SÉRGIO COSTA
B6: OBS.: Os romaneios 01 e 07 serão desconsiderados | M6: =SUBTOTAL(9,M9:M4953) -> 1.1349072e+08 | N6: =SUBTOTAL(9,N9:N4953) -> 1568704 | O6: =SUBTOTAL(9,O9:O4953) -> 212666.26 | P6: =SUBTOTAL(9,P9:P4953) -> 6528698.4 | Q6: =SUBTOTAL(9,Q9:Q4953) -> 0 | R6: =SUBTOTAL(9,R9:R4953) -> 25.2 | S6: =SUBTOTAL(9,S9:S4953) -> 1.0518062e+08 | T6: =SUBTOTAL(9,T9:T4953) -> 1.0674933e+08
B8: Romaneio | C8: Aprovação | D8: Apropriação | E8: Descrição da EAP | F8: Título | G8: Nota fiscal | H8: Tipo de nota (Material I Serviço) | I8: Data de emissão | J8: Data de vencimento | K8: CNPJ | L8: Credor | M8: Valor bruto | N8: Imposto | O8: Retenção | P8: Desconto de adiantamento | Q8: Juros e multas | R8: Devolução/Desconto | S8: Valor líquido | T8: Líquido + imposto | U8: Data efetiva de pagamento | V8: Contrato I Pedido apropriado | W8: Contrato - FD
B9: 0002 | D9: 2003001001 | E9: =_xlfn.XLOOKUP(D9,'Detalhamento - G200'!A:A,'Detalhamento - G200'!B:B,0) -> FEE | F9: 90185/1 | G9: Recibo 01 - Adiantamento | H9: ADIANTAMENTO | SINAL | I9: 46091 | J9: 46094 | K9: 37.292.522/0001-14 | L9: QPC ENGENHARIA LTDA | M9: 5000000 | N9: 0 | O9: 0 | P9: 0 | Q9: 0 | S9: =M9-SUM(N9:Q9) -> 5000000 | T9: =N9+S9 -> 5000000 | V9: CLSF/200-3-000 | W9: CLSF/200-3-000
B10: 0003 | D10: 2003001001 | E10: =_xlfn.XLOOKUP(D10,'Detalhamento - G200'!A:A,'Detalhamento - G200'!B:B,0) -> FEE | F10: 90328 | G10: Recibo 02 - Adiantamento | H10: ADIANTAMENTO | SINAL | I10: 46093 | J10: 46094 | K10: 37.292.522/0001-14 | L10: QPC ENGENHARIA LTDA | M10: 4285792 | N10: 0 | O10: 0 | P10: 0 | Q10: 0 | S10: =M10-SUM(N10:Q10) -> 4285792 | T10: =N10+S10 -> 4285792 | V10: CLSF/200-3-000 | W10: CLSF/200-3-000
B11: 0003 | D11: 2002001001 | E11: =_xlfn.XLOOKUP(D11,'Detalhamento - G200'!A:A,'Detalhamento - G200'!B:B,0) -> SALÁRIOS, DISSÍDIO/REAJUSTE E AJUDA DE CUSTO | F11: 90328 | G11: Recibo 02 - Adiantamento | H11: ADIANTAMENTO | SINAL | I11: 46093 | J11: 46095 | K11: 37.292.522/0001-14 | L11: QPC ENGENHARIA LTDA | M11: 2427480.4 | N11: 0 | O11: 0 | P11: 0 | Q11: 0 | S11: =M11-SUM(N11:Q11) -> 2427480.4 | T11: =N11+S11 -> 2427480.4 | V11: CLSF/200-3-000 | W11: CLSF/200-3-000
B12: 0005 | D12: 1001003001 | E12: =_xlfn.XLOOKUP(D12,'Detalhamento - G200'!A:A,'Detalhamento - G200'!B:B,0) -> FUNDAÇÃO GALPÃO | F12: 90331/1 | G12: 474 | H12: NF SERVIÇO | I12: 46092 | J12: 46113 | K12: 61.597.415/0001-89 | L12: VENDRAMINI ENGENHARIA LTDA | M12: 550000 | N12: 33825 | O12: 0 | P12: 0 | Q12: 0 | S12: =M12-SUM(N12:Q12) -> 516175 | T12: =N12+S12 -> 550000 | V12: CLSF/200-3-010 | W12: CLSF/200-3-010
B13: 0005 | D13: 1001001001 | E13: =_xlfn.XLOOKUP(D13,'Detalhamento - G200'!A:A,'Detalhamento - G200'!B:B,0) -> PROJETOS | F13: 90332 | G13: 830 | H13: NF SERVIÇO | I13: 46092 | J13: 46122 | K13: 04.692.016/0001-63 | L13: DO VAL ENGENHARIA CONSULTORIA SOCIEDADE SIMPLES | M13: 43500 | N13: 2675.25 | O13: 0 | P13: 0 | Q13: 0 | S13: =M13-SUM(N13:Q13) -> 40824.75 | T13: =N13+S13 -> 43500 | V13: CLSF/200-3-011 | W13: CLSF/200-3-011
B14: 0005 | D14: 1001001001 | E14: =_xlfn.XLOOKUP(D14,'Detalhamento - G200'!A:A,'Detalhamento - G200'!B:B,0) -> PROJETOS | F14: 90333 | G14: 2145 | H14: NF SERVIÇO | I14: 46092 | J14: 46122 | K14: 65.978.504/0001-26 | L14: NUCLEORA PLANEJAMENTO, ASSESSORIA E DESENVOLVIMENTO COMERCIAL LTDA | M14: 13500 | N14: 830.25 | O14: 0 | P14: 0 | Q14: 0 | S14: =M14-SUM(N14:Q14) -> 12669.75 | T14: =N14+S14 -> 13500 | V14: CLSF/200-3-007 | W14: CLSF/200-3-007
B15: 0005 | D15: 1001001001 | E15: =_xlfn.XLOOKUP(D15,'Detalhamento - G200'!A:A,'Detalhamento - G200'!B:B,0) -> PROJETOS | F15: 90335 | G15: 653 | H15: NF SERVIÇO | I15: 46093 | J15: 46113 | K15: 24.955.005/0001-36 | L15: ARQUITETURA JAPI PROJETOS E CONSULTORIA LTDA | M15: 113731.45 | N15: 6994.47 | O15: 0 | P15: 0 | Q15: 0 | S15: =M15-SUM(N15:Q15) -> 106736.98 | T15: =N15+S15 -> 113731.45 | V15: CLSF/200-3-002 | W15: CLSF/200-3-002
B16: 0005 | D16: 1001001001 | E16: =_xlfn.XLOOKUP(D16,'Detalhamento - G200'!A:A,'Detalhamento - G200'!B:B,0) -> PROJETOS | F16: 90337 | G16: 1322 | H16: NF SERVIÇO | I16: 46093 | J16: 46122 | K16: 28.254.497/0001-93 | L16: DPE ARQUITETURA E ENGENHARIA S/S | M16: 90000 | N16: 5535 | O16: 0 | P16: 0 | Q16: 0 | S16: =M16-SUM(N16:Q16) -> 84465 | T16: =N16+S16 -> 90000 | V16: CLSF/200-3-001 | W16: CLSF/200-3-001
B17: 0005 | D17: 1001001001 | E17: =_xlfn.XLOOKUP(D17,'Detalhamento - G200'!A:A,'Detalhamento - G200'!B:B,0) -> PROJETOS | F17: 90338 | G17: 8932 | H17: NF SERVIÇO | I17: 46093 | J17: 46122 | K17: 71.729.438/0001-53 | L17: LPE ENGENHARIA E CONSULTORIA LTDA | M17: 73200 | N17: 4501.8 | O17: 0 | P17: 0 | Q17: 0 | S17: =M17-SUM(N17:Q17) -> 68698.2 | T17: =N17+S17 -> 73200 | V17: CLSF/200-3-004 | W17: CLSF/200-3-004
B18: 0005 | D18: 1001001001 | E18: =_xlfn.XLOOKUP(D18,'Detalhamento - G200'!A:A,'Detalhamento - G200'!B:B,0) -> PROJETOS | F18: 90348 | G18: 20262415 | H18: NF SERVIÇO | I18: 46093 | J18: 46122 | K18: 40.610.677/0001-66 | L18: GEOTECHNIQUE CONSULTORIA E ENGENHARIA LTDA | M18: 75000 | N18: 4612.5 | O18: 0 | P18: 0 | Q18: 0 | S18: =M18-SUM(N18:Q18) -> 70387.5 | T18: =N18+S18 -> 75000 | V18: CLSF/200-3-012 | W18: CLSF/200-3-012
B19: 0005 | D19: 1001001001 | E19: =_xlfn.XLOOKUP(D19,'Detalhamento - G200'!A:A,'Detalhamento - G200'!B:B,0) -> PROJETOS | F19: 90381 | G19: 1309 | H19: NF SERVIÇO | I19: 46094 | J19: 46122 | K19: 28.649.696/0001-09 | L19: REV1 PROJETOS INTEGRADOS LTDA | M19: 5920.95 | N19: 0 | O19: 0 | P19: 0 | Q19: 0 | S19: =M19-SUM(N19:Q19) -> 5920.95 | T19: =N19+S19 -> 5920.95 | V19: CLSF/200-3-006 | W19: CLSF/200-3-006
B20: 0006 | D20: 1001002003 | E20: =_xlfn.XLOOKUP(D20,'Detalhamento - G200'!A:A,'Detalhamento - G200'!B:B,0) -> MOVIMENTAÇÃO DE TERRA | F20: 89426 | G20: Recibo - Adiantamento | H20: ADIANTAMENTO | SINAL | I20: 46083 | J20: 46101 | K20: 05.009.846/0001-06 | L20: MAGALHAES JUNIOR LOCACAO E SERVICOS LTDA | M20: 2992666.9 | N20: 0 | O20: 0 | P20: 0 | Q20: 0 | S20: =M20-SUM(N20:Q20) -> 2992666.9 | T20: =N20+S20 -> 2992666.9 | V20: CLSF/200-3-015 | W20: CLSF/200-3-015
B21: 0006 | D21: 1001002007 | E21: =_xlfn.XLOOKUP(D21,'Detalhamento - G200'!A:A,'Detalhamento - G200'!B:B,0) -> ESCAVAÇÃO NO TARDOZ | F21: 89426 | G21: Recibo - Adiantamento | H21: ADIANTAMENTO | SINAL | I21: 46083 | J21: 46101 | K21: 05.009.846/0001-06 | L21: MAGALHAES JUNIOR LOCACAO E SERVICOS LTDA | M21: 136068.71 | N21: 0 | O21: 0 | P21: 0 | Q21: 0 | S21: =M21-SUM(N21:Q21) -> 136068.71 | T21: =N21+S21 -> 136068.71 | V21: CLSF/200-3-015 | W21: CLSF/200-3-015
B22: 0008 | D22: 1001001001 | E22: =_xlfn.XLOOKUP(D22,'Detalhamento - G200'!A:A,'Detalhamento - G200'!B:B,0) -> PROJETOS | F22: 91165 | G22: 31 | H22: NF SERVIÇO | I22: 46105 | J22: 46117 | K22: 47.872.355/0001-34 | L22: HIDRO LOGICA CONSULTORIA E TREINAMENTO LTDA | M22: 7000 | N22: 0 | O22: 0 | P22: 0 | Q22: 0 | S22: =M22-SUM(N22:Q22) -> 7000 | T22: =N22+S22 -> 7000 | V22: PPC/26418 | W22: SEM CONTRATO
B23: 0008 | D23: 2001001006 | E23: =_xlfn.XLOOKUP(D23,'Detalhamento - G200'!A:A,'Detalhamento - G200'!B:B,0) -> IMPLANTAÇÃO DE CANTEIRO - CIVIL | F23: 91079 | G23: 6653 | H23: NF MATERIAL | I23: 46104 | J23: 46134 | K23: 14.205.923/0001-94 | L23: AJS SOUZA SERVIÇOS GRAFICOS | M23: 11921 | N23: 0 | O23: 0 | P23: 0 | Q23: 0 | S23: =M23-SUM(N23:Q23) -> 11921 | T23: =N23+S23 -> 11921 | V23: PPC/26511 | W23: SEM CONTRATO
B24: 0008 | D24: 1001001001 | E24: =_xlfn.XLOOKUP(D24,'Detalhamento - G200'!A:A,'Detalhamento - G200'!B:B,0) -> PROJETOS | F24: 91268 | G24: 47 | H24: NF MATERIAL | I24: 46106 | J24: 46118 | K24: 32.617.659/0001 - 88 | L24: KAIZ ENGENHARIA LTDA | M24: 9787.5 | N24: 0 | O24: 0 | P24: 0 | Q24: 0 | S24: =M24-SUM(N24:Q24) -> 9787.5 | T24: =N24+S24 -> 9787.5 | V24: CLSF/200-3-009 | W24: CLSF/200-3-009
B25: 0008 | D25: 2002001001 | E25: =_xlfn.XLOOKUP(D25,'Detalhamento - G200'!A:A,'Detalhamento - G200'!B:B,0) -> SALÁRIOS, DISSÍDIO/REAJUSTE E AJUDA DE CUSTO | F25: 91371 | G25: 175 | H25: NF SERVIÇO | I25: 46107 | J25: 46117 | K25: 37.292.522/0001-14 | L25: QPC ENGENHARIA LTDA | M25: 1636689.2 | N25: 144846.99 | O25: 0 | P25: 301288.23 | Q25: 0 | S25: =M25-SUM(N25:Q25) -> 1190553.9 | T25: =N25+S25 -> 1335400.9 | V25: CLSF/200-3-000 | W25: CLSF/200-3-000
B26: 0008 | D26: 2003001001 | E26: =_xlfn.XLOOKUP(D26,'Detalhamento - G200'!A:A,'Detalhamento - G200'!B:B,0) -> FEE | F26: 91371 | G26: 175 | H26: NF SERVIÇO | I26: 46107 | J26: 46118 | K26: 37.292.522/0001-14 | L26: QPC ENGENHARIA LTDA | M26: 344282.89 | N26: 30469.036 | O26: 0 | P26: 63376.959 | Q26: 0 | S26: =M26-SUM(N26:Q26) -> 250436.9 | T26: =N26+S26 -> 280905.93 | V26: CLSF/200-3-000 | W26: CLSF/200-3-000
B27: 0008 | D27: 2001025001 | E27: =_xlfn.XLOOKUP(D27,'Detalhamento - G200'!A:A,'Detalhamento - G200'!B:B,0) -> DESPESAS INDIRETAS DE OBRA, CANTEIRO, INSTALAÇÕES PROVISÓRIAS - FATURAMENTO QPC | F27: 91371 | G27: 175 | H27: NF SERVIÇO | I27: 46107 | J27: 46119 | K27: 37.292.522/0001-14 | L27: QPC ENGENHARIA LTDA | M27: 472563.43 | N27: 41821.864 | O27: 0 | P27: 86991.35 | Q27: 0 | S27: =M27-SUM(N27:Q27) -> 343750.22 | T27: =N27+S27 -> 385572.08 | V27: CLSF/200-3-000 | W27: CLSF/200-3-000
B28: 0008 | D28: 2001025002 | E28: =_xlfn.XLOOKUP(D28,'Detalhamento - G200'!A:A,'Detalhamento - G200'!B:B,0) -> DESPESAS INDIRETAS DE OBRA - DESEMBOLSO CANTEIRO DE OBRAS | F28: 91371 | G28: 175 | H28: NF SERVIÇO | I28: 46107 | J28: 46120 | K28: 37.292.522/0001-14 | L28: QPC ENGENHARIA LTDA | M28: 212653.54 | N28: 18819.838 | O28: 0 | P28: 39146.107 | Q28: 0 | S28: =M28-SUM(N28:Q28) -> 154687.59 | T28: =N28+S28 -> 173507.43 | V28: CLSF/200-3-000 | W28: CLSF/200-3-000
B29: 0008 | D29: 2003001001 | E29: =_xlfn.XLOOKUP(D29,'Detalhamento - G200'!A:A,'Detalhamento - G200'!B:B,0) -> FEE | F29: 91286 | G29: 168 | H29: NF SERVIÇO | I29: 46106 | J29: 46117 | K29: 37.292.522/0001-14 | L29: QPC ENGENHARIA LTDA | M29: 77368.62 | N29: 3868.43 | O29: 3868.43 | P29: 17672.16 | Q29: 0 | S29: =M29-SUM(N29:Q29) -> 51959.6 | T29: =N29+S29 -> 55828.03 | V29: CLSF/200-3-000 | W29: CLSF/200-3-000
B30: 0008 | D30: 2002001001 | E30: =_xlfn.XLOOKUP(D30,'Detalhamento - G200'!A:A,'Detalhamento - G200'!B:B,0) -> SALÁRIOS, DISSÍDIO/REAJUSTE E AJUDA DE CUSTO | F30: 91289 | G30: 169 | H30: NF SERVIÇO | I30: 46106 | J30: 46117 | K30: 37.292.522/0001-14 | L30: QPC ENGENHARIA LTDA | M30: 975618.35 | N30: 86342.218 | O30: 0 | P30: 161335.85 | Q30: 0 | S30: =M30-SUM(N30:Q30) -> 727940.28 | T30: =N30+S30 -> 814282.5 | V30: CLSF/200-3-000 | W30: CLSF/200-3-000
B31: 0008 | D31: 2003001001 | E31: =_xlfn.XLOOKUP(D31,'Detalhamento - G200'!A:A,'Detalhamento - G200'!B:B,0) -> FEE | F31: 91289 | G31: 169 | H31: NF SERVIÇO | I31: 46106 | J31: 46117 | K31: 37.292.522/0001-14 | L31: QPC ENGENHARIA LTDA | M31: 180053.71 | N31: 15934.752 | O31: 0 | P31: 29775.085 | Q31: 0 | S31: =M31-SUM(N31:Q31) -> 134343.87 | T31: =N31+S31 -> 150278.62 | V31: CLSF/200-3-000 | W31: CLSF/200-3-000
B32: 0008 | D32: 2003001001 | E32: =_xlfn.XLOOKUP(D32,'Detalhamento - G200'!A:A,'Detalhamento - G200'!B:B,0) -> FEE | F32: 91297 | G32: 170 | H32: NF SERVIÇO | I32: 46106 | J32: 46108 | K32: 37.292.522/0001-14 | L32: QPC ENGENHARIA LTDA | M32: 259763.55 | N32: 12988.18 | O32: 12988.18 | P32: 59333.91 | Q32: 0 | S32: =M32-SUM(N32:Q32) -> 174453.28 | T32: =N32+S32 -> 187441.46 | V32: CLSF/200-3-000 | W32: CLSF/200-3-000
B33: 0008 | D33: 2002001001 | E33: =_xlfn.XLOOKUP(D33,'Detalhamento - G200'!A:A,'Detalhamento - G200'!B:B,0) -> SALÁRIOS, DISSÍDIO/REAJUSTE E AJUDA DE CUSTO | F33: 91370 | G33: 174 | H33: NF SERVIÇO | I33: 46106 | J33: 46117 | K33: 37.292.522/0001-14 | L33: QPC ENGENHARIA LTDA | M33: 672262.51 | N33: 33613.125 | O33: 0 | P33: 80538.023 | Q33: 0 | S33: =M33-SUM(N33:Q33) -> 558111.36 | T33: =N33+S33 -> 591724.48 | V33: CLSF/200-3-000 | W33: CLSF/200-3-000
... B37: 0008 | D37: 1001001002 | E37: =_xlfn.XLOOKUP(D37,'Detalhamento - G200'!A:A,'Detalhamento - G200'!B:B,0) -> ENSAIOS E CONSULTORIAS | F37: 91326 | G37: 2026376 | H37: NF SERVIÇO | I37: 46106 | J37: 46117 | K37: 52.150.027/0001-64 | L37: LCL GEOTECNIA E SONDAGEM LTDA | M37: 36576.34 | N37: 1828.82 | O37: 1828.82 | P37: 0 | Q37: 0 | S37: =M37-SUM(N37:Q37) -> 32918.7 | T37: =N37+S37 -> 34747.52 | V37: CLSF/200-3-014 | W37: CLSF/200-3-014
B38: 0008 | D38: 1001002003 | E38: =_xlfn.XLOOKUP(D38,'Detalhamento - G200'!A:A,'Detalhamento - G200'!B:B,0) -> MOVIMENTAÇÃO DE TERRA | F38: 91535/1 | G38: 1441 | H38: NF SERVIÇO | I38: 46106 | J38: 46117 | K38: 54.290.200/0001-55 | L38: TERRAM ENGENHARIA DE INFRAESTRURA S/A | M38: 2176885.7 | N38: 144762.89 | O38: 0 | P38: 0 | Q38: 0 | S38: =M38-SUM(N38:Q38) -> 2032122.8 | T38: =N38+S38 -> 2176885.7 | V38: PPC/26680 | W38: SEM CONTRATO
B39: 0008 | D39: 1001002003 | E39: =_xlfn.XLOOKUP(D39,'Detalhamento - G200'!A:A,'Detalhamento - G200'!B:B,0) -> MOVIMENTAÇÃO DE TERRA | F39: 91399 | G39: 20261156 | H39: NF SERVIÇO | I39: 46106 | J39: 46118 | K39: 05.009.846/0001-06 | L39: MAGALHAES JUNIOR LOCACAO E SERVICOS LTDA | M39: 1434897.9 | N39: 95420.72 | O39: 71744.9 | P39: 286979.59 | Q39: 0 | S39: =M39-SUM(N39:Q39) -> 980752.74 | T39: =N39+S39 -> 1076173.5 | V39: CLSF/200-3-015 | W39: CLSF/200-3-015
B40: 0011 | D40: 2001002002 | E40: =_xlfn.XLOOKUP(D40,'Detalhamento - G200'!A:A,'Detalhamento - G200'!B:B,0) -> MONITORAMENTO TIME LAPSE | F40: 91931 | G40: 2995 | H40: NF SERVIÇO | I40: 46114 | J40: 46147 | K40: 34.846.377/0001-88 | L40: LEONARDO SANTOS GONCALVES PRODUCAO E SOLUCOES EM VIDEOS | M40: 2300 | N40: 0 | O40: 0 | P40: 0 | Q40: 0 | S40: =M40-SUM(N40:Q40) -> 2300 | T40: =N40+S40 -> 2300 | V40: CLSF/200-3-025 | W40: CLSF/200-3-025
B41: 0011 | D41: 1004001002 | E41: =_xlfn.XLOOKUP(D41,'Detalhamento - G200'!A:A,'Detalhamento - G200'!B:B,0) -> ELEVADOR MEZANINO | F41: 91938 | G41: Recibo - Adiantamento 1 | H41: ADIANTAMENTO | SINAL | I41: 46112 | J41: 46132 | K41: 90.347.840/0001-18 | L41: THYSSENKRUPP ELEVADORES AS | M41: 58140 | N41: 0 | O41: 0 | P41: 0 | Q41: 0 | S41: =M41-SUM(N41:Q41) -> 58140 | T41: =N41+S41 -> 58140 | V41: CLSF/200-3-036 | W41: CLSF/200-3-036
B42: 0011 | D42: 2001001007 | E42: =_xlfn.XLOOKUP(D42,'Detalhamento - G200'!A:A,'Detalhamento - G200'!B:B,0) -> LOCAÇÃO DE TOLDO | F42: 92059 | G42: 728 | H42: NF MATERIAL | I42: 46113 | J42: 46142 | K42: 13.299.597/0001-69 | L42: SOLUCAO TOLDOS EIRELI | M42: 32280 | N42: 0 | O42: 0 | P42: 0 | Q42: 0 | S42: =M42-SUM(N42:Q42) -> 32280 | T42: =N42+S42 -> 32280 | V42: PPC/25660 | W42: SEM CONTRATO
B43: 0011 | D43: 1001002003 | E43: =_xlfn.XLOOKUP(D43,'Detalhamento - G200'!A:A,'Detalhamento - G200'!B:B,0) -> MOVIMENTAÇÃO DE TERRA | F43: 92400 | G43: 4852 | H43: NF MATERIAL | I43: 46118 | J43: 46146 | K43: 05.493.638/0001-25 | L43: LIGUE COMERCIO DE GEOSSINTETICOS LTDA | M43: 3528.25 | N43: 0 | O43: 0 | P43: 0 | Q43: 0 | S43: =M43-SUM(N43:Q43) -> 3528.25 | T43: =N43+S43 -> 3528.25 | V43: PPC/27045 | W43: CLSF/200-3-039
B44: 0011 | D44: 1001002006 | E44: =_xlfn.XLOOKUP(D44,'Detalhamento - G200'!A:A,'Detalhamento - G200'!B:B,0) -> CONTENÇÕES | F44: 92400 | G44: 4852 | H44: NF MATERIAL | I44: 46118 | J44: 46146 | K44: 05.493.638/0001-25 | L44: LIGUE COMERCIO DE GEOSSINTETICOS LTDA | M44: 3570.95 | N44: 0 | O44: 0 | P44: 0 | Q44: 0 | S44: =M44-SUM(N44:Q44) -> 3570.95 | T44: =N44+S44 -> 3570.95 | V44: PPC/27045 | W44: CLSF/200-3-039
B45: 0011 | D45: 1001002006 | E45: =_xlfn.XLOOKUP(D45,'Detalhamento - G200'!A:A,'Detalhamento - G200'!B:B,0) -> CONTENÇÕES | F45: 92402 | G45: 3266 | H45: NF MATERIAL | I45: 46118 | J45: 46148 | K45: 07.130.889/0001-70 | L45: ADUANA COMERCIO DE GEOSSINTETICOS LTDA | M45: 4972 | N45: 0 | O45: 0 | P45: 0 | Q45: 0 | S45: =M45-SUM(N45:Q45) -> 4972 | T45: =N45+S45 -> 4972 | V45: PPC/26565 | W45: CLSF/200-3-039
B46: 0011 | D46: 1001002006 | E46: =_xlfn.XLOOKUP(D46,'Detalhamento - G200'!A:A,'Detalhamento - G200'!B:B,0) -> CONTENÇÕES | F46: 92407 | G46: 2445 | H46: NF MATERIAL | I46: 46119 | J46: 46149 | K46: 07.806.488/0001-98 | L46: ANTONIO CARDOSO MARTINS | M46: 16500 | N46: 0 | O46: 0 | P46: 0 | Q46: 0 | S46: =M46-SUM(N46:Q46) -> 16500 | T46: =N46+S46 -> 16500 | V46: PPC/26564 | W46: CLSF/200-3-039
B47: 0011 | D47: 1001002006 | E47: =_xlfn.XLOOKUP(D47,'Detalhamento - G200'!A:A,'Detalhamento - G200'!B:B,0) -> CONTENÇÕES | F47: 92409 | G47: 1947471 | H47: NF MATERIAL | I47: 46119 | J47: 46147 | K47: 10.921.911/0001-05 | L47: FORTLEV INDUSTRIA E COMERCIO DE PLASTICOS LTDA | M47: 10619 | N47: 0 | O47: 0 | P47: 0 | Q47: 0 | S47: =M47-SUM(N47:Q47) -> 10619 | T47: =N47+S47 -> 10619 | V47: PPC/26562 | W47: CLSF/200-3-039
B48: 0014 | D48: 2001001002 | E48: =_xlfn.XLOOKUP(D48,'Detalhamento - G200'!A:A,'Detalhamento - G200'!B:B,0) -> IMPLANTAÇÃO DE CANTEIRO - ELETRICA | F48: 92476 | G48: 285034 | H48: NF MATERIAL | I48: 46104 | J48: 46134 | K48: 12.341.222/0001-57 | L48: BAHIATECH MATERIAIS ELETRICOS LTDA | M48: 6611.3 | N48: 0 | O48: 0 | P48: 0 | Q48: 0 | R48: 25.2 | S48: =M48-SUM(N48:R48) -> 6586.1 | T48: =N48+S48 -> 6586.1 | V48: PPC/26618 | W48: SEM CONTRATO
B49: 0011 | D49: 2001001003 | E49: =_xlfn.XLOOKUP(D49,'Detalhamento - G200'!A:A,'Detalhamento - G200'!B:B,0) -> GERADOR BACK-UP | F49: 92477 | G49: 4807 | H49: NF MATERIAL | I49: 46121 | J49: 46147 | K49: 03.292.008/0001-67 | L49: GERACAO E ENERGIA SERVICOS E COMERCIO LTDA | M49: 4300 | N49: 0 | O49: 0 | P49: 0 | Q49: 0 | S49: =M49-SUM(N49:Q49) -> 4300 | T49: =N49+S49 -> 4300 | V49: PPC/26595 | W49: SEM CONTRATO
B50: 0009 | D50: 1001002003 | E50: =_xlfn.XLOOKUP(D50,'Detalhamento - G200'!A:A,'Detalhamento - G200'!B:B,0) -> MOVIMENTAÇÃO DE TERRA | F50: 92706 | G50: 1409 | H50: NF MATERIAL | I50: 45950 | J50: 46108 | K50: 54.290.200/0001-55 | L50: TERRAM ENGENHARIA DE INFRAESTRURA S/A | M50: 1867841.6 | N50: 124211.47 | O50: 0 | P50: 1743630.1 | Q50: 0 | S50: =M50-SUM(N50:Q50) -> 0 | T50: =N50+S50 -> 124211.47 | V50: PPC/27440 | W50: SEM CONTRATO
B51: 0009 | D51: 1001002003 | E51: =_xlfn.XLOOKUP(D51,'Detalhamento - G200'!A:A,'Detalhamento - G200'!B:B,0) -> MOVIMENTAÇÃO DE TERRA | F51: 92708 | G51: 1442 | H51: NF MATERIAL | I51: 46106 | J51: 46108 | K51: 54.290.200/0001-55 | L51: TERRAM ENGENHARIA DE INFRAESTRURA S/A | M51: 1183359.6 | N51: 78693.41 | O51: 0 | P51: 1104666.2 | Q51: 0 | S51: =M51-SUM(N51:Q51) -> 0 | T51: =N51+S51 -> 78693.41 | V51: PPC/27440 | W51: SEM CONTRATO
B52: 0010 | D52: 1001002003 | E52: =_xlfn.XLOOKUP(D52,'Detalhamento - G200'!A:A,'Detalhamento - G200'!B:B,0) -> MOVIMENTAÇÃO DE TERRA | F52: 91903 | G52: 254319 | H52: NF MATERIAL | I52: 46113 | J52: 46129 | K52: 13.529.482/0001-13 | L52: TRANSPORTADORA DE DIESEL CAVALO MARINHO LTDA | M52: 15575 | N52: 0 | O52: 0 | P52: 0 | Q52: 0 | S52: =M52-SUM(N52:Q52) -> 15575 | T52: =N52+S52 -> 15575 | V52: PPC/26926 | W52: CLSF/200-3-015
B53: 0010 | D53: 1001002003 | E53: =_xlfn.XLOOKUP(D53,'Detalhamento - G200'!A:A,'Detalhamento - G200'!B:B,0) -> MOVIMENTAÇÃO DE TERRA | F53: 91905 | G53: 254321 | H53: NF MATERIAL | I53: 46113 | J53: 46129 | K53: 13.529.482/0001-13 | L53: TRANSPORTADORA DE DIESEL CAVALO MARINHO LTDA | M53: 42224 | N53: 0 | O53: 0 | P53: 0 | Q53: 0 | S53: =M53-SUM(N53:Q53) -> 42224 | T53: =N53+S53 -> 42224 | V53: PPC/26926 | W53: CLSF/200-3-015
B54: 0010 | D54: 1001002003 | E54: =_xlfn.XLOOKUP(D54,'Detalhamento - G200'!A:A,'Detalhamento - G200'!B:B,0) -> MOVIMENTAÇÃO DE TERRA | F54: 91908 | G54: 254322 | H54: NF MATERIAL | I54: 46113 | J54: 46129 | K54: 13.529.482/0001-13 | L54: TRANSPORTADORA DE DIESEL CAVALO MARINHO LTDA | M54: 40745.6 | N54: 0 | O54: 0 | P54: 0 | Q54: 0 | S54: =M54-SUM(N54:Q54) -> 40745.6 | T54: =N54+S54 -> 40745.6 | V54: PPC/26926 | W54: CLSF/200-3-015
B55: 0010 | D55: 1001002003 | E55: =_xlfn.XLOOKUP(D55,'Detalhamento - G200'!A:A,'Detalhamento - G200'!B:B,0) -> MOVIMENTAÇÃO DE TERRA | F55: 94335 | G55: 345943 | H55: ADIANTAMENTO | SINAL | I55: 46114 | J55: 46135 | K55: 14.689.756/0001-02 | L55: PEDREIRAS CARANGI LTDA | M55: 71780 | N55: 0 | O55: 0 | P55: 0 | Q55: 0 | S55: =M55-SUM(N55:Q55) -> 71780 | T55: =N55+S55 -> 71780 | V55: PPC/26929 | W55: CLSF/200-3-039
B56: 0010 | D56: 1001002003 | E56: =_xlfn.XLOOKUP(D56,'Detalhamento - G200'!A:A,'Detalhamento - G200'!B:B,0) -> MOVIMENTAÇÃO DE TERRA | F56: 94335 | G56: 345943 | H56: ADIANTAMENTO | SINAL | I56: 46114 | J56: 46136 | K56: 14.689.756/0001-02 | L56: PEDREIRAS CARANGI LTDA | M56: 13580 | N56: 0 | O56: 0 | P56: 0 | Q56: 0 | S56: =M56-SUM(N56:Q56) -> 13580 | T56: =N56+S56 -> 13580 | V56: PPC/26929 | W56: CLSF/200-3-039
B57: 0010 | D57: 1001002006 | E57: =_xlfn.XLOOKUP(D57,'Detalhamento - G200'!A:A,'Detalhamento - G200'!B:B,0) -> CONTENÇÕES | F57: 94335 | G57: 345943 | H57: ADIANTAMENTO | SINAL | I57: 46114 | J57: 46137 | K57: 14.689.756/0001-02 | L57: PEDREIRAS CARANGI LTDA | M57: 7920 | N57: 0 | O57: 0 | P57: 0 | Q57: 0 | S57: =M57-SUM(N57:Q57) -> 7920 | T57: =N57+S57 -> 7920 | V57: PPC/26929 | W57: CLSF/200-3-039
B58: 0010 | D58: 2001001002 | E58: =_xlfn.XLOOKUP(D58,'Detalhamento - G200'!A:A,'Detalhamento - G200'!B:B,0) -> IMPLANTAÇÃO DE CANTEIRO - ELETRICA | F58: 92009 | G58: 15180 | H58: NF MATERIAL | I58: 46111 | J58: 46141 | K58: 34.129.420/0001-94 | L58: CABOS & LAMPADAS | M58: 183.06 | N58: 0 | O58: 0 | P58: 0 | Q58: 0 | S58: =M58-SUM(N58:Q58) -> 183.06 | T58: =N58+S58 -> 183.06 | V58: PPC/26877 | W58: SEM CONTRATO
B59: 0010 | D59: 2001001010 | E59: =_xlfn.XLOOKUP(D59,'Detalhamento - G200'!A:A,'Detalhamento - G200'!B:B,0) -> MANUTENÇÃO DE CANTEIRO | F59: 92011 | G59: 5045 | H59: NF MATERIAL | I59: 46113 | J59: 46143 | K59: 26.473.203/0001-99 | L59: LITORAL TINTAS COMERCIO MATERIAIS DE CONTRUÇÃO | M59: 795 | N59: 0 | O59: 0 | P59: 0 | Q59: 0 | S59: =M59-SUM(N59:Q59) -> 795 | T59: =N59+S59 -> 795 | V59: PPC/26969 | W59: SEM CONTRATO
B60: 0010 | D60: 2001008001 | E60: =_xlfn.XLOOKUP(D60,'Detalhamento - G200'!A:A,'Detalhamento - G200'!B:B,0) -> MATERIAIS DE COPA E LIMPEZA | F60: 92019 | G60: 368600 | H60: NF MATERIAL | I60: 46113 | J60: 46139 | K60: 11.976.959/0001-83 | L60: FORTPEL COMERCIO DE DESCARTAVEIS LTDA | M60: 1367.3 | N60: 0 | O60: 0 | P60: 0 | Q60: 0 | S60: =M60-SUM(N60:Q60) -> 1367.3 | T60: =N60+S60 -> 1367.3 | V60: PPC/26833 | W60: SEM CONTRATO
B61: 0010 | D61: 1002002001 | E61: =_xlfn.XLOOKUP(D61,'Detalhamento - G200'!A:A,'Detalhamento - G200'!B:B,0) -> FUNDAÇÃO | F61: 92031 | G61: 5975 | H61: NF MATERIAL | I61: 46112 | J61: 46142 | K61: 25.319.662/0001-50 | L61: MIX MADEIREIRA LTDA - ME | M61: 6635 | N61: 0 | O61: 0 | P61: 0 | Q61: 0 | S61: =M61-SUM(N61:Q61) -> 6635 | T61: =N61+S61 -> 6635 | V61: PPC/26993 | W61: SEM CONTRATO
B62: 0013 | D62: 1002002001 | E62: =_xlfn.XLOOKUP(D62,'Detalhamento - G200'!A:A,'Detalhamento - G200'!B:B,0) -> FUNDAÇÃO | F62: 92916/1 | G62: Recibo - Adiantamento 1 | H62: ADIANTAMENTO | SINAL | I62: 46125 | J62: 46136 | K62: 17.469.701/0001-77 | L62: ARCELORMITTAL BRASIL S.A. | M62: 1000000 | N62: 0 | O62: 0 | P62: 0 | Q62: 0 | S62: =M62-SUM(N62:Q62) -> 1000000 | T62: =N62+S62 -> 1000000 | V62: PPC/27483 | W62: SEM CONTRATO
B63: 0014 | D63: 1001001001 | E63: =_xlfn.XLOOKUP(D63,'Detalhamento - G200'!A:A,'Detalhamento - G200'!B:B,0) -> PROJETOS | F63: 93300 | G63: 1343 | H63: NF SERVIÇO | I63: 46134 | J63: 46147 | K63: 28.254.497/0001-93 | L63: DPE ARQUITETURA E ENGENHARIA S/S | M63: 35400 | N63: 2177.1 | O63: 0 | P63: 0 | Q63: 0 | R63: 0 | S63: =M63-SUM(N63:R63) -> 33222.9 | T63: =N63+S63 -> 35400 | V63: CLSF/200-3-001 | W63: CLSF/200-3-001
B64: 0014 | D64: 1001001002 | E64: =_xlfn.XLOOKUP(D64,'Detalhamento - G200'!A:A,'Detalhamento - G200'!B:B,0) -> ENSAIOS E CONSULTORIAS | F64: 93383 | G64: 394 | H64: NF SERVIÇO | I64: 46135 | J64: 46147 | K64: 52.150.027/0001-64 | L64: LCL GEOTECNIA E SONDAGEM LTDA | M64: 32975.32 | N64: 1648.77 | O64: 1648.77 | P64: 0 | Q64: 0 | R64: 0 | S64: =M64-SUM(N64:R64) -> 29677.78 | T64: =N64+S64 -> 31326.55 | V64: CLSF/200-3-014 | W64: CLSF/200-3-014
B65: 0014 | D65: 1001002003 | E65: =_xlfn.XLOOKUP(D65,'Detalhamento - G200'!A:A,'Detalhamento - G200'!B:B,0) -> MOVIMENTAÇÃO DE TERRA | F65: 93320 | G65: 1170 | H65: NF SERVIÇO | I65: 46134 | J65: 46147 | K65: 05.009.846/0001-06 | L65: MAGALHAES JUNIOR LOCACAO E SERVICOS LTDA | M65: 1077971.7 | N65: 71685.12 | O65: 53898.59 | P65: 215594.34 | Q65: 0 | R65: 0 | S65: =M65-SUM(N65:R65) -> 736793.67 | T65: =N65+S65 -> 808478.79 | V65: CLSF/200-3-015 | W65: CLSF/200-3-015
B66: 0014 | D66: 2003001001 | E66: =_xlfn.XLOOKUP(D66,'Detalhamento - G200'!A:A,'Detalhamento - G200'!B:B,0) -> FEE | F66: 93396 | G66: 185 | H66: NF SERVIÇO | I66: 46135 | J66: 46147 | K66: 37.292.522/0001-14 | L66: QPC ENGENHARIA LTDA | M66: 1064825.4 | N66: 53241.27 | O66: 53241.27 | P66: 241657.65 | Q66: 0 | R66: 0 | S66: =M66-SUM(N66:R66) -> 716685.18 | T66: =N66+S66 -> 769926.45 | V66: CLSF/200-3-000 | W66: CLSF/200-3-000
B67: 0014 | D67: 2001025001 | E67: =_xlfn.XLOOKUP(D67,'Detalhamento - G200'!A:A,'Detalhamento - G200'!B:B,0) -> DESPESAS INDIRETAS DE OBRA, CANTEIRO, INSTALAÇÕES PROVISÓRIAS - FATURAMENTO QPC | F67: 93400 | G67: 184 | H67: NF SERVIÇO | I67: 46135 | J67: 46147 | K67: 37.292.522/0001-14 | L67: QPC ENGENHARIA LTDA | M67: 666666.67 | N67: 33333.33 | O67: 0 | P67: 66197.734 | Q67: 0 | R67: 0 | S67: =M67-SUM(N67:R67) -> 567135.61 | T67: =N67+S67 -> 600468.94 | V67: CLSF/200-3-000 | W67: CLSF/200-3-000
B68: 0014 | D68: 2003001001 | E68: =_xlfn.XLOOKUP(D68,'Detalhamento - G200'!A:A,'Detalhamento - G200'!B:B,0) -> FEE | F68: 93400 | G68: 184 | H68: NF SERVIÇO | I68: 46135 | J68: 46147 | K68: 37.292.522/0001-14 | L68: QPC ENGENHARIA LTDA | M68: 88591.82 | N68: 4429.5905 | O68: 0 | P68: 8796.8665 | Q68: 0 | R68: 0 | S68: =M68-SUM(N68:R68) -> 75365.363 | T68: =N68+S68 -> 79794.954 | V68: CLSF/200-3-000 | W68: CLSF/200-3-000
B69: 0014 | D69: 2002001001 | E69: =_xlfn.XLOOKUP(D69,'Detalhamento - G200'!A:A,'Detalhamento - G200'!B:B,0) -> SALÁRIOS, DISSÍDIO/REAJUSTE E AJUDA DE CUSTO | F69: 93402 | G69: 183 | H69: NF SERVIÇO | I69: 46135 | J69: 46147 | K69: 37.292.522/0001-14 | L69: QPC ENGENHARIA LTDA | M69: 2308951.7 | N69: 204339.39 | O69: 0 | P69: 425035.09 | Q69: 0 | R69: 0 | S69: =M69-SUM(N69:R69) -> 1679577.2 | T69: =N69+S69 -> 1883916.6 | V69: CLSF/200-3-000 | W69: CLSF/200-3-000
B70: 0014 | D70: 2003001001 | E70: =_xlfn.XLOOKUP(D70,'Detalhamento - G200'!A:A,'Detalhamento - G200'!B:B,0) -> FEE | F70: 93402 | G70: 183 | H70: NF SERVIÇO | I70: 46135 | J70: 46147 | K70: 37.292.522/0001-14 | L70: QPC ENGENHARIA LTDA | M70: 357237.35 | N70: 31618.336 | O70: 0 | P70: 65767.555 | Q70: 0 | R70: 0 | S70: =M70-SUM(N70:R70) -> 259851.46 | T70: =N70+S70 -> 291469.79 | V70: CLSF/200-3-000 | W70: CLSF/200-3-000
B71: 0014 | D71: 1001002003 | E71: =_xlfn.XLOOKUP(D71,'Detalhamento - G200'!A:A,'Detalhamento - G200'!B:B,0) -> MOVIMENTAÇÃO DE TERRA | F71: 93379 | G71: 255235 | H71: NF MATERIAL | I71: 46127 | J71: 46157 | K71: 13.529.482/0001-13 | L71: TRANSPORTADORA DE DIESEL CAVALO MARINHO LTDA | M71: 1204 | N71: 0 | O71: 0 | P71: 0 | Q71: 0 | R71: 0 | S71: =M71-SUM(N71:R71) -> 1204 | T71: =N71+S71 -> 1204 | V71: PPC/26926 | W71: CLSF/200-3-015
B72: 0014 | D72: 1001002003 | E72: =_xlfn.XLOOKUP(D72,'Detalhamento - G200'!A:A,'Detalhamento - G200'!B:B,0) -> MOVIMENTAÇÃO DE TERRA | F72: 93378 | G72: 255236 | H72: NF MATERIAL | I72: 46127 | J72: 46157 | K72: 13.529.482/0001-13 | L72: TRANSPORTADORA DE DIESEL CAVALO MARINHO LTDA | M72: 1316.32 | N72: 0 | O72: 0 | P72: 0 | Q72: 0 | R72: 0 | S72: =M72-SUM(N72:R72) -> 1316.32 | T72: =N72+S72 -> 1316.32 | V72: PPC/26926 | W72: CLSF/200-3-015
B73: 0014 | D73: 1001002003 | E73: =_xlfn.XLOOKUP(D73,'Detalhamento - G200'!A:A,'Detalhamento - G200'!B:B,0) -> MOVIMENTAÇÃO DE TERRA | F73: 93372 | G73: 255237 | H73: NF MATERIAL | I73: 46127 | J73: 46157 | K73: 13.529.482/0001-13 | L73: TRANSPORTADORA DE DIESEL CAVALO MARINHO LTDA | M73: 46567.45 | N73: 0 | O73: 0 | P73: 0 | Q73: 0 | R73: 0 | S73: =M73-SUM(N73:R73) -> 46567.45 | T73: =N73+S73 -> 46567.45 | V73: PPC/26926 | W73: CLSF/200-3-015
B74: 0014 | D74: 1001002003 | E74: =_xlfn.XLOOKUP(D74,'Detalhamento - G200'!A:A,'Detalhamento - G200'!B:B,0) -> MOVIMENTAÇÃO DE TERRA | F74: 93371 | G74: 255239 | H74: NF MATERIAL | I74: 46127 | J74: 46157 | K74: 13.529.482/0001-13 | L74: TRANSPORTADORA DE DIESEL CAVALO MARINHO LTDA | M74: 28795.26 | N74: 0 | O74: 0 | P74: 0 | Q74: 0 | R74: 0 | S74: =M74-SUM(N74:R74) -> 28795.26 | T74: =N74+S74 -> 28795.26 | V74: PPC/26926 | W74: CLSF/200-3-015
... B79: 0014 | D79: 2001004004 | E79: =_xlfn.XLOOKUP(D79,'Detalhamento - G200'!A:A,'Detalhamento - G200'!B:B,0) -> DIESEL | F79: 93367 | G79: 255243 | H79: NF MATERIAL | I79: 46127 | J79: 46157 | K79: 13.529.482/0001-13 | L79: TRANSPORTADORA DE DIESEL CAVALO MARINHO LTDA | M79: 2410.62 | N79: 0 | O79: 0 | P79: 0 | Q79: 0 | R79: 0 | S79: =M79-SUM(N79:R79) -> 2410.62 | T79: =N79+S79 -> 2410.62 | V79: PPC/27608 | W79: CLSF/200-3-015
B80: 0014 | D80: 1001001001 | E80: =_xlfn.XLOOKUP(D80,'Detalhamento - G200'!A:A,'Detalhamento - G200'!B:B,0) -> PROJETOS | F80: 93248 | G80: 1354 | H80: NF SERVIÇO | I80: 46133 | J80: 05/05/2026 | K80: 28.649.696/0001-09 | L80: REV1 PROJETOS INTEGRADOS LTDA | M80: 4536.68 | N80: 0 | O80: 0 | P80: 0 | Q80: 0 | R80: 0 | S80: =M80-SUM(N80:R80) -> 4536.68 | T80: =N80+S80 -> 4536.68 | V80: CLSF/200-3-006 | W80: CLSF/200-3-006
B81: 0013 | D81: 1002002001 | E81: =_xlfn.XLOOKUP(D81,'Detalhamento - G200'!A:A,'Detalhamento - G200'!B:B,0) -> FUNDAÇÃO | F81: 93025 | G81: Recibo - Adiantamento 1 | H81: ADIANTAMENTO | SINAL | I81: 46128 | K81: 01.000.129/0001 - 62 | L81: FERROPRONTO LTDA | M81: 200000 | N81: 0 | O81: 0 | P81: 0 | Q81: 0 | S81: =M81-SUM(N81:Q81) -> 200000 | T81: =N81+S81 -> 200000 | V81: PPC/27591 | W81: SEM CONTRATO
B82: 0014 | D82: 2001006002 | E82: =_xlfn.XLOOKUP(D82,'Detalhamento - G200'!A:A,'Detalhamento - G200'!B:B,0) -> LIMPA FOSSA | F82: 93776 | G82: 14113 | H82: NF SERVIÇO | I82: 46134 | J82: 46147 | K82: 10.354.589/0001-80 | L82: QUALYSAN LOCACAO DE BENS MOVEIS EIRELI | M82: 51180 | N82: 10056.87 | O82: 0 | P82: 0 | Q82: 0 | R82: 0 | S82: =M82-SUM(N82:R82) -> 41123.13 | T82: =N82+S82 -> 51180 | V82: PPC/27148 | W82: SEM CONTRATO
B83: 0014 | D83: 2001013001 | E83: =_xlfn.XLOOKUP(D83,'Detalhamento - G200'!A:A,'Detalhamento - G200'!B:B,0) -> LOCAÇÃO - SANITÁRIO QUÍMICO | F83: 93637 | G83: 14112 | H83: NF SERVIÇO | I83: 46129 | J83: 46147 | K83: 10.354.589/0001-80 | L83: QUALYSAN LOCACAO DE BENS MOVEIS EIRELI | M83: 766.5 | N83: 142.97 | O83: 0 | P83: 0 | Q83: 0 | R83: 0 | S83: =M83-SUM(N83:R83) -> 623.53 | T83: =N83+S83 -> 766.5 | V83: CLSF/200-3-017 | W83: CLSF/200-3-017
B84: 0014 | D84: 2001013001 | E84: =_xlfn.XLOOKUP(D84,'Detalhamento - G200'!A:A,'Detalhamento - G200'!B:B,0) -> LOCAÇÃO - SANITÁRIO QUÍMICO | F84: 92789 | G84: 14080 | H84: NF SERVIÇO | I84: 46125 | J84: 46147 | K84: 10.354.589/0001-80 | L84: QUALYSAN LOCACAO DE BENS MOVEIS EIRELI | M84: 4343.5 | N84: 0 | O84: 0 | P84: 0 | Q84: 0 | R84: 0 | S84: =M84-SUM(N84:R84) -> 4343.5 | T84: =N84+S84 -> 4343.5 | V84: CLSF/200-3-017 | W84: CLSF/200-3-017
B85: 0014 | D85: 2001013001 | E85: =_xlfn.XLOOKUP(D85,'Detalhamento - G200'!A:A,'Detalhamento - G200'!B:B,0) -> LOCAÇÃO - SANITÁRIO QUÍMICO | F85: 92787 | G85: 14079 | H85: NF SERVIÇO | I85: 46125 | J85: 46147 | K85: 10.354.589/0001-80 | L85: QUALYSAN LOCACAO DE BENS MOVEIS EIRELI | M85: 3629.5 | N85: 0 | O85: 0 | P85: 0 | Q85: 0 | R85: 0 | S85: =M85-SUM(N85:R85) -> 3629.5 | T85: =N85+S85 -> 3629.5 | V85: CLSF/200-3-017 | W85: CLSF/200-3-017
B86: 0014 | D86: 2001001002 | E86: =_xlfn.XLOOKUP(D86,'Detalhamento - G200'!A:A,'Detalhamento - G200'!B:B,0) -> IMPLANTAÇÃO DE CANTEIRO - ELETRICA | F86: 93327 | G86: 630 | H86: NF SERVIÇO | I86: 46132 | J86: 46147 | K86: 50.364.288/0001-51 | L86: FF INFRA E ENGENHARIA LTDA | M86: 47439.69 | N86: 7590.34 | O86: 711.59 | P86: 0 | Q86: 0 | R86: 0 | S86: =M86-SUM(N86:R86) -> 39137.76 | T86: =N86+S86 -> 46728.1 | V86: CLSF/200-3-018 | W86: CLSF/200-3-018
B87: 0014 | D87: 1001002006 | E87: =_xlfn.XLOOKUP(D87,'Detalhamento - G200'!A:A,'Detalhamento - G200'!B:B,0) -> CONTENÇÕES | F87: 93311 | G87: 29309 | H87: NF MATERIAL | I87: 46132 | J87: 46162 | K87: 03.772.834/0001-03 | L87: TRAPICHE MINERACAO LTDA | M87: 115500 | N87: 0 | O87: 0 | P87: 0 | Q87: 0 | R87: 0 | S87: =M87-SUM(N87:R87) -> 115500 | T87: =N87+S87 -> 115500 | V87: PPC/26652 | W87: CLSF/200-3-039
B88: 0014 | D88: 1001001002 | E88: =_xlfn.XLOOKUP(D88,'Detalhamento - G200'!A:A,'Detalhamento - G200'!B:B,0) -> ENSAIOS E CONSULTORIAS | F88: 93298 | G88: 762 | H88: NF SERVIÇO | I88: 46134 | J88: 46147 | K88: 26.011.548/0001-20 | L88: GEO2 ENGENHARIA LTDA | M88: 23373.2 | N88: 1168.66 | O88: 0 | P88: 0 | Q88: 0 | R88: 0 | S88: =M88-SUM(N88:R88) -> 22204.54 | T88: =N88+S88 -> 23373.2 | V88: CLSF/200-3-016 | W88: CLSF/200-3-016
B89: 0014 | D89: 1001001002 | E89: =_xlfn.XLOOKUP(D89,'Detalhamento - G200'!A:A,'Detalhamento - G200'!B:B,0) -> ENSAIOS E CONSULTORIAS | F89: 92959 | G89: 754 | H89: NF SERVIÇO | I89: 46127 | J89: 46147 | K89: 26.011.548/0001-20 | L89: GEO2 ENGENHARIA LTDA | M89: 9010.8 | N89: 0 | O89: 450.54 | P89: 0 | Q89: 0 | R89: 0 | S89: =M89-SUM(N89:R89) -> 8560.26 | T89: =N89+S89 -> 8560.26 | V89: CLSF/200-3-016 | W89: CLSF/200-3-016
B90: 0014 | D90: 2001006013 | E90: =_xlfn.XLOOKUP(D90,'Detalhamento - G200'!A:A,'Detalhamento - G200'!B:B,0) -> BIG BAG | F90: 93294 | G90: 113819 | H90: NF MATERIAL | I90: 46125 | J90: 46155 | K90: 33.831.108/0001-85 | L90: OMEGA FERRAMENTAS E MAQUINAS LTDA | M90: 2813.3 | N90: 0 | O90: 0 | P90: 0 | Q90: 0 | R90: 0 | S90: =M90-SUM(N90:R90) -> 2813.3 | T90: =N90+S90 -> 2813.3 | V90: PPC/27127 | W90: SEM CONTRATO
B91: 0014 | D91: 2001002001 | E91: =_xlfn.XLOOKUP(D91,'Detalhamento - G200'!A:A,'Detalhamento - G200'!B:B,0) -> SEGURANÇA PATRIMONIAL - VIGILÂNCIA | F91: 93204 | G91: 67 | H91: NF SERVIÇO | I91: 46132 | J91: 46147 | K91: 56.994.417/0001-71 | L91: BOME EMPREENDIMENTOS E SERVIÇOS LTDA | M91: 31042.04 | N91: 4938.78 | O91: 1552.1 | P91: 0 | Q91: 0 | R91: 0 | S91: =M91-SUM(N91:R91) -> 24551.16 | T91: =N91+S91 -> 29489.94 | V91: CLSF/200-3-024 | W91: CLSF/200-3-024
B92: 0014 | D92: 1001001002 | E92: =_xlfn.XLOOKUP(D92,'Detalhamento - G200'!A:A,'Detalhamento - G200'!B:B,0) -> ENSAIOS E CONSULTORIAS | F92: 92977 | G92: 2729 | H92: NF SERVIÇO | I92: 46127 | J92: 46147 | K92: 10.235.085/0001-40 | L92: SOLOBAHIA ENGENHARIA E TECNOLOGIA LTDA | M92: 8780.25 | N92: 978.99 | O92: 439.01 | P92: 0 | Q92: 0 | R92: 0 | S92: =M92-SUM(N92:R92) -> 7362.25 | T92: =N92+S92 -> 8341.24 | V92: CLSF/200-3-022 | W92: CLSF/200-3-022
B93: 0014 | D93: 1001001002 | E93: =_xlfn.XLOOKUP(D93,'Detalhamento - G200'!A:A,'Detalhamento - G200'!B:B,0) -> ENSAIOS E CONSULTORIAS | F93: 93159 | G93: 2739 | H93: NF SERVIÇO | I93: 46129 | J93: 46147 | K93: 10.235.085/0001-40 | L93: SOLOBAHIA ENGENHARIA E TECNOLOGIA LTDA | M93: 30691 | N93: 3422.04 | O93: 1580.55 | P93: 0 | Q93: 0 | R93: 0 | S93: =M93-SUM(N93:R93) -> 25688.41 | T93: =N93+S93 -> 29110.45 | V93: CLSF/200-3-022 | W93: CLSF/200-3-022
... B165: 0004-G200-2025 | D165: 1001002002 | E165: =_xlfn.XLOOKUP(D165,'Detalhamento - G200'!A:A,'Detalhamento - G200'!B:B,0) -> MOVIMENTO DE TERRA - ESCOPO MÍNIMO | F165: 92707 | G165: 1410 | H165: NF SERVIÇO | I165: 45950 | J165: 45959 | K165: 54.290.200/0001-55 | L165: TERRAM ENGENHARIA DE INFRAESTRURA S/A | M165: 1585705.4 | N165: 105449.41 | O165: 0 | P165: 1480256 | Q165: 0 | R165: 0 | S165: =M165-SUM(N165:R165) -> 0 | T165: =N165+S165 -> 105449.41 | V165: PPC/27440 | W165: SEM CONTRATO
B166: SEM ROMANEIO-G200-2025 | D166: 1001002002 | E166: =_xlfn.XLOOKUP(D166,'Detalhamento - G200'!A:A,'Detalhamento - G200'!B:B,0) -> MOVIMENTO DE TERRA - ESCOPO MÍNIMO | F166: 92707 | G166: ADIANTAMENTO | H166: ADIANTAMENTO | SINAL | I166: 45950 | J166: 45959 | K166: 54.290.200/0001-55 | L166: TERRAM ENGENHARIA DE INFRAESTRURA S/A | M166: 1480256 | N166: 0 | O166: 0 | P166: 0 | Q166: 0 | R166: 0 | S166: =M166-SUM(N166:R166) -> 1480256 | T166: =N166+S166 -> 1480256 | V166: PPC/27440 | W166: SEM CONTRATO
B167: 0004-G200-2025 | D167: 1001002002 | E167: =_xlfn.XLOOKUP(D167,'Detalhamento - G200'!A:A,'Detalhamento - G200'!B:B,0) -> MOVIMENTO DE TERRA - ESCOPO MÍNIMO | G167: ADIANTAMENTO | H167: ADIANTAMENTO | SINAL | J167: 45898 | K167: 54.290.200/0001-55 | L167: TERRAM ENGENHARIA DE INFRAESTRURA S/A | M167: 2848296.3 | N167: 0 | O167: 0 | P167: 0 | Q167: 0 | R167: 0 | S167: =M167-SUM(N167:R167) -> 2848296.3 | T167: =N167+S167 -> 2848296.3 | V167: PPC/27440 | W167: SEM CONTRATO
B168: 0015 | D168: 1001003002 | E168: =_xlfn.XLOOKUP(D168,'Detalhamento - G200'!A:A,'Detalhamento - G200'!B:B,0) -> SUPERESTRUTURA GALPÃO | F168: 92616 | G168: ADIANTAMENTO | H168: ADIANTAMENTO | SINAL | I168: 46125 | J168: 46142 | K168: 01.301.612/0005-00 | L168: T & A CONSTRUCAO PRE-FABRICADA S/A | M168: 20527832 | N168: 0 | O168: 0 | P168: 0 | Q168: 0 | R168: 0 | S168: =M168-SUM(N168:R168) -> 20527832 | T168: =N168+S168 -> 20527832 | V168: CLSF/200-3-033 | W168: CLSF/200-3-033
B169: 0015 | D169: 1001003002 | E169: =_xlfn.XLOOKUP(D169,'Detalhamento - G200'!A:A,'Detalhamento - G200'!B:B,0) -> SUPERESTRUTURA GALPÃO | F169: 92618 | G169: 7264 | H169: ADIANTAMENTO | FATURAMENTO FUTURO | I169: 46125 | J169: 46142 | K169: 33.871.336/0002-60 | L169: RÓTULA METALURGICA LTDA | M169: 18027521 | N169: 0 | O169: 0 | P169: 0 | Q169: 0 | R169: 0 | S169: =M169-SUM(N169:R169) -> 18027521 | T169: =N169+S169 -> 18027521 | V169: CLSF/200-3-032 | W169: CLSF/200-3-032
B170: 0015 | D170: 1001005001 | E170: =_xlfn.XLOOKUP(D170,'Detalhamento - G200'!A:A,'Detalhamento - G200'!B:B,0) -> ELETRICA, HIDRÁULICA E COMBATE A INCÊNDIO - MEP | F170: 92620 | G170: ADIANTAMENTO | H170: ADIANTAMENTO | SINAL | I170: 46125 | J170: 46142 | K170: 15.638.181/0001-53 | L170: ARTEMP ENGENHARIA DE INSTALAÇÕES LTDA | M170: 9070763.3 | N170: 0 | O170: 0 | P170: 0 | Q170: 0 | R170: 0 | S170: =M170-SUM(N170:R170) -> 9070763.3 | T170: =N170+S170 -> 9070763.3 | V170: CLSF/200-3-034 | W170: CLSF/200-3-034
B171: 0015 | D171: 1001002006 | E171: =_xlfn.XLOOKUP(D171,'Detalhamento - G200'!A:A,'Detalhamento - G200'!B:B,0) -> CONTENÇÕES | F171: 92798 | G171: ADIANTAMENTO | H171: ADIANTAMENTO | SINAL | I171: 46126 | J171: 46142 | K171: 60.013.306/0001-04 | L171: VOC ENGENHARIA E CONSTRUCAO LTDA | M171: 393610.92 | N171: 0 | O171: 0 | P171: 0 | Q171: 0 | R171: 0 | S171: =M171-SUM(N171:R171) -> 393610.92 | T171: =N171+S171 -> 393610.92 | V171: CLSF/ 200-3-039 | W171: CLSF/ 200-3-039
B172: 0015 | D172: 1001003010 | E172: =_xlfn.XLOOKUP(D172,'Detalhamento - G200'!A:A,'Detalhamento - G200'!B:B,0) -> SERRALHERIA GALPÃO | F172: 93091 | G172: 2951 | H172: ADIANTAMENTO | FATURAMENTO FUTURO | I172: 46129 | J172: 46142 | K172: 09.254.454/0001-63 | L172: SOTEC FABRICACAO DE ESTRUTURAS METALICAS E SERVICOS LTDA | M172: 115550.02 | N172: 0 | O172: 0 | P172: 0 | Q172: 0 | R172: 0 | S172: =M172-SUM(N172:R172) -> 115550.02 | T172: =N172+S172 -> 115550.02 | V172: CLSF/200-3-038 | W172: CLSF/200-3-038
B173: 0015 | D173: 1002002004 | E173: =_xlfn.XLOOKUP(D173,'Detalhamento - G200'!A:A,'Detalhamento - G200'!B:B,0) -> SERRALHERIA | F173: 93091 | G173: 2951 | H173: ADIANTAMENTO | FATURAMENTO FUTURO | I173: 46129 | J173: 46142 | K173: 09.254.454/0001-63 | L173: SOTEC FABRICACAO DE ESTRUTURAS METALICAS E SERVICOS LTDA | M173: 319750.06 | N173: 0 | O173: 0 | P173: 0 | Q173: 0 | R173: 0 | S173: =M173-SUM(N173:R173) -> 319750.06 | T173: =N173+S173 -> 319750.06 | V173: CLSF/200-3-038 | W173: CLSF/200-3-038
B174: 0015 | D174: 1003005001 | E174: =_xlfn.XLOOKUP(D174,'Detalhamento - G200'!A:A,'Detalhamento - G200'!B:B,0) -> SERVIÇO CIVIL | F174: 93091 | G174: 2951 | H174: ADIANTAMENTO | FATURAMENTO FUTURO | I174: 46129 | J174: 46142 | K174: 09.254.454/0001-63 | L174: SOTEC FABRICACAO DE ESTRUTURAS METALICAS E SERVICOS LTDA | M174: 64700.01 | N174: 0 | O174: 0 | P174: 0 | Q174: 0 | R174: 0 | S174: =M174-SUM(N174:R174) -> 64700.01 | T174: =N174+S174 -> 64700.01 | V174: CLSF/200-3-038 | W174: CLSF/200-3-038
B175: 0016 | D175: 1001005002 | E175: =_xlfn.XLOOKUP(D175,'Detalhamento - G200'!A:A,'Detalhamento - G200'!B:B,0) -> SISTEMA DE AR CONDICIONADO E EXAUSTÃO | F175: 93631 | G175: ADIANTAMENTO | H175: ADIANTAMENTO | SINAL | I175: 46139 | J175: 46142 | K175: 14.100.265/0001-76 | L175: ARTEMP ENGENHARIA TÉRMICA LTDA | M175: 42160.88 | N175: 0 | O175: 0 | P175: 0 | Q175: 0 | R175: 0 | S175: =M175-SUM(N175:R175) -> 42160.88 | T175: =N175+S175 -> 42160.88 | V175: CLSF/200-3-042 | W175: CLSF/200-3-042
B176: 0016 | D176: 1003001001 | E176: =_xlfn.XLOOKUP(D176,'Detalhamento - G200'!A:A,'Detalhamento - G200'!B:B,0) -> EQUIPAMENTO | F176: 93631 | G176: ADIANTAMENTO | H176: ADIANTAMENTO | SINAL | I176: 46139 | J176: 46142 | K176: 14.100.265/0001-76 | L176: ARTEMP ENGENHARIA TÉRMICA LTDA | M176: 1992187.9 | N176: 0 | O176: 0 | P176: 0 | Q176: 0 | R176: 0 | S176: =M176-SUM(N176:R176) -> 1992187.9 | T176: =N176+S176 -> 1992187.9 | V176: CLSF/200-3-042 | W176: CLSF/200-3-042
B177: 0016 | D177: 1003002001 | E177: =_xlfn.XLOOKUP(D177,'Detalhamento - G200'!A:A,'Detalhamento - G200'!B:B,0) -> CAVALETES HIDRÁULICOS E VÁLVULAS | F177: 93631 | G177: ADIANTAMENTO | H177: ADIANTAMENTO | SINAL | I177: 46139 | J177: 46142 | K177: 14.100.265/0001-76 | L177: ARTEMP ENGENHARIA TÉRMICA LTDA | M177: 131065.24 | N177: 0 | O177: 0 | P177: 0 | Q177: 0 | R177: 0 | S177: =M177-SUM(N177:R177) -> 131065.24 | T177: =N177+S177 -> 131065.24 | V177: CLSF/200-3-042 | W177: CLSF/200-3-042
B178: 0016 | D178: 1003002002 | E178: =_xlfn.XLOOKUP(D178,'Detalhamento - G200'!A:A,'Detalhamento - G200'!B:B,0) -> REDE HIDRÁULICA | F178: 93631 | G178: ADIANTAMENTO | H178: ADIANTAMENTO | SINAL | I178: 46139 | J178: 46142 | K178: 14.100.265/0001-76 | L178: ARTEMP ENGENHARIA TÉRMICA LTDA | M178: 496972.38 | N178: 0 | O178: 0 | P178: 0 | Q178: 0 | R178: 0 | S178: =M178-SUM(N178:R178) -> 496972.38 | T178: =N178+S178 -> 496972.38 | V178: CLSF/200-3-042 | W178: CLSF/200-3-042
B179: 0016 | D179: 1003003001 | E179: =_xlfn.XLOOKUP(D179,'Detalhamento - G200'!A:A,'Detalhamento - G200'!B:B,0) -> QUADROS ELÉTRICOS E AUTOMAÇÃO | F179: 93631 | G179: ADIANTAMENTO | H179: ADIANTAMENTO | SINAL | I179: 46139 | J179: 46142 | K179: 14.100.265/0001-76 | L179: ARTEMP ENGENHARIA TÉRMICA LTDA | M179: 541295.79 | N179: 0 | O179: 0 | P179: 0 | Q179: 0 | R179: 0 | S179: =M179-SUM(N179:R179) -> 541295.79 | T179: =N179+S179 -> 541295.79 | V179: CLSF/200-3-042 | W179: CLSF/200-3-042
B180: 0016 | D180: 1003003002 | E180: =_xlfn.XLOOKUP(D180,'Detalhamento - G200'!A:A,'Detalhamento - G200'!B:B,0) -> INTERLIGAÇÕES ELÉTRICAS | F180: 93631 | G180: ADIANTAMENTO | H180: ADIANTAMENTO | SINAL | I180: 46139 | J180: 46142 | K180: 14.100.265/0001-76 | L180: ARTEMP ENGENHARIA TÉRMICA LTDA | M180: 688245.54 | N180: 0 | O180: 0 | P180: 0 | Q180: 0 | R180: 0 | S180: =M180-SUM(N180:R180) -> 688245.54 | T180: =N180+S180 -> 688245.54 | V180: CLSF/200-3-042 | W180: CLSF/200-3-042
...

Sheet Detalhamento - Sub69
A1: G200 – REPORT SEMANAL DE CUSTOS - DETALHAMENTO Data de Emissão: 30/01/2026 Versão: 00
A2: CÓDIGO | B2: DESCRIÇÃO | C2: VALOR ORÇADO | D2: VALOR COMPROMETIDO | E2: SALDO DO COMPROMETIDO | F2: VALOR REALIZADO | G2: PROJEÇÕES | H2: TENDÊNCIA | I2: VARIAÇÃO | K2: OBSERVAÇÕES
A3: 0 | B3: TOTAL OBRA | C3: =SUBTOTAL(9,C4:C152) -> 25805974 | D3: =SUBTOTAL(9,D4:D152) -> 27884465 | E3: =SUBTOTAL(9,E4:E152) -> -2078490.2 | F3: =SUBTOTAL(9,F4:F152) -> 3930874.8 | G3: =SUBTOTAL(9,G4:G152) -> -2078490.2 | H3: =SUBTOTAL(9,H4:H152) -> 25805974 | I3: =SUBTOTAL(9,I4:I152) -> 0
A4: 1 | B4: DESPESAS DIRETAS | C4: =SUBTOTAL(9,C5:C8) -> 20038494 | D4: =SUBTOTAL(9,D5:D8) -> 23500000 | E4: =SUBTOTAL(9,E5:E8) -> -3461506 | F4: =SUBTOTAL(9,F5:F8) -> 2590000 | G4: =SUBTOTAL(9,G5:G8) -> -3461506 | H4: =SUBTOTAL(9,H5:H8) -> 20038494 | I4: =SUBTOTAL(9,I5:I8) -> 0
A5: 1001 | B5: SUBESTAÇÃO 69KV | C5: =SUBTOTAL(9,C6:C8) -> 20038494 | D5: =SUBTOTAL(9,D6:D8) -> 23500000 | E5: =SUBTOTAL(9,E6:E8) -> -3461506 | F5: =SUBTOTAL(9,F6:F8) -> 2590000 | G5: =SUBTOTAL(9,G6:G8) -> -3461506 | H5: =SUBTOTAL(9,H6:H8) -> 20038494 | I5: =SUBTOTAL(9,I6:I8) -> 0
A6: 1001001 | B6: SERVIÇOS DIRETOS | C6: =SUBTOTAL(9,C7:C8) -> 20038494 | D6: =SUBTOTAL(9,D7:D8) -> 23500000 | E6: =SUBTOTAL(9,E7:E8) -> -3461506 | F6: =SUBTOTAL(9,F7:F8) -> 2590000 | G6: =SUBTOTAL(9,G7:G8) -> -3461506 | H6: =SUBTOTAL(9,H7:H8) -> 20038494 | I6: =SUBTOTAL(9,I7:I8) -> 0
A7: 1001001001 | B7: CONSTRUÇÃO SUBESTAÇÃO DE 69 | ENTREGUE 1 TRAFO DE 10MVA | C7: 16332396 | D7: =SUMIF('Contratos - Sub69'!D:D,'Detalhamento - Sub69'!A7,'Contratos - Sub69'!I:I)+SUMIF('Pedidos - Sub69'!D:D,'Detalhamento - Sub69'!A7,'Pedidos - Sub69'!G:G) -> 3700000 | E7: =C7-D7 -> 12632396 | F7: =SUMIF('Notas fiscais - Sub69'!D:D,'Detalhamento - Sub69'!A7,'Notas fiscais - Sub69'!R:R) -> 2590000 | G7: =VLOOKUP(A7,'Projeções - Sub69'!B:F,5) -> 12632396 | H7: =D7+G7 -> 16332396 | I7: =C7-H7 -> 0
A8: 1001001002 | B8: LINHA DE DISTRIBUIÇÃO 69 KV COTEGIPE - CAMAÇARI - SEC SIMÕES FILHO | C8: 3706098.5 | D8: =SUMIF('Contratos - Sub69'!D:D,'Detalhamento - Sub69'!A8,'Contratos - Sub69'!I:I)+SUMIF('Pedidos - Sub69'!D:D,'Detalhamento - Sub69'!A8,'Pedidos - Sub69'!G:G) -> 19800000 | E8: =C8-D8 -> -16093902 | F8: =SUMIF('Notas fiscais - Sub69'!D:D,'Detalhamento - Sub69'!A8,'Notas fiscais - Sub69'!R:R) -> 0 | G8: =VLOOKUP(A8,'Projeções - Sub69'!B:F,5) -> -16093902 | H8: =D8+G8 -> 3706098.5 | I8: =C8-H8 -> 0
A9: 2 | B9: BDI | C9: =SUBTOTAL(9,C10:C152) -> 5767480.5 | D9: =SUBTOTAL(9,D10:D152) -> 4384464.7 | E9: =SUBTOTAL(9,E10:E152) -> 1383015.9 | F9: =SUBTOTAL(9,F10:F152) -> 1340874.8 | G9: =SUBTOTAL(9,G10:G152) -> 1383015.9 | H9: =SUBTOTAL(9,H10:H152) -> 5767480.5 | I9: =SUBTOTAL(9,I10:I152) -> 0
A10: 2001 | B10: CONDIÇÕES GERAIS | C10: =SUBTOTAL(9,C11:C142) -> 1275000 | D10: =SUBTOTAL(9,D11:D142) -> 0 | E10: =SUBTOTAL(9,E11:E142) -> 1275000 | F10: =SUBTOTAL(9,F11:F142) -> 0 | G10: =SUBTOTAL(9,G11:G142) -> 1275000 | H10: =SUBTOTAL(9,H11:H142) -> 1275000 | I10: =SUBTOTAL(9,I11:I142) -> 0
A11: 2001001 | B11: CANTEIRO | C11: =SUBTOTAL(9,C12:C21) -> 0 | D11: =SUBTOTAL(9,D12:D21) -> 0 | E11: =SUBTOTAL(9,E12:E21) -> 0 | F11: =SUBTOTAL(9,F12:F21) -> 0 | G11: =SUBTOTAL(9,G12:G21) -> 0 | H11: =SUBTOTAL(9,H12:H21) -> 0 | I11: =SUBTOTAL(9,I12:I21) -> 0
A12: 2001001001 | B12: BASE DE OPERACIONAL | C12: 0 | D12: =SUMIF('Contratos - Sub69'!D:D,'Detalhamento - Sub69'!A12,'Contratos - Sub69'!I:I)+SUMIF('Pedidos - Sub69'!D:D,'Detalhamento - Sub69'!A12,'Pedidos - Sub69'!G:G) -> 0 | E12: =C12-D12 -> 0 | F12: =SUMIF('Notas fiscais - Sub69'!D:D,'Detalhamento - Sub69'!A12,'Notas fiscais - Sub69'!R:R) -> 0 | G12: =VLOOKUP(A12,'Projeções - Sub69'!B:F,5) -> 0 | H12: =D12+G12 -> 0 | I12: =C12-H12 -> 0
A13: 2001001002 | B13: IMPLANTAÇÃO DE CANTEIRO - ELETRICA | C13: 0 | D13: =SUMIF('Contratos - Sub69'!D:D,'Detalhamento - Sub69'!A13,'Contratos - Sub69'!I:I)+SUMIF('Pedidos - Sub69'!D:D,'Detalhamento - Sub69'!A13,'Pedidos - Sub69'!G:G) -> 0 | E13: =C13-D13 -> 0 | F13: =SUMIF('Notas fiscais - Sub69'!D:D,'Detalhamento - Sub69'!A13,'Notas fiscais - Sub69'!R:R) -> 0 | G13: =VLOOKUP(A13,'Projeções - Sub69'!B:F,5) -> 0 | H13: =D13+G13 -> 0 | I13: =C13-H13 -> 0
A14: 2001001003 | B14: GERADOR BACK-UP | C14: 0 | D14: =SUMIF('Contratos - Sub69'!D:D,'Detalhamento - Sub69'!A14,'Contratos - Sub69'!I:I)+SUMIF('Pedidos - Sub69'!D:D,'Detalhamento - Sub69'!A14,'Pedidos - Sub69'!G:G) -> 0 | E14: =C14-D14 -> 0 | F14: =SUMIF('Notas fiscais - Sub69'!D:D,'Detalhamento - Sub69'!A14,'Notas fiscais - Sub69'!R:R) -> 0 | G14: =VLOOKUP(A14,'Projeções - Sub69'!B:F,5) -> 0 | H14: =D14+G14 -> 0 | I14: =C14-H14 -> 0
A15: 2001001004 | B15: LOCAÇÃO DE CONTAINER | C15: 0 | D15: =SUMIF('Contratos - Sub69'!D:D,'Detalhamento - Sub69'!A15,'Contratos - Sub69'!I:I)+SUMIF('Pedidos - Sub69'!D:D,'Detalhamento - Sub69'!A15,'Pedidos - Sub69'!G:G) -> 0 | E15: =C15-D15 -> 0 | F15: =SUMIF('Notas fiscais - Sub69'!D:D,'Detalhamento - Sub69'!A15,'Notas fiscais - Sub69'!R:R) -> 0 | G15: =VLOOKUP(A15,'Projeções - Sub69'!B:F,5) -> 0 | H15: =D15+G15 -> 0 | I15: =C15-H15 -> 0
A16: 2001001005 | B16: IMPLANTAÇÃO DE CANTEIRO - HIDRÁULICA | C16: 0 | D16: =SUMIF('Contratos - Sub69'!D:D,'Detalhamento - Sub69'!A16,'Contratos - Sub69'!I:I)+SUMIF('Pedidos - Sub69'!D:D,'Detalhamento - Sub69'!A16,'Pedidos - Sub69'!G:G) -> 0 | E16: =C16-D16 -> 0 | F16: =SUMIF('Notas fiscais - Sub69'!D:D,'Detalhamento - Sub69'!A16,'Notas fiscais - Sub69'!R:R) -> 0 | G16: =VLOOKUP(A16,'Projeções - Sub69'!B:F,5) -> 0 | H16: =D16+G16 -> 0 | I16: =C16-H16 -> 0
A17: 2001001006 | B17: IMPLANTAÇÃO DE CANTEIRO - CIVIL | C17: 0 | D17: =SUMIF('Contratos - Sub69'!D:D,'Detalhamento - Sub69'!A17,'Contratos - Sub69'!I:I)+SUMIF('Pedidos - Sub69'!D:D,'Detalhamento - Sub69'!A17,'Pedidos - Sub69'!G:G) -> 0 | E17: =C17-D17 -> 0 | F17: =SUMIF('Notas fiscais - Sub69'!D:D,'Detalhamento - Sub69'!A17,'Notas fiscais - Sub69'!R:R) -> 0 | G17: =VLOOKUP(A17,'Projeções - Sub69'!B:F,5) -> 0 | H17: =D17+G17 -> 0 | I17: =C17-H17 -> 0
A18: 2001001007 | B18: LOCAÇÃO DE TOLDO | C18: 0 | D18: =SUMIF('Contratos - Sub69'!D:D,'Detalhamento - Sub69'!A18,'Contratos - Sub69'!I:I)+SUMIF('Pedidos - Sub69'!D:D,'Detalhamento - Sub69'!A18,'Pedidos - Sub69'!G:G) -> 0 | E18: =C18-D18 -> 0 | F18: =SUMIF('Notas fiscais - Sub69'!D:D,'Detalhamento - Sub69'!A18,'Notas fiscais - Sub69'!R:R) -> 0 | G18: =VLOOKUP(A18,'Projeções - Sub69'!B:F,5) -> 0 | H18: =D18+G18 -> 0 | I18: =C18-H18 -> 0
A19: 2001001008 | B19: MOBILIARIO | C19: 0 | D19: =SUMIF('Contratos - Sub69'!D:D,'Detalhamento - Sub69'!A19,'Contratos - Sub69'!I:I)+SUMIF('Pedidos - Sub69'!D:D,'Detalhamento - Sub69'!A19,'Pedidos - Sub69'!G:G) -> 0 | E19: =C19-D19 -> 0 | F19: =SUMIF('Notas fiscais - Sub69'!D:D,'Detalhamento - Sub69'!A19,'Notas fiscais - Sub69'!R:R) -> 0 | G19: =VLOOKUP(A19,'Projeções - Sub69'!B:F,5) -> 0 | H19: =D19+G19 -> 0 | I19: =C19-H19 -> 0
A20: 2001001009 | B20: LAVA RODAS | C20: 0 | D20: =SUMIF('Contratos - Sub69'!D:D,'Detalhamento - Sub69'!A20,'Contratos - Sub69'!I:I)+SUMIF('Pedidos - Sub69'!D:D,'Detalhamento - Sub69'!A20,'Pedidos - Sub69'!G:G) -> 0 | E20: =C20-D20 -> 0 | F20: =SUMIF('Notas fiscais - Sub69'!D:D,'Detalhamento - Sub69'!A20,'Notas fiscais - Sub69'!R:R) -> 0 | G20: =VLOOKUP(A20,'Projeções - Sub69'!B:F,5) -> 0 | H20: =D20+G20 -> 0 | I20: =C20-H20 -> 0
A21: 2001001010 | B21: MANUTENÇÃO DE CANTEIRO | C21: 0 | D21: =SUMIF('Contratos - Sub69'!D:D,'Detalhamento - Sub69'!A21,'Contratos - Sub69'!I:I)+SUMIF('Pedidos - Sub69'!D:D,'Detalhamento - Sub69'!A21,'Pedidos - Sub69'!G:G) -> 0 | E21: =C21-D21 -> 0 | F21: =SUMIF('Notas fiscais - Sub69'!D:D,'Detalhamento - Sub69'!A21,'Notas fiscais - Sub69'!R:R) -> 0 | G21: =VLOOKUP(A21,'Projeções - Sub69'!B:F,5) -> 0 | H21: =D21+G21 -> 0 | I21: =C21-H21 -> 0
A22: 2001002 | B22: SEGURANÇA PATRIMONIAL | C22: =SUBTOTAL(9,C23:C25) -> 0 | D22: =SUBTOTAL(9,D23:D25) -> 0 | E22: =SUBTOTAL(9,E23:E25) -> 0 | F22: =SUBTOTAL(9,F23:F25) -> 0 | G22: =SUBTOTAL(9,G23:G25) -> 0 | H22: =SUBTOTAL(9,H23:H25) -> 0 | I22: =SUBTOTAL(9,I23:I25) -> 0
A23: 2001002001 | B23: SEGURANÇA PATRIMONIAL - VIGILÂNCIA | C23: 0 | D23: =SUMIF('Contratos - Sub69'!D:D,'Detalhamento - Sub69'!A23,'Contratos - Sub69'!I:I)+SUMIF('Pedidos - Sub69'!D:D,'Detalhamento - Sub69'!A23,'Pedidos - Sub69'!G:G) -> 0 | E23: =C23-D23 -> 0 | F23: =SUMIF('Notas fiscais - Sub69'!D:D,'Detalhamento - Sub69'!A23,'Notas fiscais - Sub69'!R:R) -> 0 | G23: =VLOOKUP(A23,'Projeções - Sub69'!B:F,5) -> 0 | H23: =D23+G23 -> 0 | I23: =C23-H23 -> 0
A24: 2001002002 | B24: MONITORAMENTO TIME LAPSE | C24: 0 | D24: =SUMIF('Contratos - Sub69'!D:D,'Detalhamento - Sub69'!A24,'Contratos - Sub69'!I:I)+SUMIF('Pedidos - Sub69'!D:D,'Detalhamento - Sub69'!A24,'Pedidos - Sub69'!G:G) -> 0 | E24: =C24-D24 -> 0 | F24: =SUMIF('Notas fiscais - Sub69'!D:D,'Detalhamento - Sub69'!A24,'Notas fiscais - Sub69'!R:R) -> 0 | G24: =VLOOKUP(A24,'Projeções - Sub69'!B:F,5) -> 0 | H24: =D24+G24 -> 0 | I24: =C24-H24 -> 0
A25: 2001002003 | B25: CÂMERA DE MONITORAMENTO | C25: 0 | D25: =SUMIF('Contratos - Sub69'!D:D,'Detalhamento - Sub69'!A25,'Contratos - Sub69'!I:I)+SUMIF('Pedidos - Sub69'!D:D,'Detalhamento - Sub69'!A25,'Pedidos - Sub69'!G:G) -> 0 | E25: =C25-D25 -> 0 | F25: =SUMIF('Notas fiscais - Sub69'!D:D,'Detalhamento - Sub69'!A25,'Notas fiscais - Sub69'!R:R) -> 0 | G25: =VLOOKUP(A25,'Projeções - Sub69'!B:F,5) -> 0 | H25: =D25+G25 -> 0 | I25: =C25-H25 -> 0
A26: 2001003 | B26: LOCAÇÃO DE VEÍCULOS | C26: =SUBTOTAL(9,C27:C29) -> 1034300.9 | D26: =SUBTOTAL(9,D27:D29) -> 0 | E26: =SUBTOTAL(9,E27:E29) -> 1034300.9 | F26: =SUBTOTAL(9,F27:F29) -> 0 | G26: =SUBTOTAL(9,G27:G29) -> 1034300.9 | H26: =SUBTOTAL(9,H27:H29) -> 1034300.9 | I26: =SUBTOTAL(9,I27:I29) -> 0
A27: 2001003001 | B27: TRANSPORTE SSA-LSF | C27: 1034300.9 | D27: =SUMIF('Contratos - Sub69'!D:D,'Detalhamento - Sub69'!A27,'Contratos - Sub69'!I:I)+SUMIF('Pedidos - Sub69'!D:D,'Detalhamento - Sub69'!A27,'Pedidos - Sub69'!G:G) -> 0 | E27: =C27-D27 -> 1034300.9 | F27: =SUMIF('Notas fiscais - Sub69'!D:D,'Detalhamento - Sub69'!A27,'Notas fiscais - Sub69'!R:R) -> 0 | G27: =VLOOKUP(A27,'Projeções - Sub69'!B:F,5) -> 1034300.9 | H27: =D27+G27 -> 1034300.9 | I27: =C27-H27 -> 0
A28: 2001003002 | B28: LOCAÇÃO DE CARRO OBRA | C28: 0 | D28: =SUMIF('Contratos - Sub69'!D:D,'Detalhamento - Sub69'!A28,'Contratos - Sub69'!I:I)+SUMIF('Pedidos - Sub69'!D:D,'Detalhamento - Sub69'!A28,'Pedidos - Sub69'!G:G) -> 0 | E28: =C28-D28 -> 0 | F28: =SUMIF('Notas fiscais - Sub69'!D:D,'Detalhamento - Sub69'!A28,'Notas fiscais - Sub69'!R:R) -> 0 | G28: =VLOOKUP(A28,'Projeções - Sub69'!B:F,5) -> 0 | H28: =D28+G28 -> 0 | I28: =C28-H28 -> 0
A29: 2001003003 | B29: GASOLINA CARRO OBRA | C29: 0 | D29: =SUMIF('Contratos - Sub69'!D:D,'Detalhamento - Sub69'!A29,'Contratos - Sub69'!I:I)+SUMIF('Pedidos - Sub69'!D:D,'Detalhamento - Sub69'!A29,'Pedidos - Sub69'!G:G) -> 0 | E29: =C29-D29 -> 0 | F29: =SUMIF('Notas fiscais - Sub69'!D:D,'Detalhamento - Sub69'!A29,'Notas fiscais - Sub69'!R:R) -> 0 | G29: =VLOOKUP(A29,'Projeções - Sub69'!B:F,5) -> 0 | H29: =D29+G29 -> 0 | I29: =C29-H29 -> 0
A30: 2001004 | B30: LOCAÇÃO DE MÁQUINAS | C30: =SUBTOTAL(9,C31:C34) -> 240699.07 | D30: =SUBTOTAL(9,D31:D34) -> 0 | E30: =SUBTOTAL(9,E31:E34) -> 240699.07 | F30: =SUBTOTAL(9,F31:F34) -> 0 | G30: =SUBTOTAL(9,G31:G34) -> 240699.07 | H30: =SUBTOTAL(9,H31:H34) -> 240699.07 | I30: =SUBTOTAL(9,I31:I34) -> 0
A31: 2001004001 | B31: LOCAÇÃO DE MUNCK | C31: 91206.28 | D31: =SUMIF('Contratos - Sub69'!D:D,'Detalhamento - Sub69'!A31,'Contratos - Sub69'!I:I)+SUMIF('Pedidos - Sub69'!D:D,'Detalhamento - Sub69'!A31,'Pedidos - Sub69'!G:G) -> 0 | E31: =C31-D31 -> 91206.28 | F31: =SUMIF('Notas fiscais - Sub69'!D:D,'Detalhamento - Sub69'!A31,'Notas fiscais - Sub69'!R:R) -> 0 | G31: =VLOOKUP(A31,'Projeções - Sub69'!B:F,5) -> 91206.28 | H31: =D31+G31 -> 91206.28 | I31: =C31-H31 -> 0
A32: 2001004002 | B32: LOCAÇÃO DE BOBCAT | C32: 69259.77 | D32: =SUMIF('Contratos - Sub69'!D:D,'Detalhamento - Sub69'!A32,'Contratos - Sub69'!I:I)+SUMIF('Pedidos - Sub69'!D:D,'Detalhamento - Sub69'!A32,'Pedidos - Sub69'!G:G) -> 0 | E32: =C32-D32 -> 69259.77 | F32: =SUMIF('Notas fiscais - Sub69'!D:D,'Detalhamento - Sub69'!A32,'Notas fiscais - Sub69'!R:R) -> 0 | G32: =VLOOKUP(A32,'Projeções - Sub69'!B:F,5) -> 69259.77 | H32: =D32+G32 -> 69259.77 | I32: =C32-H32 -> 0
A33: 2001004003 | B33: LOCAÇÃO DE CAMINHÃO PIPA | C33: 13538.43 | D33: =SUMIF('Contratos - Sub69'!D:D,'Detalhamento - Sub69'!A33,'Contratos - Sub69'!I:I)+SUMIF('Pedidos - Sub69'!D:D,'Detalhamento - Sub69'!A33,'Pedidos - Sub69'!G:G) -> 0 | E33: =C33-D33 -> 13538.43 | F33: =SUMIF('Notas fiscais - Sub69'!D:D,'Detalhamento - Sub69'!A33,'Notas fiscais - Sub69'!R:R) -> 0 | G33: =VLOOKUP(A33,'Projeções - Sub69'!B:F,5) -> 13538.43 | H33: =D33+G33 -> 13538.43 | I33: =C33-H33 -> 0
A34: 2001004004 | B34: DIESEL | C34: 66694.59 | D34: =SUMIF('Contratos - Sub69'!D:D,'Detalhamento - Sub69'!A34,'Contratos - Sub69'!I:I)+SUMIF('Pedidos - Sub69'!D:D,'Detalhamento - Sub69'!A34,'Pedidos - Sub69'!G:G) -> 0 | E34: =C34-D34 -> 66694.59 | F34: =SUMIF('Notas fiscais - Sub69'!D:D,'Detalhamento - Sub69'!A34,'Notas fiscais - Sub69'!R:R) -> 0 | G34: =VLOOKUP(A34,'Projeções - Sub69'!B:F,5) -> 66694.59 | H34: =D34+G34 -> 66694.59 | I34: =C34-H34 -> 0
A35: 2001005 | B35: EPC - EQUIPAMENTOS DE PROTEÇÃO COLETIVA | C35: =SUBTOTAL(9,C36:C37) -> 0 | D35: =SUBTOTAL(9,D36:D37) -> 0 | E35: =SUBTOTAL(9,E36:E37) -> 0 | F35: =SUBTOTAL(9,F36:F37) -> 0 | G35: =SUBTOTAL(9,G36:G37) -> 0 | H35: =SUBTOTAL(9,H36:H37) -> 0 | I35: =SUBTOTAL(9,I36:I37) -> 0
A36: 2001005001 | B36: GUARDA CORPO | C36: 0 | D36: =SUMIF('Contratos - Sub69'!D:D,'Detalhamento - Sub69'!A36,'Contratos - Sub69'!I:I)+SUMIF('Pedidos - Sub69'!D:D,'Detalhamento - Sub69'!A36,'Pedidos - Sub69'!G:G) -> 0 | E36: =C36-D36 -> 0 | F36: =SUMIF('Notas fiscais - Sub69'!D:D,'Detalhamento - Sub69'!A36,'Notas fiscais - Sub69'!R:R) -> 0 | G36: =VLOOKUP(A36,'Projeções - Sub69'!B:F,5) -> 0 | H36: =D36+G36 -> 0 | I36: =C36-H36 -> 0
A37: 2001005002 | B37: EPC GERAL E COMUNICAÇÃO VISUAL | C37: 0 | D37: =SUMIF('Contratos - Sub69'!D:D,'Detalhamento - Sub69'!A37,'Contratos - Sub69'!I:I)+SUMIF('Pedidos - Sub69'!D:D,'Detalhamento - Sub69'!A37,'Pedidos - Sub69'!G:G) -> 0 | E37: =C37-D37 -> 0 | F37: =SUMIF('Notas fiscais - Sub69'!D:D,'Detalhamento - Sub69'!A37,'Notas fiscais - Sub69'!R:R) -> 0 | G37: =VLOOKUP(A37,'Projeções - Sub69'!B:F,5) -> 0 | H37: =D37+G37 -> 0 | I37: =C37-H37 -> 0
A38: 2001006 | B38: MEIO AMBIENTE | C38: =SUBTOTAL(9,C39:C58) -> 0 | D38: =SUBTOTAL(9,D39:D58) -> 0 | E38: =SUBTOTAL(9,E39:E58) -> 0 | F38: =SUBTOTAL(9,F39:F58) -> 0 | G38: =SUBTOTAL(9,G39:G58) -> 0 | H38: =SUBTOTAL(9,H39:H58) -> 0 | I38: =SUBTOTAL(9,I39:I58) -> 0
A39: 2001006001 | B39: DESCARTE DOS RESÍDUOS | C39: 0 | D39: =SUMIF('Contratos - Sub69'!D:D,'Detalhamento - Sub69'!A39,'Contratos - Sub69'!I:I)+SUMIF('Pedidos - Sub69'!D:D,'Detalhamento - Sub69'!A39,'Pedidos - Sub69'!G:G) -> 0 | E39: =C39-D39 -> 0 | F39: =SUMIF('Notas fiscais - Sub69'!D:D,'Detalhamento - Sub69'!A39,'Notas fiscais - Sub69'!R:R) -> 0 | G39: =VLOOKUP(A39,'Projeções - Sub69'!B:F,5) -> 0 | H39: =D39+G39 -> 0 | I39: =C39-H39 -> 0
A40: 2001006002 | B40: LIMPA FOSSA | C40: 0 | D40: =SUMIF('Contratos - Sub69'!D:D,'Detalhamento - Sub69'!A40,'Contratos - Sub69'!I:I)+SUMIF('Pedidos - Sub69'!D:D,'Detalhamento - Sub69'!A40,'Pedidos - Sub69'!G:G) -> 0 | E40: =C40-D40 -> 0 | F40: =SUMIF('Notas fiscais - Sub69'!D:D,'Detalhamento - Sub69'!A40,'Notas fiscais - Sub69'!R:R) -> 0 | G40: =VLOOKUP(A40,'Projeções - Sub69'!B:F,5) -> 0 | H40: =D40+G40 -> 0 | I40: =C40-H40 -> 0
A41: 2001006003 | B41: MONITORAMENTO DE ÁGUA - POÇO E BEBEDOUROS | C41: 0 | D41: =SUMIF('Contratos - Sub69'!D:D,'Detalhamento - Sub69'!A41,'Contratos - Sub69'!I:I)+SUMIF('Pedidos - Sub69'!D:D,'Detalhamento - Sub69'!A41,'Pedidos - Sub69'!G:G) -> 0 | E41: =C41-D41 -> 0 | F41: =SUMIF('Notas fiscais - Sub69'!D:D,'Detalhamento - Sub69'!A41,'Notas fiscais - Sub69'!R:R) -> 0 | G41: =VLOOKUP(A41,'Projeções - Sub69'!B:F,5) -> 0 | H41: =D41+G41 -> 0 | I41: =C41-H41 -> 0
A42: 2001006004 | B42: PROGRAMA DE EDUCAÇÃO AMBIENTAL | C42: 0 | D42: =SUMIF('Contratos - Sub69'!D:D,'Detalhamento - Sub69'!A42,'Contratos - Sub69'!I:I)+SUMIF('Pedidos - Sub69'!D:D,'Detalhamento - Sub69'!A42,'Pedidos - Sub69'!G:G) -> 0 | E42: =C42-D42 -> 0 | F42: =SUMIF('Notas fiscais - Sub69'!D:D,'Detalhamento - Sub69'!A42,'Notas fiscais - Sub69'!R:R) -> 0 | G42: =VLOOKUP(A42,'Projeções - Sub69'!B:F,5) -> 0 | H42: =D42+G42 -> 0 | I42: =C42-H42 -> 0
A43: 2001006005 | B43: RELATÓRIO DE LAIA | C43: 0 | D43: =SUMIF('Contratos - Sub69'!D:D,'Detalhamento - Sub69'!A43,'Contratos - Sub69'!I:I)+SUMIF('Pedidos - Sub69'!D:D,'Detalhamento - Sub69'!A43,'Pedidos - Sub69'!G:G) -> 0 | E43: =C43-D43 -> 0 | F43: =SUMIF('Notas fiscais - Sub69'!D:D,'Detalhamento - Sub69'!A43,'Notas fiscais - Sub69'!R:R) -> 0 | G43: =VLOOKUP(A43,'Projeções - Sub69'!B:F,5) -> 0 | H43: =D43+G43 -> 0 | I43: =C43-H43 -> 0
A44: 2001006006 | B44: BOMBONAS PLÁSTICAS | C44: 0 | D44: =SUMIF('Contratos - Sub69'!D:D,'Detalhamento - Sub69'!A44,'Contratos - Sub69'!I:I)+SUMIF('Pedidos - Sub69'!D:D,'Detalhamento - Sub69'!A44,'Pedidos - Sub69'!G:G) -> 0 | E44: =C44-D44 -> 0 | F44: =SUMIF('Notas fiscais - Sub69'!D:D,'Detalhamento - Sub69'!A44,'Notas fiscais - Sub69'!R:R) -> 0 | G44: =VLOOKUP(A44,'Projeções - Sub69'!B:F,5) -> 0 | H44: =D44+G44 -> 0 | I44: =C44-H44 -> 0
A45: 2001006007 | B45: NOVA ESTAÇÃO METEOROLÓGICA | C45: 0 | D45: =SUMIF('Contratos - Sub69'!D:D,'Detalhamento - Sub69'!A45,'Contratos - Sub69'!I:I)+SUMIF('Pedidos - Sub69'!D:D,'Detalhamento - Sub69'!A45,'Pedidos - Sub69'!G:G) -> 0 | E45: =C45-D45 -> 0 | F45: =SUMIF('Notas fiscais - Sub69'!D:D,'Detalhamento - Sub69'!A45,'Notas fiscais - Sub69'!R:R) -> 0 | G45: =VLOOKUP(A45,'Projeções - Sub69'!B:F,5) -> 0 | H45: =D45+G45 -> 0 | I45: =C45-H45 -> 0
A46: 2001006008 | B46: PLANO DE EMERGÊNCIA AMBIENTAL | C46: 0 | D46: =SUMIF('Contratos - Sub69'!D:D,'Detalhamento - Sub69'!A46,'Contratos - Sub69'!I:I)+SUMIF('Pedidos - Sub69'!D:D,'Detalhamento - Sub69'!A46,'Pedidos - Sub69'!G:G) -> 0 | E46: =C46-D46 -> 0 | F46: =SUMIF('Notas fiscais - Sub69'!D:D,'Detalhamento - Sub69'!A46,'Notas fiscais - Sub69'!R:R) -> 0 | G46: =VLOOKUP(A46,'Projeções - Sub69'!B:F,5) -> 0 | H46: =D46+G46 -> 0 | I46: =C46-H46 -> 0
A47: 2001006009 | B47: PLANO DE GERENCIAMENTO DE RESÍDUOS | C47: 0 | D47: =SUMIF('Contratos - Sub69'!D:D,'Detalhamento - Sub69'!A47,'Contratos - Sub69'!I:I)+SUMIF('Pedidos - Sub69'!D:D,'Detalhamento - Sub69'!A47,'Pedidos - Sub69'!G:G) -> 0 | E47: =C47-D47 -> 0 | F47: =SUMIF('Notas fiscais - Sub69'!D:D,'Detalhamento - Sub69'!A47,'Notas fiscais - Sub69'!R:R) -> 0 | G47: =VLOOKUP(A47,'Projeções - Sub69'!B:F,5) -> 0 | H47: =D47+G47 -> 0 | I47: =C47-H47 -> 0
A48: 2001006010 | B48: KIT CONTENÇÃO VAZAMENTO DE ÓLEO | C48: 0 | D48: =SUMIF('Contratos - Sub69'!D:D,'Detalhamento - Sub69'!A48,'Contratos - Sub69'!I:I)+SUMIF('Pedidos - Sub69'!D:D,'Detalhamento - Sub69'!A48,'Pedidos - Sub69'!G:G) -> 0 | E48: =C48-D48 -> 0 | F48: =SUMIF('Notas fiscais - Sub69'!D:D,'Detalhamento - Sub69'!A48,'Notas fiscais - Sub69'!R:R) -> 0 | G48: =VLOOKUP(A48,'Projeções - Sub69'!B:F,5) -> 0 | H48: =D48+G48 -> 0 | I48: =C48-H48 -> 0
A49: 2001006011 | B49: MONITORAMENTO DE RUIDO / MATERIAL PARTICULADO | C49: 0 | D49: =SUMIF('Contratos - Sub69'!D:D,'Detalhamento - Sub69'!A49,'Contratos - Sub69'!I:I)+SUMIF('Pedidos - Sub69'!D:D,'Detalhamento - Sub69'!A49,'Pedidos - Sub69'!G:G) -> 0 | E49: =C49-D49 -> 0 | F49: =SUMIF('Notas fiscais - Sub69'!D:D,'Detalhamento - Sub69'!A49,'Notas fiscais - Sub69'!R:R) -> 0 | G49: =VLOOKUP(A49,'Projeções - Sub69'!B:F,5) -> 0 | H49: =D49+G49 -> 0 | I49: =C49-H49 -> 0
A50: 2001006012 | B50: DESRATIZAÇÃO | C50: 0 | D50: =SUMIF('Contratos - Sub69'!D:D,'Detalhamento - Sub69'!A50,'Contratos - Sub69'!I:I)+SUMIF('Pedidos - Sub69'!D:D,'Detalhamento - Sub69'!A50,'Pedidos - Sub69'!G:G) -> 0 | E50: =C50-D50 -> 0 | F50: =SUMIF('Notas fiscais - Sub69'!D:D,'Detalhamento - Sub69'!A50,'Notas fiscais - Sub69'!R:R) -> 0 | G50: =VLOOKUP(A50,'Projeções - Sub69'!B:F,5) -> 0 | H50: =D50+G50 -> 0 | I50: =C50-H50 -> 0
